Workbook
Name académico: '(info_t_d_c)'!$BC$3:$BC$199
Name analista_jr.: '(info_t_d_c)'!$AS$3:$AS$199
Name analista_sr.: '(info_t_d_c)'!$AR$3:$AR$199
Name ancho: '(cata_mp)'!$K$4:$K$15855
Name articulo: '(cata_mp)'!$C$4:$C$15855
Name bespoke: '(info_t_d_c)'!$BF$3:$BF$199
Name bespoke_y_desarrollo: '(info_t_d_c)'!$CA$3:$CA$199
Name bespoke_y_desarrollo_costo_de_gasto_indirecto: '(info_t_d_c)'!$FW$3:$FW$199
Name bespoke_y_desarrollo_costo_de_mano_de_obra: '(info_t_d_c)'!$FV$3:$FV$199
Name bespoke_y_desarrollo_costo_de_producto: '(info_t_d_c)'!$FU$3:$FU$199
Name bespoke_y_desarrollo_costos_y_precios: '(info_t_d_c)'!$FT$3:$FT$199
Name bespoke_y_desarrollo_precio_volumen_alto: '(info_t_d_c)'!$FX$3:$FX$199
Name bespoke_y_desarrollo_precio_volumen_bajo: '(info_t_d_c)'!$FZ$3:$FZ$199
Name bespoke_y_desarrollo_precio_volumen_intermedio: '(info_t_d_c)'!$FY$3:$FY$199
Name calendario: "Complemento 4"
Name cantidad_máxima_de_artículos: '(info_t_d_c)'!$AV$3:$AV$199
Name clave_comercial: '(cata_mp)'!$M$4:$M$15855
Name co_creación: '(info_t_d_c)'!$AG$3:$AG$22
Name co_creación_estratégica: '(info_t_d_c)'!$BZ$3:$BZ$199
Name co_creación_estratégica_costo_de_gasto_indirecto: '(info_t_d_c)'!$FP$3:$FP$199
Name co_creación_estratégica_costo_de_mano_de_obra: '(info_t_d_c)'!$FO$3:$FO$199
Name co_creación_estratégica_costo_de_producto: '(info_t_d_c)'!$FN$3:$FN$199
Name co_creación_estratégica_costos_y_precios: '(info_t_d_c)'!$FM$3:$FM$199
Name co_creación_estratégica_precio_volumen_alto: '(info_t_d_c)'!$FQ$3:$FQ$199
Name co_creación_estratégica_precio_volumen_bajo: '(info_t_d_c)'!$FS$3:$FS$199
Name co_creación_estratégica_precio_volumen_intermedio: '(info_t_d_c)'!$FR$3:$FR$199
Name comercial: '(info_t_d_c)'!$AY$3:$AY$199
Name compra_de_dólares_mxn: '(info_t_d_c)'!$CG$3:$CG$199
Name contabilidad_por_tipo_de_venta: '(info_t_d_c)'!$CF$3:$CF$10
Name corporativo: '(info_t_d_c)'!$AX$3:$AX$199
Name corto_contable: '(info_t_d_c)'!$H$3:$H$16
Name corto_de_tipo: '(info_t_d_c)'!$F$3:$F$11
Name corto_porcentaje: '(info_t_d_c)'!$I$3:$I$16
Name cos_fab: '(info_t_d_c)'!$I$6
Name cos_gas_ind: '(info_t_d_c)'!$I$5
Name cos_man_obr: '(info_t_d_c)'!$I$4
Name cos_mat: '(info_t_d_c)'!$I$3
Name costo_por_minuto: '(info_t_d_c)'!$AB$3:$AB$12
Name costo_última_compra: '(cata_mp)'!$I$4:$I$15855
Name costos_precios_y_descuentos: 'REG-DCC-IDP-032 (t_d_p)'!$D$28
Name departamento: '(info_t_d_c)'!$AE$3:$AE$34
Name des_com: '(info_t_d_c)'!$I$14
Name des_dir: '(info_t_d_c)'!$I$15
Name des_dis: '(info_t_d_c)'!$I$16
Name desarrollo: '(cata_mp)'!$L$4:$L$15855
Name descripción: '(cata_mp)'!$D$4:$D$15855
Name descripción_de_servicio_de_maquila: '(info_t_d_c)'!$AA$3:$AA$12
Name descripción_de_servicio_por_ganchos_en_tren_de_pintura: '(info_t_d_c)'!$AA$3:$AA$166
Name detalle_de_empaque_embalaje: '(info_t_d_c)'!$U$3:$U$13
Name detalle_de_entrega_trasporte_instalación: '(info_t_d_c)'!$X$3:$X$16
Name detalle_empaque_embalaje: 'REG-DCC-IDP-032 (t_d_p)'!$E$16
Name detalle_entrega_trasporte_instalación: 'REG-DCC-IDP-032 (t_d_p)'!$E$18
Name días_asignados: '(info_t_d_c)'!$AU$3:$AU$199
Name días_avilés_de_tabla: '(info_t_d_c)'!$L$3:$L$8
Name dificultad_de_task: '(info_t_d_c)'!$AT$3:$AT$199
Name dirección: '(info_t_d_c)'!$AC$3:$AC$11
Name dirección_co_creación_costo_de_gasto_indirecto: '(info_t_d_c)'!$GN$3:$GN$8
Name dirección_co_creación_costo_de_mano_de_obra: '(info_t_d_c)'!$GM$3:$GM$8
Name dirección_co_creación_costo_de_producto: '(info_t_d_c)'!$GL$3:$GL$8
Name dirección_co_creación_costos_y_precio: '(info_t_d_c)'!$GK$3:$GK$8

Sheet REG-DCC-IDP-032 (t_d_p)
C1: 46204 | D1: solicitud de tabla de comparación: | E1: {=MID(CELL("nombrearchivo"),FIND("[",CELL("nombrearchivo"))+1,FIND("]",CELL("nombrearchivo"))-FIND("[",CELL("nombrearchivo"))-1)} -> C-CO-516R Copete abatible de cabecera.xlsx
D3: fecha: | E3: solicita:
D4: 46248 | E4: =IFERROR(VLOOKUP($D$8,departamento:responsable,2,0),"") -> pedro_r.
D5: fecha_requerida: | E5: n°_de_días_propuestos
D6: 46248 | E6: =IFERROR(NETWORKDAYS.INTL(D4,D6,1),"") -> 1
D7: departamento: | E7: dificultad_de_task
D8: proyectos_vonhaucke | E8: =IFERROR(VLOOKUP($D$16,tipo_de_task:cantidad_máxima_de_artículos,5,0),"") -> intermedio_con_clave_desarrollo_información | H8: {=IFERROR((TRANSPOSE(INDIRECT($G$8))),"")}
D9: sector_de_venta | E9: diseño
D10: corporativo | E10: =IFERROR(VLOOKUP($D$20,tipo_de_línea:diseño,2,0),"") -> diseño_del_cliente
D11: tipo_de_venta | E11: moneda
D12: tradicional | E12: =IFERROR(VLOOKUP($D$12,tipo_de_venta:moneda,2,0),"") -> mxn
D13: n°_de_artículos | E13: contabilidad_por_tipo_de_venta
D14: 1 | E14: =IFERROR(VLOOKUP($D$12,tipo_de_venta:contabilidad_por_tipo_de_venta,4,0),"") -> venta_tradicional_costos_precios_y_descuentos
D15: tabla_requerida | E15: detalle_empaque_embalaje
D16: cotización_producto_vonhaucke(s) | E16: =IFERROR(VLOOKUP($D$24,nivel_emp___emb:detalle_de_empaque_embalaje,2,0),"") -> articulo_empacado_con_espuma_de_1⁄32"_+_cartón_+_película_elástica.
D17: mobiliario | E17: detalle_entrega_trasporte_instalación
D18: mobiliario_de_línea | E18: =IFERROR(VLOOKUP($D$26,nivel_logística:detalle_de_entrega_trasporte_instalación,2,0),"") -> al_cliente_en_vonhaucke_calle_4_no._80._sin_maniobras,_transporte,_instalación.
D19: línea
D20: línea_modificada
D21: =IFERROR(VLOOKUP($D$18,mobiliario:modelo_o_cliente,2,0),"modelo_o_cliente") -> modelo
D22: modulor
D23: tipo_empaque_embalaje
D24: emp_jgo_1_unitario_básico
D25: tipo_entrega_trasporte_instalación
D26: ent_1_cliente_vonhaucke
D27: costos_precios_y_descuentos
D28: standard_line_costos_precios_y_descuentos
D29: {=IFERROR((TRANSPOSE(INDIRECT($D$28))),"%")} -> standard_line_costo_de_producto | E29: standard_line_costo_de_mano_de_obra | F29: standard_line_costo_de_gasto_indirecto | G29: standard_line_precio_mínimo | H29: standard_line_precio_comercial | I29: standard_line_descuento_comercial | J29: standard_line_descuento_dirección | K29: standard_line_precio_distribuidor | L29: standard_line_descuento_distribuidor | M29: 0 | N29: 0 | O29: 0 | P29: 0 | Q29: 0 | R29: 0 | S29: 0 | T29: 0 | U29: 0 | V29: 0 | W29: 0 | X29: 0 | Y29: 0 | Z29: 0 | AA29: 0 | AB29: 0 | AC29: 0 | AD29: 0 | AE29: 0 | AF29: 0 | AG29: 0 | AH29: 0 | AI29: 0 | AJ29: 0 | AK29: 0 | AL29: 0 | AM29: 0 | AN29: 0 | AO29: 0 | AP29: 0 | AQ29: 0 | AR29: 0 | AS29: 0 | AT29: 0 | AU29: 0 | AV29: 0 | AW29: 0 | AX29: 0 | AY29: 0 | AZ29: 0 | BA29: 0 | BB29: 0 | BC29: 0 | BD29: 0 | BE29: 0 | BF29: 0 | BG29: 0 | BH29: 0 | BI29: 0 | BJ29: 0 | BK29: 0 | BL29: 0 | BM29: 0 | BN29: 0 | BO29: 0 | BP29: 0 | BQ29: 0 | BR29: 0 | BS29: 0 | BT29: 0 | BU29: 0 | BV29: 0 | BW29: 0 | BX29: 0 | BY29: 0 | BZ29: 0 | CA29: 0 | CB29: 0 | CC29: 0 | CD29: 0 | CE29: 0 | CF29: 0 | CG29: 0 | CH29: 0 | CI29: 0 | CJ29: 0 | CK29: 0 | CL29: 0 | CM29: 0 | CN29: 0 | CO29: 0 | CP29: 0 | CQ29: 0 | CR29: 0 | CS29: 0 | CT29: 0 | CU29: 0 | CV29: 0 | CW29: 0 | CX29: 0 | CY29: 0 | CZ29: 0 | DA29: 0 | DB29: 0 | DC29: 0 | DD29: 0 | DE29: 0 | DF29: 0 | DG29: 0 | DH29: 0 | DI29: 0 | DJ29: 0 | DK29: 0 | DL29: 0 | DM29: 0 | DN29: 0 | DO29: 0 | DP29: 0 | DQ29: 0 | DR29: 0 | DS29: 0 | DT29: 0 | DU29: 0 | DV29: 0 | DW29: 0 | DX29: 0 | DY29: 0 | DZ29: 0 | EA29: 0 | EB29: 0 | EC29: 0 | ED29: 0 | EE29: 0 | EF29: 0 | EG29: 0 | EH29: 0 | EI29: 0 | EJ29: 0 | EK29: 0 | EL29: 0 | EM29: 0 | EN29: 0 | EO29: 0 | EP29: 0 | EQ29: 0 | ER29: 0 | ES29: 0 | ET29: 0 | EU29: 0 | EV29: 0 | EW29: 0 | EX29: 0 | EY29: 0 | EZ29: 0 | FA29: 0 | FB29: 0 | FC29: 0 | FD29: 0 | FE29: 0 | FF29: 0 | FG29: 0 | FH29: 0 | FI29: 0 | FJ29: 0 | FK29: 0 | FL29: 0 | FM29: 0 | FN29: 0 | FO29: 0 | FP29: 0 | FQ29: 0 | FR29: 0 | FS29: 0 | FT29: 0 | FU29: 0 | FV29: 0 | FW29: 0 | FX29: 0 | FY29: 0 | FZ29: 0 | GA29: 0 | GB29: 0 | GC29: 0 | GD29: 0 | GE29: 0 | GF29: 0 | GG29: 0 | GH29: 0 | GI29: 0 | GJ29: 0 | GK29: 0 | GL29: 0 | GM29: 0 | GN29: 0 | GO29: 0 | GP29: 0 | GQ29: 0 | GR29: 0
D30: {=IFERROR(INDIRECT(TRANSPOSE(D29)),"%")} -> standard_line_mueble_fabricado | E30: {=IFERROR(INDIRECT(TRANSPOSE(E29)),"%")} -> 0.2 | F30: {=IFERROR(INDIRECT(TRANSPOSE(F29)),"%")} -> 3 | G30: {=IFERROR(INDIRECT(TRANSPOSE(G29)),"%")} -> 1.45 | H30: {=IFERROR(INDIRECT(TRANSPOSE(H29)),"%")} -> 0.7 | I30: {=IFERROR(INDIRECT(TRANSPOSE(I29)),"%")} -> 0.1 | J30: {=IFERROR(INDIRECT(TRANSPOSE(J29)),"%")} -> #VALUE! | K30: {=IFERROR(INDIRECT(TRANSPOSE(K29)),"%")} -> #VALUE! | L30: {=IFERROR(INDIRECT(TRANSPOSE(L29)),"%")} -> #VALUE!
D31: standard_line_componente_fabricado | E31: 0.15 | F31: 3 | G31: 1.45 | H31: 0.7 | I31: 0.1 | J31: {=IFERROR(INDIRECT(TRANSPOSE(J30)),"%")} -> % | K31: {=IFERROR(INDIRECT(TRANSPOSE(K30)),"%")} -> % | L31: {=IFERROR(INDIRECT(TRANSPOSE(L30)),"%")} -> %
D32: standard_line_mueble_compra_venta | E32: 0.01 | F32: 0.05 | G32: 1.25 | H32: 0.7 | I32: 0.1 | J32: {=IFERROR(INDIRECT(TRANSPOSE(J31)),"%")} -> % | K32: {=IFERROR(INDIRECT(TRANSPOSE(K31)),"%")} -> % | L32: {=IFERROR(INDIRECT(TRANSPOSE(L31)),"%")} -> %
D33: standard_line_componente_compra_venta | E33: 0.05 | F33: 0.05 | G33: 1.25 | H33: 0.7 | I33: 0.1 | J33: {=IFERROR(INDIRECT(TRANSPOSE(J32)),"%")} -> % | K33: {=IFERROR(INDIRECT(TRANSPOSE(K32)),"%")} -> % | L33: {=IFERROR(INDIRECT(TRANSPOSE(L32)),"%")} -> %
D34: standard_line_accesorio_compra_venta | E34: 0.01 | F34: 0.05 | G34: 1.25 | H34: 0.7 | I34: 0.1 | J34: {=IFERROR(INDIRECT(TRANSPOSE(J33)),"%")} -> % | K34: {=IFERROR(INDIRECT(TRANSPOSE(K33)),"%")} -> % | L34: {=IFERROR(INDIRECT(TRANSPOSE(L33)),"%")} -> %
D35: standard_line_servicio_directo | E35: 0.1 | F35: 2.75 | G35: 1.2 | H35: 0 | I35: 1.2 | J35: {=IFERROR(INDIRECT(TRANSPOSE(J34)),"%")} -> % | K35: {=IFERROR(INDIRECT(TRANSPOSE(K34)),"%")} -> % | L35: {=IFERROR(INDIRECT(TRANSPOSE(L34)),"%")} -> %
D36: 0 | E36: 0 | F36: 0 | G36: 0 | H36: 0 | I36: 0 | J36: {=IFERROR(INDIRECT(TRANSPOSE(J35)),"%")} -> % | K36: {=IFERROR(INDIRECT(TRANSPOSE(K35)),"%")} -> % | L36: {=IFERROR(INDIRECT(TRANSPOSE(L35)),"%")} -> %
D37: 0 | E37: 0 | F37: 0 | G37: 0 | H37: 0 | I37: 0 | J37: {=IFERROR(INDIRECT(TRANSPOSE(J36)),"%")} -> % | K37: {=IFERROR(INDIRECT(TRANSPOSE(K36)),"%")} -> % | L37: {=IFERROR(INDIRECT(TRANSPOSE(L36)),"%")} -> %
D38: 0 | E38: 0 | F38: 0 | G38: 0 | H38: 0 | I38: 0 | J38: {=IFERROR(INDIRECT(TRANSPOSE(J37)),"%")} -> % | K38: {=IFERROR(INDIRECT(TRANSPOSE(K37)),"%")} -> % | L38: {=IFERROR(INDIRECT(TRANSPOSE(L37)),"%")} -> %
D39: 0 | E39: 0 | F39: 0 | G39: 0 | H39: 0 | I39: 0 | J39: {=IFERROR(INDIRECT(TRANSPOSE(J38)),"%")} -> % | K39: {=IFERROR(INDIRECT(TRANSPOSE(K38)),"%")} -> % | L39: {=IFERROR(INDIRECT(TRANSPOSE(L38)),"%")} -> %
D40: 0 | E40: 0 | F40: 0 | G40: 0 | H40: 0 | I40: 0 | J40: {=IFERROR(INDIRECT(TRANSPOSE(J39)),"%")} -> % | K40: {=IFERROR(INDIRECT(TRANSPOSE(K39)),"%")} -> % | L40: {=IFERROR(INDIRECT(TRANSPOSE(L39)),"%")} -> %
D41: 0 | E41: 0 | F41: 0 | G41: 0 | H41: 0 | I41: 0 | J41: {=IFERROR(INDIRECT(TRANSPOSE(J40)),"%")} -> % | K41: {=IFERROR(INDIRECT(TRANSPOSE(K40)),"%")} -> % | L41: {=IFERROR(INDIRECT(TRANSPOSE(L40)),"%")} -> %
D42: 0 | E42: 0 | F42: 0 | G42: 0 | H42: 0 | I42: 0 | J42: {=IFERROR(INDIRECT(TRANSPOSE(J41)),"%")} -> % | K42: {=IFERROR(INDIRECT(TRANSPOSE(K41)),"%")} -> % | L42: {=IFERROR(INDIRECT(TRANSPOSE(L41)),"%")} -> %
D43: 0 | E43: 0 | F43: 0 | G43: 0 | H43: 0 | I43: 0
D44: 0 | E44: 0 | F44: 0 | G44: 0 | H44: 0 | I44: 0
D45: 0 | E45: 0 | F45: 0 | G45: 0 | H45: 0 | I45: 0
D46: 0 | E46: 0 | F46: 0 | G46: 0 | H46: 0 | I46: 0
D47: 0 | E47: 0 | F47: 0 | G47: 0 | H47: 0 | I47: 0
D48: 0 | E48: 0 | F48: 0 | G48: 0 | H48: 0 | I48: 0
D49: 0 | E49: 0 | F49: 0 | G49: 0 | H49: 0 | I49: 0
D50: 0 | E50: 0 | F50: 0 | G50: 0 | H50: 0 | I50: 0
D51: 0 | E51: 0 | F51: 0 | G51: 0 | H51: 0 | I51: 0
D52: 0 | E52: 0 | F52: 0 | G52: 0 | H52: 0 | I52: 0
D53: 0 | E53: 0 | F53: 0 | G53: 0 | H53: 0 | I53: 0
D54: 0 | E54: 0 | F54: 0 | G54: 0 | H54: 0 | I54: 0
... D226: 0 | E226: 0 | F226: 0 | G226: 0 | H226: 0 | I226: 0

Sheet REG-DCC-IDP-031 (T_d_C) 
C1: estimaciones y análisis de costos | L1: Registro | O1: REG-DCC-IDP-031
C2: tabla de comparación | L2: Tabla de comparación | O2: Revision: 9.0 | P2: Version: 4.0
C3: {=MID(CELL("nombrearchivo"),FIND("[",CELL("nombrearchivo"))+1,FIND("]",CELL("nombrearchivo"))-FIND("[",CELL("nombrearchivo"))-1)} -> C-CO-516R Copete abatible de cabecera.xlsx | L3: Asociado a: Cláusula 8.2 Requisitos para los productos y servicios; Procedimiento de estimaciones y costos, Manual del Sistema de Gestión de la Calidad. | O3: Página: 1 de 1
C5: Informacion de solicitud: | P5: fecha:
C6: solicita: | P6: 46280
D7: =solicita -> pedro_r.
C8: fecha_requerida:
D9: =fecha_requerida -> 46248
C10: tipo de tabla:
D11: =tabla_requerida -> cotización_producto_vonhaucke(s)
C12: contabilidad de tabla:
D13: =costos_precios_y_descuentos -> standard_line_costos_precios_y_descuentos
C14: tipo de ventta:
D15: ='REG-DCC-IDP-032 (t_d_p)'!E14 -> venta_tradicional_costos_precios_y_descuentos
C16: tipo de empaque y/o embalaje incluyen:
D17: =tipo_empaque_embalaje -> emp_jgo_1_unitario_básico
C18: tipo de entrega y/o instalacion incluye: | J18: 0.15 | K18: 0.05 | M18: 1.25
D19: =tipo_entrega_trasporte_instalación -> ent_1_cliente_vonhaucke | J19: 0.2 | K19: 3 | M19: 1.55 | N19: 0.7 | O19: 0.42
D21: id_nº | E21: clave | F21: imagen | G21: descripcion | H21: cantidad | I21: $_cos_mat | J21: $_cos_man_obr | K21: $_cos_gas_ind | L21: $_cos_fab | M21: precio_mínimo | N21: precio_lista | O21: precio_2
D22: id_01 | E22: Copete abatible de 1000 x 900 x 58 mm. | G22: Copete abatible de 1000 x 900 x 58 mm, plegado. Fabricado en: Marcos y brazos en perfil cuadrado de 1" cal 18 armados a 45°. Bisagra metálica tipo libro de 2 x 2 para pliegue de marcos y de herrajes. Herrajes de ajuste fabricado en lámina cal 14, hoja de 4x10. Marcos de fabricados a partir de baguetas de lámina cal 18, hoja 4 x 10. Tuerca hexagonal galvanizada de para tornillo de 1/4". Tornillo perilla estrella ø 1/4" x 2 1/2” en plástico color negro - "PEE14212" Acabado en electropintura Charcoal op 118. | H22: De 750 a 1,000 | I22: =id_01_costo_total -> 460.57 | J22: =I22*$J$19 -> 92.11 | K22: =J22*$K$19 -> 276.33 | L22: =SUM(I22:K22) -> 829.01 | M22: =ROUNDUP((L22*$M$19),-1) -> 1290 | N22: =ROUNDUP((M22/0.699),-1) -> 1850 | O22: =ROUNDUP((M22/$O$19),-1) -> 3080
D23: id_02 | I23: =id_02_costo_total -> 0 | J23: =I23*$J$19 -> 0 | K23: =J23*$K$19 -> 0 | L23: =SUM(I23:K23) -> 0 | M23: =ROUNDUP((L23*$M$19),-1) -> 0 | N23: =ROUNDUP((M23/0.699),-1) -> 0 | O23: =ROUNDUP((M23/$O$19),-1) -> 0
D24: id_03 | I24: =id_03_costo_total -> 0 | J24: =I24*$J$18 -> 0 | K24: =J24*$K$19 -> 0 | L24: =SUM(I24:K24) -> 0 | M24: =ROUNDUP((L24*$M$19),-1) -> 0 | N24: =ROUNDUP((M24/0.699),-1) -> 0 | O24: =ROUNDUP((M24/$O$19),-1) -> 0
D25: id_04 | I25: =id_04_costo_total -> 0 | J25: =I25*$J$18 -> 0 | K25: =J25*$K$19 -> 0 | L25: =SUM(I25:K25) -> 0 | M25: =ROUNDUP((L25*$M$19),-1) -> 0 | N25: =ROUNDUP((M25/0.699),-1) -> 0 | O25: =ROUNDUP((M25/$O$19),-1) -> 0
D26: id_05 | I26: =id_05_costo_total -> 0 | J26: =I26*$J$18 -> 0 | K26: =J26*$K$19 -> 0 | L26: =SUM(I26:K26) -> 0 | M26: =ROUNDUP((L26*$M$19),-1) -> 0 | N26: =ROUNDUP((M26/0.699),-1) -> 0 | O26: =ROUNDUP((M26/$O$19),-1) -> 0
D27: id_06 | I27: =id_06_costo_total -> 0 | J27: =I27*$J$19 -> 0 | K27: =J27*$K$19 -> 0 | L27: =SUM(I27:K27) -> 0 | M27: =ROUNDUP((L27*$M$19),-1) -> 0 | N27: =ROUNDUP((M27/0.699),-1) -> 0 | O27: =ROUNDUP((M27/$O$19),-1) -> 0
D28: id_07 | I28: =id_07_costo_total -> 0 | J28: =I28*$J$19 -> 0 | K28: =J28*$K$19 -> 0 | L28: =SUM(I28:K28) -> 0 | M28: =ROUNDUP((L28*$M$19),-1) -> 0 | N28: =ROUNDUP((M28/0.699),-1) -> 0 | O28: =ROUNDUP((M28/$O$19),-1) -> 0
D29: id_08 | I29: =id_08_costo_total -> 0 | J29: =I29*$J$19 -> 0 | K29: =J29*$K$19 -> 0 | L29: =SUM(I29:K29) -> 0 | M29: =ROUNDUP((L29*$M$19),-1) -> 0 | N29: =ROUNDUP((M29/0.699),-1) -> 0 | O29: =ROUNDUP((M29/$O$19),-1) -> 0
D30: id_09 | I30: =id_09_costo_total -> 0 | J30: =I30*$J$19 -> 0 | K30: =J30*$K$19 -> 0 | L30: =SUM(I30:K30) -> 0 | M30: =ROUNDUP((L30*$M$19),-1) -> 0 | N30: =ROUNDUP((M30/0.699),-1) -> 0 | O30: =ROUNDUP((M30/$O$19),-1) -> 0
D31: id_10 | I31: =id_10_costo_total -> 0 | J31: =I31*$J$19 -> 0 | K31: =J31*$K$19 -> 0 | L31: =SUM(I31:K31) -> 0 | M31: =ROUNDUP((L31*$M$19),-1) -> 0 | N31: =ROUNDUP((M31/0.699),-1) -> 0 | O31: =ROUNDUP((M31/$O$19),-1) -> 0
D34: Departamento de estimaciones y costos
C36: * | D36: fabricación a nuestra capacidad de proceso
C37: * | D37: tolerancias en dimensión general + - 5mm y en cuota crítica + - 3mm.
C38: * | D38: nivel de empaque / emp_jgo_1_unitario_basico
C39: * | D39: nivel de maneobra / transporte / entrega / instalacion
C40: * | D40: moneda en $-MXP
C41: * | D41: precios sin IVA
C42: * | D42: costo de tabla validos por 15 días
C43: * | D43: Analista/ Angel Adaya

Sheet  (Explo_MP)
D3: ='REG-DCC-IDP-032 (t_d_p)'!D30 -> standard_line_mueble_fabricado | E3: ='REG-DCC-IDP-032 (t_d_p)'!D29 -> standard_line_costo_de_producto | F3: ='REG-DCC-IDP-032 (t_d_p)'!F29 -> standard_line_costo_de_gasto_indirecto | G3: ='REG-DCC-IDP-032 (t_d_p)'!J3 -> 0 | H3: ='REG-DCC-IDP-032 (t_d_p)'!K3 -> 0 | I3: ='REG-DCC-IDP-032 (t_d_p)'!L3 -> 0 | J3: ='REG-DCC-IDP-032 (t_d_p)'!M3 -> 0 | K3: ='REG-DCC-IDP-032 (t_d_p)'!#REF! -> #REF! | L3: ='REG-DCC-IDP-032 (t_d_p)'!#REF! -> #REF! | M3: ='REG-DCC-IDP-032 (t_d_p)'!#REF! -> #REF! | P3: ='REG-DCC-IDP-031 (T_d_C) '!D22 -> id_01
D4: ='REG-DCC-IDP-032 (t_d_p)'!D31 -> standard_line_componente_fabricado | E4: ='REG-DCC-IDP-032 (t_d_p)'!#REF! -> #REF! | F4: ='REG-DCC-IDP-032 (t_d_p)'!F30 -> 3 | G4: ='REG-DCC-IDP-032 (t_d_p)'!J4 -> 0 | H4: ='REG-DCC-IDP-032 (t_d_p)'!K4 -> 0 | I4: ='REG-DCC-IDP-032 (t_d_p)'!L4 -> 0 | J4: ='REG-DCC-IDP-032 (t_d_p)'!M4 -> 0 | K4: ='REG-DCC-IDP-032 (t_d_p)'!#REF! -> #REF! | L4: ='REG-DCC-IDP-032 (t_d_p)'!#REF! -> #REF! | M4: ='REG-DCC-IDP-032 (t_d_p)'!#REF! -> #REF! | R4: familia_de_operación | S4: articulo | T4: descripción | U4: opción | V4: opción_descripción | W4: unidad | X4: fecha_última_compra | Y4: costo_última_compra | Z4: consumo_unitaruio | AA4: costo_unitario
D5: ='REG-DCC-IDP-032 (t_d_p)'!D32 -> standard_line_mueble_compra_venta | E5: ='REG-DCC-IDP-032 (t_d_p)'!#REF! -> #REF! | F5: ='REG-DCC-IDP-032 (t_d_p)'!F31 -> 3 | G5: ='REG-DCC-IDP-032 (t_d_p)'!J5 -> 0 | H5: ='REG-DCC-IDP-032 (t_d_p)'!K5 -> 0 | I5: ='REG-DCC-IDP-032 (t_d_p)'!L5 -> 0 | J5: ='REG-DCC-IDP-032 (t_d_p)'!M5 -> 0 | K5: ='REG-DCC-IDP-032 (t_d_p)'!#REF! -> #REF! | L5: ='REG-DCC-IDP-032 (t_d_p)'!#REF! -> #REF! | M5: ='REG-DCC-IDP-032 (t_d_p)'!#REF! -> #REF! | T5: ='REG-DCC-IDP-031 (T_d_C) '!E22 -> Copete abatible de 1000 x 900 x 58 mm.
S6: MVLSTU01080401 | T6: =IFERROR(VLOOKUP(S6,'(cata_mp)'!C14:I16417,2,FALSE)," ") -> TUBULAR INDUSTRIAL CUADRADO 1" CALIBRE 18 PIEZA DE 6000 mm - TC181 | U6: - | V6: =IFERROR(INDEX(opción_descripción,MATCH(' (Explo_MP)'!$U6,opción,0))," ") -> Sin Opc. | W6: =IFERROR(VLOOKUP(S6,'(cata_mp)'!C29:I16432,5,FALSE)," ") -> pieza | X6: {=IFERROR(INDEX('(cata_mp)'!H28:H16431,MATCH(' (Explo_MP)'!S6&' (Explo_MP)'!U6,'(cata_mp)'!C28:C16431&'(cata_mp)'!E28:E16431,0)), " ")} -> 46121 | Y6: {=IFERROR(INDEX('(cata_mp)'!I:I,MATCH(' (Explo_MP)'!S6&' (Explo_MP)'!U6,'(cata_mp)'!C:C&'(cata_mp)'!E:E,0)),"$ 0")} -> 122.41 | Z6: 1.5 | AA6: =Y6*Z6 -> 183.62
T7: Bisagra libro soldable 2″ x 2″ | U7: - | V7: =IFERROR(INDEX(opción_descripción,MATCH(' (Explo_MP)'!$U7,opción,0))," ") -> Sin Opc. | W7: =IFERROR(VLOOKUP(S7,'(cata_mp)'!C30:I16433,5,FALSE)," ") | X7: {=IFERROR(INDEX('(cata_mp)'!H29:H16432,MATCH(' (Explo_MP)'!S7&' (Explo_MP)'!U7,'(cata_mp)'!C29:C16432&'(cata_mp)'!E29:E16432,0)), " ")} | Y7: 11.01 | Z7: 6 | AA7: =Y7*Z7 -> 66.06
S8: MVLSLA05270202 | T8: =IFERROR(VLOOKUP(S8,'(cata_mp)'!C16:I16419,2,FALSE)," ") -> LAMINA NEGRA HOJA 4 X 10 CALIBRE 14 ACERO 1008 - ""LN14410""" | U8: - | V8: =IFERROR(INDEX(opción_descripción,MATCH(' (Explo_MP)'!$U8,opción,0))," ") -> Sin Opc. | W8: =IFERROR(VLOOKUP(S8,'(cata_mp)'!C31:I16434,5,FALSE)," ") -> Hoja | X8: {=IFERROR(INDEX('(cata_mp)'!H30:H16433,MATCH(' (Explo_MP)'!S8&' (Explo_MP)'!U8,'(cata_mp)'!C30:C16433&'(cata_mp)'!E30:E16433,0)), " ")} -> 45868 | Y8: {=IFERROR(INDEX('(cata_mp)'!I:I,MATCH(' (Explo_MP)'!S8&' (Explo_MP)'!U8,'(cata_mp)'!C:C&'(cata_mp)'!E:E,0)),"$ 0")} -> 1125.4 | Z8: 0.02 | AA8: =Y8*Z8 -> 22.51
S9: MVLSLA05270402 | T9: =IFERROR(VLOOKUP(S9,'(cata_mp)'!C17:I16420,2,FALSE)," ") -> LAMINA NEGRA HOJA 4 X 10 CALIBRE 18 ACERO 1008 - ""LN18410""" | U9: - | V9: =IFERROR(INDEX(opción_descripción,MATCH(' (Explo_MP)'!$U9,opción,0))," ") -> Sin Opc. | W9: =IFERROR(VLOOKUP(S9,'(cata_mp)'!C32:I16435,5,FALSE)," ") -> Hoja | X9: {=IFERROR(INDEX('(cata_mp)'!H31:H16434,MATCH(' (Explo_MP)'!S9&' (Explo_MP)'!U9,'(cata_mp)'!C31:C16434&'(cata_mp)'!E31:E16434,0)), " ")} -> 45947 | Y9: {=IFERROR(INDEX('(cata_mp)'!I:I,MATCH(' (Explo_MP)'!S9&' (Explo_MP)'!U9,'(cata_mp)'!C:C&'(cata_mp)'!E:E,0)),"$ 0")} -> 696.71 | Z9: 0.02 | AA9: =Y9*Z9 -> 13.93
S10: MVLUTO34160016 | T10: =IFERROR(VLOOKUP(S10,'(cata_mp)'!C18:I16421,2,FALSE)," ") -> TORNILLO PERILLA ESTRELLA Ø 1/4" X 2 1/2" EN PLASTICO COLOR NEGRO - "PEE14212" | U10: - | V10: =IFERROR(INDEX(opción_descripción,MATCH(' (Explo_MP)'!$U10,opción,0))," ") -> Sin Opc. | W10: =IFERROR(VLOOKUP(S10,'(cata_mp)'!C33:I16436,5,FALSE)," ") -> pieza | X10: {=IFERROR(INDEX('(cata_mp)'!H32:H16435,MATCH(' (Explo_MP)'!S10&' (Explo_MP)'!U10,'(cata_mp)'!C32:C16435&'(cata_mp)'!E32:E16435,0)), " ")} -> 42461 | Y10: {=IFERROR(INDEX('(cata_mp)'!I:I,MATCH(' (Explo_MP)'!S10&' (Explo_MP)'!U10,'(cata_mp)'!C:C&'(cata_mp)'!E:E,0)),"$ 0")} -> 10 | Z10: 10 | AA10: =Y10*Z10 -> 100
S11: MVLUTU22520002 | T11: =IFERROR(VLOOKUP(S11,'(cata_mp)'!C19:I16422,2,FALSE)," ") -> TUERCA HEXAGONAL Ø1/4" GALVANIZADO -- TU14HE | U11: - | V11: =IFERROR(INDEX(opción_descripción,MATCH(' (Explo_MP)'!$U11,opción,0))," ") -> Sin Opc. | W11: =IFERROR(VLOOKUP(S11,'(cata_mp)'!C34:I16437,5,FALSE)," ") -> pieza | X11: {=IFERROR(INDEX('(cata_mp)'!H33:H16436,MATCH(' (Explo_MP)'!S11&' (Explo_MP)'!U11,'(cata_mp)'!C33:C16436&'(cata_mp)'!E33:E16436,0)), " ")} -> 46042 | Y11: {=IFERROR(INDEX('(cata_mp)'!I:I,MATCH(' (Explo_MP)'!S11&' (Explo_MP)'!U11,'(cata_mp)'!C:C&'(cata_mp)'!E:E,0)),"$ 0")} -> 0.22 | Z11: 12 | AA11: =Y11*Z11 -> 2.64
S12: MVLQPP00000000 | T12: =IFERROR(VLOOKUP(S12,'(cata_mp)'!C16:I16419,2,FALSE)," ") -> PINTURA EN POLVO - ""PPH""" | U12: a118 | V12: =IFERROR(INDEX(opción_descripción,MATCH(' (Explo_MP)'!$U12,opción,0))," ") -> COLOR METAL CHARCOAL | W12: =IFERROR(VLOOKUP(S12,'(cata_mp)'!C31:I16434,5,FALSE)," ") -> Kg | X12: {=IFERROR(INDEX('(cata_mp)'!H30:H16433,MATCH(' (Explo_MP)'!S12&' (Explo_MP)'!U12,'(cata_mp)'!C30:C16433&'(cata_mp)'!E30:E16433,0)), " ")} -> 46107 | Y12: {=IFERROR(INDEX('(cata_mp)'!I:I,MATCH(' (Explo_MP)'!S12&' (Explo_MP)'!U12,'(cata_mp)'!C:C&'(cata_mp)'!E:E,0)),"$ 0")} -> 181.99 | Z12: =0.32+0.01 -> 0.33 | AA12: =Y12*Z12 -> 60.06
T13: emp_jgo_1_unitario_basico | U13: - | V13: =IFERROR(INDEX(opción_descripción,MATCH(' (Explo_MP)'!$U13,opción,0))," ") -> Sin Opc. | W13: =IFERROR(VLOOKUP(S13,'(cata_mp)'!C32:I16435,5,FALSE)," ") | X13: {=IFERROR(INDEX('(cata_mp)'!H31:H16434,MATCH(' (Explo_MP)'!S13&' (Explo_MP)'!U13,'(cata_mp)'!C31:C16434&'(cata_mp)'!E31:E16434,0)), " ")} | Y13: 225.99 | Z13: =1*0.9*0.058 -> 0.052 | AA13: =Y13*Z13 -> 11.75
T14: =IFERROR(VLOOKUP(S14,'(cata_mp)'!C20:I16423,2,FALSE)," ") | U14: - | V14: =IFERROR(INDEX(opción_descripción,MATCH(' (Explo_MP)'!$U14,opción,0))," ") -> Sin Opc. | W14: =IFERROR(VLOOKUP(S14,'(cata_mp)'!C35:I16438,5,FALSE)," ") | X14: {=IFERROR(INDEX('(cata_mp)'!H34:H16437,MATCH(' (Explo_MP)'!S14&' (Explo_MP)'!U14,'(cata_mp)'!C34:C16437&'(cata_mp)'!E34:E16437,0)), " ")} | Y14: {=IFERROR(INDEX('(cata_mp)'!I:I,MATCH(' (Explo_MP)'!S14&' (Explo_MP)'!U14,'(cata_mp)'!C:C&'(cata_mp)'!E:E,0)),"$ 0")} -> $ 0 | AA14: =Y14*Z14 -> 0
Y15: =P3 -> id_01 | Z15: =P3&" costo_total:" -> id_01 costo_total: | AA15: =+SUM(AA6:AA14) -> 460.57
P19: ='REG-DCC-IDP-031 (T_d_C) '!D23 -> id_02
R20: familia_de_operación | S20: articulo | T20: descripción | U20: opción | V20: opción_descripción | W20: unidad | X20: fecha_última_compra | Y20: costo_última_compra | Z20: consumo_unitaruio | AA20: costo_unitario
T21: ='REG-DCC-IDP-031 (T_d_C) '!E23 -> 0
T22: =IFERROR(VLOOKUP(S22,'(cata_mp)'!C37:I16440,2,FALSE)," ") | U22: - | V22: =IFERROR(INDEX(opción_descripción,MATCH(' (Explo_MP)'!$U22,opción,0))," ") -> Sin Opc. | W22: =IFERROR(VLOOKUP(S22,'(cata_mp)'!C40:I16443,5,FALSE)," ") | X22: {=IFERROR(INDEX('(cata_mp)'!H39:H16442,MATCH(' (Explo_MP)'!S22&' (Explo_MP)'!U22,'(cata_mp)'!C39:C16442&'(cata_mp)'!E39:E16442,0)), " ")} | Y22: {=IFERROR(INDEX('(cata_mp)'!I:I,MATCH(' (Explo_MP)'!S22&' (Explo_MP)'!U22,'(cata_mp)'!C:C&'(cata_mp)'!E:E,0)),"$ 0")} -> $ 0 | AA22: =Y22*Z22 -> 0
T23: =IFERROR(VLOOKUP(S23,'(cata_mp)'!C38:I16441,2,FALSE)," ") | U23: - | V23: =IFERROR(INDEX(opción_descripción,MATCH(' (Explo_MP)'!$U23,opción,0))," ") -> Sin Opc. | W23: =IFERROR(VLOOKUP(S23,'(cata_mp)'!C41:I16444,5,FALSE)," ") | X23: {=IFERROR(INDEX('(cata_mp)'!H40:H16443,MATCH(' (Explo_MP)'!S23&' (Explo_MP)'!U23,'(cata_mp)'!C40:C16443&'(cata_mp)'!E40:E16443,0)), " ")} | Y23: {=IFERROR(INDEX('(cata_mp)'!I:I,MATCH(' (Explo_MP)'!S23&' (Explo_MP)'!U23,'(cata_mp)'!C:C&'(cata_mp)'!E:E,0)),"$ 0")} -> $ 0 | AA23: =Y23*Z23 -> 0
T24: =IFERROR(VLOOKUP(S24,'(cata_mp)'!C39:I16442,2,FALSE)," ") | U24: - | V24: =IFERROR(INDEX(opción_descripción,MATCH(' (Explo_MP)'!$U24,opción,0))," ") -> Sin Opc. | W24: =IFERROR(VLOOKUP(S24,'(cata_mp)'!C42:I16445,5,FALSE)," ") | X24: {=IFERROR(INDEX('(cata_mp)'!H41:H16444,MATCH(' (Explo_MP)'!S24&' (Explo_MP)'!U24,'(cata_mp)'!C41:C16444&'(cata_mp)'!E41:E16444,0)), " ")} | Y24: {=IFERROR(INDEX('(cata_mp)'!I:I,MATCH(' (Explo_MP)'!S24&' (Explo_MP)'!U24,'(cata_mp)'!C:C&'(cata_mp)'!E:E,0)),"$ 0")} -> $ 0 | AA24: =Y24*Z24 -> 0
T25: =IFERROR(VLOOKUP(S25,'(cata_mp)'!C40:I16443,2,FALSE)," ") | U25: - | V25: =IFERROR(INDEX(opción_descripción,MATCH(' (Explo_MP)'!$U25,opción,0))," ") -> Sin Opc. | W25: =IFERROR(VLOOKUP(S25,'(cata_mp)'!C43:I16446,5,FALSE)," ") | X25: {=IFERROR(INDEX('(cata_mp)'!H42:H16445,MATCH(' (Explo_MP)'!S25&' (Explo_MP)'!U25,'(cata_mp)'!C42:C16445&'(cata_mp)'!E42:E16445,0)), " ")} | Y25: {=IFERROR(INDEX('(cata_mp)'!I:I,MATCH(' (Explo_MP)'!S25&' (Explo_MP)'!U25,'(cata_mp)'!C:C&'(cata_mp)'!E:E,0)),"$ 0")} -> $ 0 | AA25: =Y25*Z25 -> 0
T26: =IFERROR(VLOOKUP(S26,'(cata_mp)'!C41:I16444,2,FALSE)," ") | U26: - | V26: =IFERROR(INDEX(opción_descripción,MATCH(' (Explo_MP)'!$U26,opción,0))," ") -> Sin Opc. | W26: =IFERROR(VLOOKUP(S26,'(cata_mp)'!C44:I16447,5,FALSE)," ") | X26: {=IFERROR(INDEX('(cata_mp)'!H43:H16446,MATCH(' (Explo_MP)'!S26&' (Explo_MP)'!U26,'(cata_mp)'!C43:C16446&'(cata_mp)'!E43:E16446,0)), " ")} | Y26: {=IFERROR(INDEX('(cata_mp)'!I:I,MATCH(' (Explo_MP)'!S26&' (Explo_MP)'!U26,'(cata_mp)'!C:C&'(cata_mp)'!E:E,0)),"$ 0")} -> $ 0 | AA26: =Y26*Z26 -> 0
T27: =IFERROR(VLOOKUP(S27,'(cata_mp)'!C42:I16445,2,FALSE)," ") | U27: - | V27: =IFERROR(INDEX(opción_descripción,MATCH(' (Explo_MP)'!$U27,opción,0))," ") -> Sin Opc. | W27: =IFERROR(VLOOKUP(S27,'(cata_mp)'!C45:I16448,5,FALSE)," ") | X27: {=IFERROR(INDEX('(cata_mp)'!H44:H16447,MATCH(' (Explo_MP)'!S27&' (Explo_MP)'!U27,'(cata_mp)'!C44:C16447&'(cata_mp)'!E44:E16447,0)), " ")} | Y27: {=IFERROR(INDEX('(cata_mp)'!I:I,MATCH(' (Explo_MP)'!S27&' (Explo_MP)'!U27,'(cata_mp)'!C:C&'(cata_mp)'!E:E,0)),"$ 0")} -> $ 0 | AA27: =Y27*Z27 -> 0
Y28: =P19 -> id_02 | Z28: =P19&" costo_total:" -> id_02 costo_total: | AA28: =+SUM(AA22:AA27) -> 0
P32: ='REG-DCC-IDP-031 (T_d_C) '!D24 -> id_03
R33: familia_de_operación | S33: articulo | T33: descripción | U33: opción | V33: opción_descripción | W33: unidad | X33: fecha_última_compra | Y33: costo_última_compra | Z33: consumo_unitaruio | AA33: costo_unitario
T34: ='REG-DCC-IDP-031 (T_d_C) '!E24 -> 0
T35: =IFERROR(VLOOKUP(S35,'(cata_mp)'!C47:I16450,2,FALSE)," ") | U35: - | V35: =IFERROR(INDEX(opción_descripción,MATCH(' (Explo_MP)'!$U35,opción,0))," ") -> Sin Opc. | W35: =IFERROR(VLOOKUP(S35,'(cata_mp)'!C49:I16452,5,FALSE)," ") | X35: {=IFERROR(INDEX('(cata_mp)'!H48:H16451,MATCH(' (Explo_MP)'!S35&' (Explo_MP)'!U35,'(cata_mp)'!C48:C16451&'(cata_mp)'!E48:E16451,0)), " ")} | Y35: {=IFERROR(INDEX('(cata_mp)'!I:I,MATCH(' (Explo_MP)'!S35&' (Explo_MP)'!U35,'(cata_mp)'!C:C&'(cata_mp)'!E:E,0)),"$ 0")} -> $ 0 | AA35: =Y35*Z35 -> 0
T36: =IFERROR(VLOOKUP(S36,'(cata_mp)'!C48:I16451,2,FALSE)," ") | U36: - | V36: =IFERROR(INDEX(opción_descripción,MATCH(' (Explo_MP)'!$U36,opción,0))," ") -> Sin Opc. | W36: =IFERROR(VLOOKUP(S36,'(cata_mp)'!C50:I16453,5,FALSE)," ") | X36: {=IFERROR(INDEX('(cata_mp)'!H49:H16452,MATCH(' (Explo_MP)'!S36&' (Explo_MP)'!U36,'(cata_mp)'!C49:C16452&'(cata_mp)'!E49:E16452,0)), " ")} | Y36: {=IFERROR(INDEX('(cata_mp)'!I:I,MATCH(' (Explo_MP)'!S36&' (Explo_MP)'!U36,'(cata_mp)'!C:C&'(cata_mp)'!E:E,0)),"$ 0")} -> $ 0 | AA36: =Y36*Z36 -> 0
T37: =IFERROR(VLOOKUP(S37,'(cata_mp)'!C49:I16452,2,FALSE)," ") | U37: - | V37: =IFERROR(INDEX(opción_descripción,MATCH(' (Explo_MP)'!$U37,opción,0))," ") -> Sin Opc. | W37: =IFERROR(VLOOKUP(S37,'(cata_mp)'!C51:I16454,5,FALSE)," ") | X37: {=IFERROR(INDEX('(cata_mp)'!H50:H16453,MATCH(' (Explo_MP)'!S37&' (Explo_MP)'!U37,'(cata_mp)'!C50:C16453&'(cata_mp)'!E50:E16453,0)), " ")} | Y37: {=IFERROR(INDEX('(cata_mp)'!I:I,MATCH(' (Explo_MP)'!S37&' (Explo_MP)'!U37,'(cata_mp)'!C:C&'(cata_mp)'!E:E,0)),"$ 0")} -> $ 0 | AA37: =Y37*Z37 -> 0
T38: =IFERROR(VLOOKUP(S38,'(cata_mp)'!C50:I16453,2,FALSE)," ") | U38: - | V38: =IFERROR(INDEX(opción_descripción,MATCH(' (Explo_MP)'!$U38,opción,0))," ") -> Sin Opc. | W38: =IFERROR(VLOOKUP(S38,'(cata_mp)'!C52:I16455,5,FALSE)," ") | X38: {=IFERROR(INDEX('(cata_mp)'!H51:H16454,MATCH(' (Explo_MP)'!S38&' (Explo_MP)'!U38,'(cata_mp)'!C51:C16454&'(cata_mp)'!E51:E16454,0)), " ")} | Y38: {=IFERROR(INDEX('(cata_mp)'!I:I,MATCH(' (Explo_MP)'!S38&' (Explo_MP)'!U38,'(cata_mp)'!C:C&'(cata_mp)'!E:E,0)),"$ 0")} -> $ 0 | AA38: =Y38*Z38 -> 0
T39: =IFERROR(VLOOKUP(S39,'(cata_mp)'!C51:I16454,2,FALSE)," ") | U39: - | V39: =IFERROR(INDEX(opción_descripción,MATCH(' (Explo_MP)'!$U39,opción,0))," ") -> Sin Opc. | W39: =IFERROR(VLOOKUP(S39,'(cata_mp)'!C53:I16456,5,FALSE)," ") | X39: {=IFERROR(INDEX('(cata_mp)'!H52:H16455,MATCH(' (Explo_MP)'!S39&' (Explo_MP)'!U39,'(cata_mp)'!C52:C16455&'(cata_mp)'!E52:E16455,0)), " ")} | Y39: {=IFERROR(INDEX('(cata_mp)'!I:I,MATCH(' (Explo_MP)'!S39&' (Explo_MP)'!U39,'(cata_mp)'!C:C&'(cata_mp)'!E:E,0)),"$ 0")} -> $ 0 | AA39: =Y39*Z39 -> 0
Y40: =P32 -> id_03 | Z40: =P32&" costo_total:" -> id_03 costo_total: | AA40: =+SUM(AA35:AA39) -> 0
P44: ='REG-DCC-IDP-031 (T_d_C) '!D25 -> id_04
R45: familia_de_operación | S45: articulo | T45: descripción | U45: opción | V45: opción_descripción | W45: unidad | X45: fecha_última_compra | Y45: costo_última_compra | Z45: consumo_unitaruio | AA45: costo_unitario
T46: ='REG-DCC-IDP-031 (T_d_C) '!E25 -> 0
T47: =IFERROR(VLOOKUP(S47,'(cata_mp)'!C66:I16469,2,FALSE)," ") | U47: - | V47: =IFERROR(INDEX(opción_descripción,MATCH(' (Explo_MP)'!$U47,opción,0))," ") -> Sin Opc. | W47: =IFERROR(VLOOKUP(S47,'(cata_mp)'!C68:I16471,5,FALSE)," ") | X47: {=IFERROR(INDEX('(cata_mp)'!H67:H16470,MATCH(' (Explo_MP)'!S47&' (Explo_MP)'!U47,'(cata_mp)'!C67:C16470&'(cata_mp)'!E67:E16470,0)), " ")} | Y47: {=IFERROR(INDEX('(cata_mp)'!I:I,MATCH(' (Explo_MP)'!S47&' (Explo_MP)'!U47,'(cata_mp)'!C:C&'(cata_mp)'!E:E,0)),"$ 0")} -> $ 0 | AA47: =Y47*Z47 -> 0
T48: =IFERROR(VLOOKUP(S48,'(cata_mp)'!C67:I16470,2,FALSE)," ") | U48: - | V48: =IFERROR(INDEX(opción_descripción,MATCH(' (Explo_MP)'!$U48,opción,0))," ") -> Sin Opc. | W48: =IFERROR(VLOOKUP(S48,'(cata_mp)'!C69:I16472,5,FALSE)," ") | X48: {=IFERROR(INDEX('(cata_mp)'!H68:H16471,MATCH(' (Explo_MP)'!S48&' (Explo_MP)'!U48,'(cata_mp)'!C68:C16471&'(cata_mp)'!E68:E16471,0)), " ")} | Y48: {=IFERROR(INDEX('(cata_mp)'!I:I,MATCH(' (Explo_MP)'!S48&' (Explo_MP)'!U48,'(cata_mp)'!C:C&'(cata_mp)'!E:E,0)),"$ 0")} -> $ 0 | AA48: =Y48*Z48 -> 0
T49: =IFERROR(VLOOKUP(S49,'(cata_mp)'!C68:I16471,2,FALSE)," ") | U49: - | V49: =IFERROR(INDEX(opción_descripción,MATCH(' (Explo_MP)'!$U49,opción,0))," ") -> Sin Opc. | W49: =IFERROR(VLOOKUP(S49,'(cata_mp)'!C70:I16473,5,FALSE)," ") | X49: {=IFERROR(INDEX('(cata_mp)'!H69:H16472,MATCH(' (Explo_MP)'!S49&' (Explo_MP)'!U49,'(cata_mp)'!C69:C16472&'(cata_mp)'!E69:E16472,0)), " ")} | Y49: {=IFERROR(INDEX('(cata_mp)'!I:I,MATCH(' (Explo_MP)'!S49&' (Explo_MP)'!U49,'(cata_mp)'!C:C&'(cata_mp)'!E:E,0)),"$ 0")} -> $ 0 | AA49: =Y49*Z49 -> 0
T50: =IFERROR(VLOOKUP(S50,'(cata_mp)'!C69:I16472,2,FALSE)," ") | U50: - | V50: =IFERROR(INDEX(opción_descripción,MATCH(' (Explo_MP)'!$U50,opción,0))," ") -> Sin Opc. | W50: =IFERROR(VLOOKUP(S50,'(cata_mp)'!C71:I16474,5,FALSE)," ") | X50: {=IFERROR(INDEX('(cata_mp)'!H70:H16473,MATCH(' (Explo_MP)'!S50&' (Explo_MP)'!U50,'(cata_mp)'!C70:C16473&'(cata_mp)'!E70:E16473,0)), " ")} | Y50: {=IFERROR(INDEX('(cata_mp)'!I:I,MATCH(' (Explo_MP)'!S50&' (Explo_MP)'!U50,'(cata_mp)'!C:C&'(cata_mp)'!E:E,0)),"$ 0")} -> $ 0 | AA50: =Y50*Z50 -> 0
T51: =IFERROR(VLOOKUP(S51,'(cata_mp)'!C70:I16473,2,FALSE)," ") | U51: - | V51: =IFERROR(INDEX(opción_descripción,MATCH(' (Explo_MP)'!$U51,opción,0))," ") -> Sin Opc. | W51: =IFERROR(VLOOKUP(S51,'(cata_mp)'!C72:I16475,5,FALSE)," ") | X51: {=IFERROR(INDEX('(cata_mp)'!H71:H16474,MATCH(' (Explo_MP)'!S51&' (Explo_MP)'!U51,'(cata_mp)'!C71:C16474&'(cata_mp)'!E71:E16474,0)), " ")} | Y51: {=IFERROR(INDEX('(cata_mp)'!I:I,MATCH(' (Explo_MP)'!S51&' (Explo_MP)'!U51,'(cata_mp)'!C:C&'(cata_mp)'!E:E,0)),"$ 0")} -> $ 0 | AA51: =Y51*Z51 -> 0
Y52: =P44 -> id_04 | Z52: =P44&" costo_total:" -> id_04 costo_total: | AA52: =+SUM(AA47:AA51) -> 0
P56: ='REG-DCC-IDP-031 (T_d_C) '!D26 -> id_05
R57: familia_de_operación | S57: articulo | T57: descripción | U57: opción | V57: opción_descripción | W57: unidad | X57: fecha_última_compra | Y57: costo_última_compra | Z57: consumo_unitaruio | AA57: costo_unitario
T58: ='REG-DCC-IDP-031 (T_d_C) '!E26 -> 0
T59: =IFERROR(VLOOKUP(S59,'(cata_mp)'!C79:I16482,2,FALSE)," ") | U59: - | V59: =IFERROR(INDEX(opción_descripción,MATCH(' (Explo_MP)'!$U59,opción,0))," ") -> Sin Opc. | W59: =IFERROR(VLOOKUP(S59,'(cata_mp)'!C81:I16484,5,FALSE)," ") | X59: {=IFERROR(INDEX('(cata_mp)'!H80:H16483,MATCH(' (Explo_MP)'!S59&' (Explo_MP)'!U59,'(cata_mp)'!C80:C16483&'(cata_mp)'!E80:E16483,0)), " ")} | Y59: {=IFERROR(INDEX('(cata_mp)'!I:I,MATCH(' (Explo_MP)'!S59&' (Explo_MP)'!U59,'(cata_mp)'!C:C&'(cata_mp)'!E:E,0)),"$ 0")} -> $ 0 | AA59: =Y59*Z59 -> 0
T60: =IFERROR(VLOOKUP(S60,'(cata_mp)'!C80:I16483,2,FALSE)," ") | U60: - | V60: =IFERROR(INDEX(opción_descripción,MATCH(' (Explo_MP)'!$U60,opción,0))," ") -> Sin Opc. | W60: =IFERROR(VLOOKUP(S60,'(cata_mp)'!C82:I16485,5,FALSE)," ") | X60: {=IFERROR(INDEX('(cata_mp)'!H81:H16484,MATCH(' (Explo_MP)'!S60&' (Explo_MP)'!U60,'(cata_mp)'!C81:C16484&'(cata_mp)'!E81:E16484,0)), " ")} | Y60: {=IFERROR(INDEX('(cata_mp)'!I:I,MATCH(' (Explo_MP)'!S60&' (Explo_MP)'!U60,'(cata_mp)'!C:C&'(cata_mp)'!E:E,0)),"$ 0")} -> $ 0 | AA60: =Y60*Z60 -> 0
T61: =IFERROR(VLOOKUP(S61,'(cata_mp)'!C81:I16484,2,FALSE)," ") | U61: - | V61: =IFERROR(INDEX(opción_descripción,MATCH(' (Explo_MP)'!$U61,opción,0))," ") -> Sin Opc. | W61: =IFERROR(VLOOKUP(S61,'(cata_mp)'!C83:I16486,5,FALSE)," ") | X61: {=IFERROR(INDEX('(cata_mp)'!H82:H16485,MATCH(' (Explo_MP)'!S61&' (Explo_MP)'!U61,'(cata_mp)'!C82:C16485&'(cata_mp)'!E82:E16485,0)), " ")} | Y61: {=IFERROR(INDEX('(cata_mp)'!I:I,MATCH(' (Explo_MP)'!S61&' (Explo_MP)'!U61,'(cata_mp)'!C:C&'(cata_mp)'!E:E,0)),"$ 0")} -> $ 0 | AA61: =Y61*Z61 -> 0
T62: =IFERROR(VLOOKUP(S62,'(cata_mp)'!C82:I16485,2,FALSE)," ") | U62: - | V62: =IFERROR(INDEX(opción_descripción,MATCH(' (Explo_MP)'!$U62,opción,0))," ") -> Sin Opc. | W62: =IFERROR(VLOOKUP(S62,'(cata_mp)'!C84:I16487,5,FALSE)," ") | X62: {=IFERROR(INDEX('(cata_mp)'!H83:H16486,MATCH(' (Explo_MP)'!S62&' (Explo_MP)'!U62,'(cata_mp)'!C83:C16486&'(cata_mp)'!E83:E16486,0)), " ")} | Y62: {=IFERROR(INDEX('(cata_mp)'!I:I,MATCH(' (Explo_MP)'!S62&' (Explo_MP)'!U62,'(cata_mp)'!C:C&'(cata_mp)'!E:E,0)),"$ 0")} -> $ 0 | AA62: =Y62*Z62 -> 0
T63: =IFERROR(VLOOKUP(S63,'(cata_mp)'!C83:I16486,2,FALSE)," ") | U63: - | V63: =IFERROR(INDEX(opción_descripción,MATCH(' (Explo_MP)'!$U63,opción,0))," ") -> Sin Opc. | W63: =IFERROR(VLOOKUP(S63,'(cata_mp)'!C85:I16488,5,FALSE)," ") | X63: {=IFERROR(INDEX('(cata_mp)'!H84:H16487,MATCH(' (Explo_MP)'!S63&' (Explo_MP)'!U63,'(cata_mp)'!C84:C16487&'(cata_mp)'!E84:E16487,0)), " ")} | Y63: {=IFERROR(INDEX('(cata_mp)'!I:I,MATCH(' (Explo_MP)'!S63&' (Explo_MP)'!U63,'(cata_mp)'!C:C&'(cata_mp)'!E:E,0)),"$ 0")} -> $ 0 | AA63: =Y63*Z63 -> 0
U64: - | V64: =IFERROR(INDEX(opción_descripción,MATCH(' (Explo_MP)'!$U64,opción,0))," ") -> Sin Opc. | W64: =IFERROR(VLOOKUP($S64,articulo:costo_última_compra,5,FALSE)," ") | X64: {=IFERROR(INDEX(fecha_última_compra,MATCH(' (Explo_MP)'!S64&' (Explo_MP)'!U64,articulo&opción,0)), " ")} | Y64: =P56 -> id_05 | Z64: =P56&" costo_total:" -> id_05 costo_total: | AA64: =+SUM(AA59:AA63) -> 0
P68: ='REG-DCC-IDP-031 (T_d_C) '!D27 -> id_06
R69: familia_de_operación | S69: articulo | T69: descripción | U69: opción | V69: opción_descripción | W69: unidad | X69: fecha_última_compra | Y69: costo_última_compra | Z69: consumo_unitaruio | AA69: costo_unitario
T70: ='REG-DCC-IDP-031 (T_d_C) '!E27 -> 0
P71: 10 | T71: =IFERROR(VLOOKUP(S71,'(cata_mp)'!C91:I16494,2,FALSE)," ") | U71: - | V71: =IFERROR(INDEX(opción_descripción,MATCH(' (Explo_MP)'!$U71,opción,0))," ") -> Sin Opc. | W71: =IFERROR(VLOOKUP(S71,'(cata_mp)'!C93:I16496,5,FALSE)," ") | X71: {=IFERROR(INDEX('(cata_mp)'!H92:H16495,MATCH(' (Explo_MP)'!S71&' (Explo_MP)'!U71,'(cata_mp)'!C92:C16495&'(cata_mp)'!E92:E16495,0)), " ")} | Y71: {=IFERROR(INDEX('(cata_mp)'!I:I,MATCH(' (Explo_MP)'!S71&' (Explo_MP)'!U71,'(cata_mp)'!C:C&'(cata_mp)'!E:E,0)),"$ 0")} -> $ 0 | AA71: =Y71*Z71 -> 0
T72: =IFERROR(VLOOKUP(S72,'(cata_mp)'!C92:I16495,2,FALSE)," ") | U72: - | V72: =IFERROR(INDEX(opción_descripción,MATCH(' (Explo_MP)'!$U72,opción,0))," ") -> Sin Opc. | W72: =IFERROR(VLOOKUP(S72,'(cata_mp)'!C94:I16497,5,FALSE)," ") | X72: {=IFERROR(INDEX('(cata_mp)'!H93:H16496,MATCH(' (Explo_MP)'!S72&' (Explo_MP)'!U72,'(cata_mp)'!C93:C16496&'(cata_mp)'!E93:E16496,0)), " ")} | Y72: {=IFERROR(INDEX('(cata_mp)'!I:I,MATCH(' (Explo_MP)'!S72&' (Explo_MP)'!U72,'(cata_mp)'!C:C&'(cata_mp)'!E:E,0)),"$ 0")} -> $ 0 | AA72: =Y72*Z72 -> 0
T73: =IFERROR(VLOOKUP(S73,'(cata_mp)'!C93:I16496,2,FALSE)," ") | U73: - | V73: =IFERROR(INDEX(opción_descripción,MATCH(' (Explo_MP)'!$U73,opción,0))," ") -> Sin Opc. | W73: =IFERROR(VLOOKUP(S73,'(cata_mp)'!C95:I16498,5,FALSE)," ") | X73: {=IFERROR(INDEX('(cata_mp)'!H94:H16497,MATCH(' (Explo_MP)'!S73&' (Explo_MP)'!U73,'(cata_mp)'!C94:C16497&'(cata_mp)'!E94:E16497,0)), " ")} | Y73: {=IFERROR(INDEX('(cata_mp)'!I:I,MATCH(' (Explo_MP)'!S73&' (Explo_MP)'!U73,'(cata_mp)'!C:C&'(cata_mp)'!E:E,0)),"$ 0")} -> $ 0 | AA73: =Y73*Z73 -> 0
T74: =IFERROR(VLOOKUP(S74,'(cata_mp)'!C94:I16497,2,FALSE)," ") | U74: - | V74: =IFERROR(INDEX(opción_descripción,MATCH(' (Explo_MP)'!$U74,opción,0))," ") -> Sin Opc. | W74: =IFERROR(VLOOKUP(S74,'(cata_mp)'!C96:I16499,5,FALSE)," ") | X74: {=IFERROR(INDEX('(cata_mp)'!H95:H16498,MATCH(' (Explo_MP)'!S74&' (Explo_MP)'!U74,'(cata_mp)'!C95:C16498&'(cata_mp)'!E95:E16498,0)), " ")} | Y74: {=IFERROR(INDEX('(cata_mp)'!I:I,MATCH(' (Explo_MP)'!S74&' (Explo_MP)'!U74,'(cata_mp)'!C:C&'(cata_mp)'!E:E,0)),"$ 0")} -> $ 0 | AA74: =Y74*Z74 -> 0
T75: =IFERROR(VLOOKUP(S75,'(cata_mp)'!C95:I16498,2,FALSE)," ") | U75: - | V75: =IFERROR(INDEX(opción_descripción,MATCH(' (Explo_MP)'!$U75,opción,0))," ") -> Sin Opc. | W75: =IFERROR(VLOOKUP(S75,'(cata_mp)'!C97:I16500,5,FALSE)," ") | X75: {=IFERROR(INDEX('(cata_mp)'!H96:H16499,MATCH(' (Explo_MP)'!S75&' (Explo_MP)'!U75,'(cata_mp)'!C96:C16499&'(cata_mp)'!E96:E16499,0)), " ")} | Y75: {=IFERROR(INDEX('(cata_mp)'!I:I,MATCH(' (Explo_MP)'!S75&' (Explo_MP)'!U75,'(cata_mp)'!C:C&'(cata_mp)'!E:E,0)),"$ 0")} -> $ 0 | AA75: =Y75*Z75 -> 0
T76: =IFERROR(VLOOKUP(S76,'(cata_mp)'!C96:I16499,2,FALSE)," ") | U76: - | V76: =IFERROR(INDEX(opción_descripción,MATCH(' (Explo_MP)'!$U76,opción,0))," ") -> Sin Opc. | W76: =IFERROR(VLOOKUP(S76,'(cata_mp)'!C98:I16501,5,FALSE)," ") | X76: {=IFERROR(INDEX('(cata_mp)'!H97:H16500,MATCH(' (Explo_MP)'!S76&' (Explo_MP)'!U76,'(cata_mp)'!C97:C16500&'(cata_mp)'!E97:E16500,0)), " ")} | Y76: {=IFERROR(INDEX('(cata_mp)'!I:I,MATCH(' (Explo_MP)'!S76&' (Explo_MP)'!U76,'(cata_mp)'!C:C&'(cata_mp)'!E:E,0)),"$ 0")} -> $ 0 | AA76: =Y76*Z76 -> 0
T77: =IFERROR(VLOOKUP(S77,'(cata_mp)'!C97:I16500,2,FALSE)," ") | U77: - | V77: =IFERROR(INDEX(opción_descripción,MATCH(' (Explo_MP)'!$U77,opción,0))," ") -> Sin Opc. | W77: =IFERROR(VLOOKUP(S77,'(cata_mp)'!C99:I16502,5,FALSE)," ") | X77: {=IFERROR(INDEX('(cata_mp)'!H98:H16501,MATCH(' (Explo_MP)'!S77&' (Explo_MP)'!U77,'(cata_mp)'!C98:C16501&'(cata_mp)'!E98:E16501,0)), " ")} | Y77: {=IFERROR(INDEX('(cata_mp)'!I:I,MATCH(' (Explo_MP)'!S77&' (Explo_MP)'!U77,'(cata_mp)'!C:C&'(cata_mp)'!E:E,0)),"$ 0")} -> $ 0 | AA77: =Y77*Z77 -> 0
T78: =IFERROR(VLOOKUP(S78,'(cata_mp)'!C98:I16501,2,FALSE)," ") | U78: - | V78: =IFERROR(INDEX(opción_descripción,MATCH(' (Explo_MP)'!$U78,opción,0))," ") -> Sin Opc. | W78: =IFERROR(VLOOKUP(S78,'(cata_mp)'!C100:I16503,5,FALSE)," ") | X78: {=IFERROR(INDEX('(cata_mp)'!H99:H16502,MATCH(' (Explo_MP)'!S78&' (Explo_MP)'!U78,'(cata_mp)'!C99:C16502&'(cata_mp)'!E99:E16502,0)), " ")} | Y78: {=IFERROR(INDEX('(cata_mp)'!I:I,MATCH(' (Explo_MP)'!S78&' (Explo_MP)'!U78,'(cata_mp)'!C:C&'(cata_mp)'!E:E,0)),"$ 0")} -> $ 0 | AA78: =Y78*Z78 -> 0
T79: =IFERROR(VLOOKUP(S79,'(cata_mp)'!C99:I16502,2,FALSE)," ") | U79: - | V79: =IFERROR(INDEX(opción_descripción,MATCH(' (Explo_MP)'!$U79,opción,0))," ") -> Sin Opc. | W79: =IFERROR(VLOOKUP(S79,'(cata_mp)'!C101:I16504,5,FALSE)," ") | X79: {=IFERROR(INDEX('(cata_mp)'!H100:H16503,MATCH(' (Explo_MP)'!S79&' (Explo_MP)'!U79,'(cata_mp)'!C100:C16503&'(cata_mp)'!E100:E16503,0)), " ")} | Y79: {=IFERROR(INDEX('(cata_mp)'!I:I,MATCH(' (Explo_MP)'!S79&' (Explo_MP)'!U79,'(cata_mp)'!C:C&'(cata_mp)'!E:E,0)),"$ 0")} -> $ 0 | AA79: =Y79*Z79 -> 0
T80: =IFERROR(VLOOKUP(S80,'(cata_mp)'!C100:I16503,2,FALSE)," ") | U80: - | V80: =IFERROR(INDEX(opción_descripción,MATCH(' (Explo_MP)'!$U80,opción,0))," ") -> Sin Opc. | W80: =IFERROR(VLOOKUP(S80,'(cata_mp)'!C102:I16505,5,FALSE)," ") | X80: {=IFERROR(INDEX('(cata_mp)'!H101:H16504,MATCH(' (Explo_MP)'!S80&' (Explo_MP)'!U80,'(cata_mp)'!C101:C16504&'(cata_mp)'!E101:E16504,0)), " ")} | Y80: {=IFERROR(INDEX('(cata_mp)'!I:I,MATCH(' (Explo_MP)'!S80&' (Explo_MP)'!U80,'(cata_mp)'!C:C&'(cata_mp)'!E:E,0)),"$ 0")} -> $ 0 | AA80: =Y80*Z80 -> 0
T81: =IFERROR(VLOOKUP(S81,'(cata_mp)'!C101:I16504,2,FALSE)," ") | U81: - | V81: =IFERROR(INDEX(opción_descripción,MATCH(' (Explo_MP)'!$U81,opción,0))," ") -> Sin Opc. | W81: =IFERROR(VLOOKUP(S81,'(cata_mp)'!C103:I16506,5,FALSE)," ") | X81: {=IFERROR(INDEX('(cata_mp)'!H102:H16505,MATCH(' (Explo_MP)'!S81&' (Explo_MP)'!U81,'(cata_mp)'!C102:C16505&'(cata_mp)'!E102:E16505,0)), " ")} | Y81: {=IFERROR(INDEX('(cata_mp)'!I:I,MATCH(' (Explo_MP)'!S81&' (Explo_MP)'!U81,'(cata_mp)'!C:C&'(cata_mp)'!E:E,0)),"$ 0")} -> $ 0 | AA81: =Y81*Z81 -> 0
T82: =IFERROR(VLOOKUP(S82,'(cata_mp)'!C102:I16505,2,FALSE)," ") | U82: - | V82: =IFERROR(INDEX(opción_descripción,MATCH(' (Explo_MP)'!$U82,opción,0))," ") -> Sin Opc. | W82: =IFERROR(VLOOKUP(S82,'(cata_mp)'!C104:I16507,5,FALSE)," ") | X82: {=IFERROR(INDEX('(cata_mp)'!H103:H16506,MATCH(' (Explo_MP)'!S82&' (Explo_MP)'!U82,'(cata_mp)'!C103:C16506&'(cata_mp)'!E103:E16506,0)), " ")} | Y82: {=IFERROR(INDEX('(cata_mp)'!I:I,MATCH(' (Explo_MP)'!S82&' (Explo_MP)'!U82,'(cata_mp)'!C:C&'(cata_mp)'!E:E,0)),"$ 0")} -> $ 0 | AA82: =Y82*Z82 -> 0
T83: =IFERROR(VLOOKUP(S83,'(cata_mp)'!C103:I16506,2,FALSE)," ") | U83: - | V83: =IFERROR(INDEX(opción_descripción,MATCH(' (Explo_MP)'!$U83,opción,0))," ") -> Sin Opc. | W83: =IFERROR(VLOOKUP(S83,'(cata_mp)'!C105:I16508,5,FALSE)," ") | X83: {=IFERROR(INDEX('(cata_mp)'!H104:H16507,MATCH(' (Explo_MP)'!S83&' (Explo_MP)'!U83,'(cata_mp)'!C104:C16507&'(cata_mp)'!E104:E16507,0)), " ")} | Y83: {=IFERROR(INDEX('(cata_mp)'!I:I,MATCH(' (Explo_MP)'!S83&' (Explo_MP)'!U83,'(cata_mp)'!C:C&'(cata_mp)'!E:E,0)),"$ 0")} -> $ 0 | AA83: =Y83*Z83 -> 0
Y84: =P68 -> id_06 | Z84: =P68&" costo_total:" -> id_06 costo_total: | AA84: =+SUM(AA71:AA83) -> 0
P88: ='REG-DCC-IDP-031 (T_d_C) '!D28 -> id_07
R89: familia_de_operación | S89: articulo | T89: descripción | U89: opción | V89: opción_descripción | W89: unidad | X89: fecha_última_compra | Y89: costo_última_compra | Z89: consumo_unitaruio | AA89: costo_unitario
T90: ='REG-DCC-IDP-031 (T_d_C) '!G28 -> 0
T91: =IFERROR(VLOOKUP(S91,'(cata_mp)'!C111:I16514,2,FALSE)," ") | U91: - | V91: =IFERROR(INDEX(opción_descripción,MATCH(' (Explo_MP)'!$U91,opción,0))," ") -> Sin Opc. | W91: =IFERROR(VLOOKUP(S91,'(cata_mp)'!C113:I16516,5,FALSE)," ") | X91: {=IFERROR(INDEX('(cata_mp)'!H112:H16515,MATCH(' (Explo_MP)'!S91&' (Explo_MP)'!U91,'(cata_mp)'!C112:C16515&'(cata_mp)'!E112:E16515,0)), " ")} | Y91: {=IFERROR(INDEX('(cata_mp)'!I:I,MATCH(' (Explo_MP)'!S91&' (Explo_MP)'!U91,'(cata_mp)'!C:C&'(cata_mp)'!E:E,0)),"$ 0")} -> $ 0 | AA91: =Y91*Z91 -> 0
T92: =IFERROR(VLOOKUP(S92,'(cata_mp)'!C112:I16515,2,FALSE)," ") | U92: - | V92: =IFERROR(INDEX(opción_descripción,MATCH(' (Explo_MP)'!$U92,opción,0))," ") -> Sin Opc. | W92: =IFERROR(VLOOKUP(S92,'(cata_mp)'!C114:I16517,5,FALSE)," ") | X92: {=IFERROR(INDEX('(cata_mp)'!H113:H16516,MATCH(' (Explo_MP)'!S92&' (Explo_MP)'!U92,'(cata_mp)'!C113:C16516&'(cata_mp)'!E113:E16516,0)), " ")} | Y92: {=IFERROR(INDEX('(cata_mp)'!I:I,MATCH(' (Explo_MP)'!S92&' (Explo_MP)'!U92,'(cata_mp)'!C:C&'(cata_mp)'!E:E,0)),"$ 0")} -> $ 0 | AA92: =Y92*Z92 -> 0
T93: =IFERROR(VLOOKUP(S93,'(cata_mp)'!C113:I16516,2,FALSE)," ") | U93: - | V93: =IFERROR(INDEX(opción_descripción,MATCH(' (Explo_MP)'!$U93,opción,0))," ") -> Sin Opc. | W93: =IFERROR(VLOOKUP(S93,'(cata_mp)'!C115:I16518,5,FALSE)," ") | X93: {=IFERROR(INDEX('(cata_mp)'!H114:H16517,MATCH(' (Explo_MP)'!S93&' (Explo_MP)'!U93,'(cata_mp)'!C114:C16517&'(cata_mp)'!E114:E16517,0)), " ")} | Y93: {=IFERROR(INDEX('(cata_mp)'!I:I,MATCH(' (Explo_MP)'!S93&' (Explo_MP)'!U93,'(cata_mp)'!C:C&'(cata_mp)'!E:E,0)),"$ 0")} -> $ 0 | AA93: =Y93*Z93 -> 0
T94: =IFERROR(VLOOKUP(S94,'(cata_mp)'!C114:I16517,2,FALSE)," ") | U94: - | V94: =IFERROR(INDEX(opción_descripción,MATCH(' (Explo_MP)'!$U94,opción,0))," ") -> Sin Opc. | W94: =IFERROR(VLOOKUP(S94,'(cata_mp)'!C116:I16519,5,FALSE)," ") | X94: {=IFERROR(INDEX('(cata_mp)'!H115:H16518,MATCH(' (Explo_MP)'!S94&' (Explo_MP)'!U94,'(cata_mp)'!C115:C16518&'(cata_mp)'!E115:E16518,0)), " ")} | Y94: {=IFERROR(INDEX('(cata_mp)'!I:I,MATCH(' (Explo_MP)'!S94&' (Explo_MP)'!U94,'(cata_mp)'!C:C&'(cata_mp)'!E:E,0)),"$ 0")} -> $ 0 | AA94: =Y94*Z94 -> 0
T95: =IFERROR(VLOOKUP(S95,'(cata_mp)'!C115:I16518,2,FALSE)," ") | U95: - | V95: =IFERROR(INDEX(opción_descripción,MATCH(' (Explo_MP)'!$U95,opción,0))," ") -> Sin Opc. | W95: =IFERROR(VLOOKUP(S95,'(cata_mp)'!C117:I16520,5,FALSE)," ") | X95: {=IFERROR(INDEX('(cata_mp)'!H116:H16519,MATCH(' (Explo_MP)'!S95&' (Explo_MP)'!U95,'(cata_mp)'!C116:C16519&'(cata_mp)'!E116:E16519,0)), " ")} | Y95: {=IFERROR(INDEX('(cata_mp)'!I:I,MATCH(' (Explo_MP)'!S95&' (Explo_MP)'!U95,'(cata_mp)'!C:C&'(cata_mp)'!E:E,0)),"$ 0")} -> $ 0 | AA95: =Y95*Z95 -> 0
T96: =IFERROR(VLOOKUP(S96,'(cata_mp)'!C116:I16519,2,FALSE)," ") | U96: - | V96: =IFERROR(INDEX(opción_descripción,MATCH(' (Explo_MP)'!$U96,opción,0))," ") -> Sin Opc. | W96: =IFERROR(VLOOKUP(S96,'(cata_mp)'!C118:I16521,5,FALSE)," ") | X96: {=IFERROR(INDEX('(cata_mp)'!H117:H16520,MATCH(' (Explo_MP)'!S96&' (Explo_MP)'!U96,'(cata_mp)'!C117:C16520&'(cata_mp)'!E117:E16520,0)), " ")} | Y96: {=IFERROR(INDEX('(cata_mp)'!I:I,MATCH(' (Explo_MP)'!S96&' (Explo_MP)'!U96,'(cata_mp)'!C:C&'(cata_mp)'!E:E,0)),"$ 0")} -> $ 0 | AA96: =Y96*Z96 -> 0
T97: =IFERROR(VLOOKUP(S97,'(cata_mp)'!C117:I16520,2,FALSE)," ") | U97: - | V97: =IFERROR(INDEX(opción_descripción,MATCH(' (Explo_MP)'!$U97,opción,0))," ") -> Sin Opc. | W97: =IFERROR(VLOOKUP(S97,'(cata_mp)'!C119:I16522,5,FALSE)," ") | X97: {=IFERROR(INDEX('(cata_mp)'!H118:H16521,MATCH(' (Explo_MP)'!S97&' (Explo_MP)'!U97,'(cata_mp)'!C118:C16521&'(cata_mp)'!E118:E16521,0)), " ")} | Y97: {=IFERROR(INDEX('(cata_mp)'!I:I,MATCH(' (Explo_MP)'!S97&' (Explo_MP)'!U97,'(cata_mp)'!C:C&'(cata_mp)'!E:E,0)),"$ 0")} -> $ 0 | AA97: =Y97*Z97 -> 0
Y98: =P88 -> id_07 | Z98: =P88&" costo_total:" -> id_07 costo_total: | AA98: =+SUM(AA91:AA97) -> 0
P102: ='REG-DCC-IDP-031 (T_d_C) '!D29 -> id_08
R103: familia_de_operación | S103: articulo | T103: descripción | U103: opción | V103: opción_descripción | W103: unidad | X103: fecha_última_compra | Y103: costo_última_compra | Z103: consumo_unitaruio | AA103: costo_unitario
T104: ='REG-DCC-IDP-031 (T_d_C) '!G29 -> 0
P105: 30 | T105: =IFERROR(VLOOKUP(S105,'(cata_mp)'!C125:I16528,2,FALSE)," ") | U105: - | V105: =IFERROR(INDEX(opción_descripción,MATCH(' (Explo_MP)'!$U105,opción,0))," ") -> Sin Opc. | W105: =IFERROR(VLOOKUP(S105,'(cata_mp)'!C127:I16530,5,FALSE)," ") | X105: {=IFERROR(INDEX('(cata_mp)'!H126:H16529,MATCH(' (Explo_MP)'!S105&' (Explo_MP)'!U105,'(cata_mp)'!C126:C16529&'(cata_mp)'!E126:E16529,0)), " ")} | Y105: {=IFERROR(INDEX('(cata_mp)'!I:I,MATCH(' (Explo_MP)'!S105&' (Explo_MP)'!U105,'(cata_mp)'!C:C&'(cata_mp)'!E:E,0)),"$ 0")} -> $ 0 | AA105: =Y105*Z105 -> 0
T106: =IFERROR(VLOOKUP(S106,'(cata_mp)'!C126:I16529,2,FALSE)," ") | U106: - | V106: =IFERROR(INDEX(opción_descripción,MATCH(' (Explo_MP)'!$U106,opción,0))," ") -> Sin Opc. | W106: =IFERROR(VLOOKUP(S106,'(cata_mp)'!C128:I16531,5,FALSE)," ") | X106: {=IFERROR(INDEX('(cata_mp)'!H127:H16530,MATCH(' (Explo_MP)'!S106&' (Explo_MP)'!U106,'(cata_mp)'!C127:C16530&'(cata_mp)'!E127:E16530,0)), " ")} | Y106: {=IFERROR(INDEX('(cata_mp)'!I:I,MATCH(' (Explo_MP)'!S106&' (Explo_MP)'!U106,'(cata_mp)'!C:C&'(cata_mp)'!E:E,0)),"$ 0")} -> $ 0 | AA106: =Y106*Z106 -> 0
T107: =IFERROR(VLOOKUP(S107,'(cata_mp)'!C127:I16530,2,FALSE)," ") | U107: - | V107: =IFERROR(INDEX(opción_descripción,MATCH(' (Explo_MP)'!$U107,opción,0))," ") -> Sin Opc. | W107: =IFERROR(VLOOKUP(S107,'(cata_mp)'!C129:I16532,5,FALSE)," ") | X107: {=IFERROR(INDEX('(cata_mp)'!H128:H16531,MATCH(' (Explo_MP)'!S107&' (Explo_MP)'!U107,'(cata_mp)'!C128:C16531&'(cata_mp)'!E128:E16531,0)), " ")} | Y107: {=IFERROR(INDEX('(cata_mp)'!I:I,MATCH(' (Explo_MP)'!S107&' (Explo_MP)'!U107,'(cata_mp)'!C:C&'(cata_mp)'!E:E,0)),"$ 0")} -> $ 0 | AA107: =Y107*Z107 -> 0
T108: =IFERROR(VLOOKUP(S108,'(cata_mp)'!C128:I16531,2,FALSE)," ") | U108: - | V108: =IFERROR(INDEX(opción_descripción,MATCH(' (Explo_MP)'!$U108,opción,0))," ") -> Sin Opc. | W108: =IFERROR(VLOOKUP(S108,'(cata_mp)'!C130:I16533,5,FALSE)," ") | X108: {=IFERROR(INDEX('(cata_mp)'!H129:H16532,MATCH(' (Explo_MP)'!S108&' (Explo_MP)'!U108,'(cata_mp)'!C129:C16532&'(cata_mp)'!E129:E16532,0)), " ")} | Y108: {=IFERROR(INDEX('(cata_mp)'!I:I,MATCH(' (Explo_MP)'!S108&' (Explo_MP)'!U108,'(cata_mp)'!C:C&'(cata_mp)'!E:E,0)),"$ 0")} -> $ 0 | AA108: =Y108*Z108 -> 0
T109: =IFERROR(VLOOKUP(S109,'(cata_mp)'!C129:I16532,2,FALSE)," ") | U109: - | V109: =IFERROR(INDEX(opción_descripción,MATCH(' (Explo_MP)'!$U109,opción,0))," ") -> Sin Opc. | W109: =IFERROR(VLOOKUP(S109,'(cata_mp)'!C131:I16534,5,FALSE)," ") | X109: {=IFERROR(INDEX('(cata_mp)'!H130:H16533,MATCH(' (Explo_MP)'!S109&' (Explo_MP)'!U109,'(cata_mp)'!C130:C16533&'(cata_mp)'!E130:E16533,0)), " ")} | Y109: {=IFERROR(INDEX('(cata_mp)'!I:I,MATCH(' (Explo_MP)'!S109&' (Explo_MP)'!U109,'(cata_mp)'!C:C&'(cata_mp)'!E:E,0)),"$ 0")} -> $ 0 | AA109: =Y109*Z109 -> 0
T110: =IFERROR(VLOOKUP(S110,'(cata_mp)'!C130:I16533,2,FALSE)," ") | U110: - | V110: =IFERROR(INDEX(opción_descripción,MATCH(' (Explo_MP)'!$U110,opción,0))," ") -> Sin Opc. | W110: =IFERROR(VLOOKUP(S110,'(cata_mp)'!C132:I16535,5,FALSE)," ") | X110: {=IFERROR(INDEX('(cata_mp)'!H131:H16534,MATCH(' (Explo_MP)'!S110&' (Explo_MP)'!U110,'(cata_mp)'!C131:C16534&'(cata_mp)'!E131:E16534,0)), " ")} | Y110: {=IFERROR(INDEX('(cata_mp)'!I:I,MATCH(' (Explo_MP)'!S110&' (Explo_MP)'!U110,'(cata_mp)'!C:C&'(cata_mp)'!E:E,0)),"$ 0")} -> $ 0 | AA110: =Y110*Z110 -> 0
T111: =IFERROR(VLOOKUP(S111,'(cata_mp)'!C131:I16534,2,FALSE)," ") | U111: - | V111: =IFERROR(INDEX(opción_descripción,MATCH(' (Explo_MP)'!$U111,opción,0))," ") -> Sin Opc. | W111: =IFERROR(VLOOKUP(S111,'(cata_mp)'!C133:I16536,5,FALSE)," ") | X111: {=IFERROR(INDEX('(cata_mp)'!H132:H16535,MATCH(' (Explo_MP)'!S111&' (Explo_MP)'!U111,'(cata_mp)'!C132:C16535&'(cata_mp)'!E132:E16535,0)), " ")} | Y111: {=IFERROR(INDEX('(cata_mp)'!I:I,MATCH(' (Explo_MP)'!S111&' (Explo_MP)'!U111,'(cata_mp)'!C:C&'(cata_mp)'!E:E,0)),"$ 0")} -> $ 0 | AA111: =Y111*Z111 -> 0
T112: =IFERROR(VLOOKUP(S112,'(cata_mp)'!C132:I16535,2,FALSE)," ") | U112: - | V112: =IFERROR(INDEX(opción_descripción,MATCH(' (Explo_MP)'!$U112,opción,0))," ") -> Sin Opc. | W112: =IFERROR(VLOOKUP(S112,'(cata_mp)'!C134:I16537,5,FALSE)," ") | X112: {=IFERROR(INDEX('(cata_mp)'!H133:H16536,MATCH(' (Explo_MP)'!S112&' (Explo_MP)'!U112,'(cata_mp)'!C133:C16536&'(cata_mp)'!E133:E16536,0)), " ")} | Y112: {=IFERROR(INDEX('(cata_mp)'!I:I,MATCH(' (Explo_MP)'!S112&' (Explo_MP)'!U112,'(cata_mp)'!C:C&'(cata_mp)'!E:E,0)),"$ 0")} -> $ 0 | AA112: =Y112*Z112 -> 0
T113: =IFERROR(VLOOKUP(S113,'(cata_mp)'!C133:I16536,2,FALSE)," ") | U113: - | V113: =IFERROR(INDEX(opción_descripción,MATCH(' (Explo_MP)'!$U113,opción,0))," ") -> Sin Opc. | W113: =IFERROR(VLOOKUP(S113,'(cata_mp)'!C135:I16538,5,FALSE)," ") | X113: {=IFERROR(INDEX('(cata_mp)'!H134:H16537,MATCH(' (Explo_MP)'!S113&' (Explo_MP)'!U113,'(cata_mp)'!C134:C16537&'(cata_mp)'!E134:E16537,0)), " ")} | Y113: {=IFERROR(INDEX('(cata_mp)'!I:I,MATCH(' (Explo_MP)'!S113&' (Explo_MP)'!U113,'(cata_mp)'!C:C&'(cata_mp)'!E:E,0)),"$ 0")} -> $ 0 | AA113: =Y113*Z113 -> 0
T114: =IFERROR(VLOOKUP(S114,'(cata_mp)'!C134:I16537,2,FALSE)," ") | U114: - | V114: =IFERROR(INDEX(opción_descripción,MATCH(' (Explo_MP)'!$U114,opción,0))," ") -> Sin Opc. | W114: =IFERROR(VLOOKUP(S114,'(cata_mp)'!C136:I16539,5,FALSE)," ") | X114: {=IFERROR(INDEX('(cata_mp)'!H135:H16538,MATCH(' (Explo_MP)'!S114&' (Explo_MP)'!U114,'(cata_mp)'!C135:C16538&'(cata_mp)'!E135:E16538,0)), " ")} | Y114: {=IFERROR(INDEX('(cata_mp)'!I:I,MATCH(' (Explo_MP)'!S114&' (Explo_MP)'!U114,'(cata_mp)'!C:C&'(cata_mp)'!E:E,0)),"$ 0")} -> $ 0 | AA114: =Y114*Z114 -> 0
Y115: =P102 -> id_08 | Z115: =P102&" costo_total:" -> id_08 costo_total: | AA115: =+SUM(AA105:AA114) -> 0
P119: ='REG-DCC-IDP-031 (T_d_C) '!D30 -> id_09
R120: familia_de_operación | S120: articulo | T120: descripción | U120: opción | V120: opción_descripción | W120: unidad | X120: fecha_última_compra | Y120: costo_última_compra | Z120: consumo_unitaruio | AA120: costo_unitario
T121: ='REG-DCC-IDP-031 (T_d_C) '!G30 -> 0
P122: 30 | T122: =IFERROR(VLOOKUP(S122,'(cata_mp)'!C142:I16545,2,FALSE)," ") | U122: - | V122: =IFERROR(INDEX(opción_descripción,MATCH(' (Explo_MP)'!$U122,opción,0))," ") -> Sin Opc. | W122: =IFERROR(VLOOKUP(S122,'(cata_mp)'!C144:I16547,5,FALSE)," ") | X122: {=IFERROR(INDEX('(cata_mp)'!H143:H16546,MATCH(' (Explo_MP)'!S122&' (Explo_MP)'!U122,'(cata_mp)'!C143:C16546&'(cata_mp)'!E143:E16546,0)), " ")} | Y122: {=IFERROR(INDEX('(cata_mp)'!I:I,MATCH(' (Explo_MP)'!S122&' (Explo_MP)'!U122,'(cata_mp)'!C:C&'(cata_mp)'!E:E,0)),"$ 0")} -> $ 0 | AA122: =Y122*Z122 -> 0
T123: =IFERROR(VLOOKUP(S123,'(cata_mp)'!C143:I16546,2,FALSE)," ") | U123: - | V123: =IFERROR(INDEX(opción_descripción,MATCH(' (Explo_MP)'!$U123,opción,0))," ") -> Sin Opc. | W123: =IFERROR(VLOOKUP(S123,'(cata_mp)'!C145:I16548,5,FALSE)," ") | X123: {=IFERROR(INDEX('(cata_mp)'!H144:H16547,MATCH(' (Explo_MP)'!S123&' (Explo_MP)'!U123,'(cata_mp)'!C144:C16547&'(cata_mp)'!E144:E16547,0)), " ")} | Y123: {=IFERROR(INDEX('(cata_mp)'!I:I,MATCH(' (Explo_MP)'!S123&' (Explo_MP)'!U123,'(cata_mp)'!C:C&'(cata_mp)'!E:E,0)),"$ 0")} -> $ 0 | AA123: =Y123*Z123 -> 0
T124: =IFERROR(VLOOKUP(S124,'(cata_mp)'!C144:I16547,2,FALSE)," ") | U124: - | V124: =IFERROR(INDEX(opción_descripción,MATCH(' (Explo_MP)'!$U124,opción,0))," ") -> Sin Opc. | W124: =IFERROR(VLOOKUP(S124,'(cata_mp)'!C146:I16549,5,FALSE)," ") | X124: {=IFERROR(INDEX('(cata_mp)'!H145:H16548,MATCH(' (Explo_MP)'!S124&' (Explo_MP)'!U124,'(cata_mp)'!C145:C16548&'(cata_mp)'!E145:E16548,0)), " ")} | Y124: {=IFERROR(INDEX('(cata_mp)'!I:I,MATCH(' (Explo_MP)'!S124&' (Explo_MP)'!U124,'(cata_mp)'!C:C&'(cata_mp)'!E:E,0)),"$ 0")} -> $ 0 | AA124: =Y124*Z124 -> 0
T125: =IFERROR(VLOOKUP(S125,'(cata_mp)'!C145:I16548,2,FALSE)," ") | U125: - | V125: =IFERROR(INDEX(opción_descripción,MATCH(' (Explo_MP)'!$U125,opción,0))," ") -> Sin Opc. | W125: =IFERROR(VLOOKUP(S125,'(cata_mp)'!C147:I16550,5,FALSE)," ") | X125: {=IFERROR(INDEX('(cata_mp)'!H146:H16549,MATCH(' (Explo_MP)'!S125&' (Explo_MP)'!U125,'(cata_mp)'!C146:C16549&'(cata_mp)'!E146:E16549,0)), " ")} | Y125: {=IFERROR(INDEX('(cata_mp)'!I:I,MATCH(' (Explo_MP)'!S125&' (Explo_MP)'!U125,'(cata_mp)'!C:C&'(cata_mp)'!E:E,0)),"$ 0")} -> $ 0 | AA125: =Y125*Z125 -> 0
T126: =IFERROR(VLOOKUP(S126,'(cata_mp)'!C146:I16549,2,FALSE)," ") | U126: - | V126: =IFERROR(INDEX(opción_descripción,MATCH(' (Explo_MP)'!$U126,opción,0))," ") -> Sin Opc. | W126: =IFERROR(VLOOKUP(S126,'(cata_mp)'!C148:I16551,5,FALSE)," ") | X126: {=IFERROR(INDEX('(cata_mp)'!H147:H16550,MATCH(' (Explo_MP)'!S126&' (Explo_MP)'!U126,'(cata_mp)'!C147:C16550&'(cata_mp)'!E147:E16550,0)), " ")} | Y126: {=IFERROR(INDEX('(cata_mp)'!I:I,MATCH(' (Explo_MP)'!S126&' (Explo_MP)'!U126,'(cata_mp)'!C:C&'(cata_mp)'!E:E,0)),"$ 0")} -> $ 0 | AA126: =Y126*Z126 -> 0
...

Sheet (cata_mp)
C2: Consulta MP, MD y MI última Compra_20260410
C3: articulo | D3: descripción | E3: opción | F3: opción_descripción | G3: unidad | H3: fecha_última_compra | I3: costo_última_compra | J3: largo | K3: ancho | L3: desarrollo | M3: clave_comercial
C4: MVLPTA270000F0 | D4: (SCREW CAPS FOR VITRINE) TAPA AUTO ADHERIBLE PARA RETOCAR COLOR BLANCO ABSOLUTO 4159 MASISA (PLANILLA) - "TADB4159" | E4: - | F4: Sin Opc. | G4: pieza | H4: 43424 | I4: 9 | L4: 0 | M4: TADB4159
C5: MLEAAR03000000 | D5: 1:20 R/C VW BEETLE 4718487746361 27026 - "27026" | E5: - | F5: Sin Opc. | G5: pieza | H5: 43829 | I5: 119.73 | L5: 0 | M5: 27026
C6: MLEAAR17000000 | D6: 1:24 LAMBORGHINIHURACAN PERFORMANTE VERSION 4718487746699 27059 - "27059" | E6: - | F6: Sin Opc. | G6: pieza | H6: 43829 | I6: 119.97 | L6: 0 | M6: 27059
C7: MLEAAR16000000 | D7: 1:24 LAMBORGHINILP770-4 CENTENNIAL EDITION 4718487746354 27058 - "27058" | E7: - | F7: Sin Opc. | G7: pieza | H7: 43829 | I7: 121.66 | L7: 0 | M7: 27058
C8: MLEAAR15000000 | D8: 1:24 R/C AUDI R8 4718487746347 27057 - "27057" | E8: - | F8: Sin Opc. | G8: pieza | H8: 43829 | I8: 117.56 | L8: 0 | M8: 27057
C9: MLEAAR10000000 | D9: 1:24 R/C BENTLY GT SUPERSPORT 4718487746439 27040 - "27040" | E9: - | F9: Sin Opc. | G9: pieza | H9: 43829 | I9: 117.56 | L9: 0 | M9: 27040
C10: MLEAAR07000000 | D10: 1:24 R/C BENZ SLS 4718487746408 27046 - "27046" | E10: - | F10: Sin Opc. | G10: pieza | H10: 43829 | I10: 117.56 | L10: 0 | M10: 27046
C11: MLEAAR12000000 | D11: 1:24 R/C FORD MUSTANG GT500 4718487746453 27050 - "27050" | E11: - | F11: Sin Opc. | G11: pieza | H11: 43829 | I11: 117.56 | L11: 0 | M11: 27050
C12: MLEAAR08000000 | D12: 1:24 R/C HUMMER H2 4718487746415 27020 - "27020" | E12: - | F12: Sin Opc. | G12: pieza | H12: 43829 | I12: 133.22 | L12: 0 | M12: 27020
C13: MLEAAR18000000 | D13: 1:24 R/C LAMBORGHINI LP670 4718487745104 - "" | E13: - | F13: Sin Opc. | G13: pieza | L13: 0 | M13: 27018
C14: MLEAAR04000000 | D14: 1:24 R/C LAMBORGHINI LP670 4718487746378 27018 - "27018" | E14: - | F14: Sin Opc. | G14: pieza | H14: 43829 | I14: 117.56 | L14: 0 | M14: 27018
C15: MLEAAR06000000 | D15: 1:24 R/C LAMBORGHINI LP700 4718487746392 27021 - "27021 4" | E15: - | F15: Sin Opc. | G15: pieza | H15: 43829 | I15: 117.56 | L15: 0 | M15: 27021 4
C16: MLEAAR05000000 | D16: 1:24 R/C LAMBORGHINI REVENTON 4718487746385 27024 - "27024" | E16: - | F16: Sin Opc. | G16: pieza | H16: 43829 | I16: 117.56 | L16: 0 | M16: 27024
C17: MLEAAR11000000 | D17: 1:24 R/C LAMBORGHINI VENENO 4718487746446 27043 - "27043" | E17: - | F17: Sin Opc. | G17: pieza | H17: 43829 | I17: 117.56 | L17: 0 | M17: 27043
C18: MLEAAR14000000 | D18: 1:24 R/C MASERATI SUV 4718487746330 27056 - "27056" | E18: - | F18: Sin Opc. | G18: pieza | H18: 43829 | I18: 119.73 | L18: 0 | M18: 27026
C19: MLEAAR09000000 | D19: 1:24 R/C MERCEDES BENZ G55 4718487746422 27029 - "27029" | E19: - | F19: Sin Opc. | G19: pieza | H19: 43829 | I19: 119.73 | L19: 0 | M19: 27029
C20: MLEAAR13000000 | D20: 1:24 R/C PAGANI HUAYRA 4718487746323 27042 - "27042" | E20: - | F20: Sin Opc. | G20: pieza | H20: 43829 | I20: 117.56 | L20: 0 | M20: 27042
C21: MLEECA00840000 | D21: 12" PASS THRU BE05926-BK-12 - "BE05926BK12" | E21: - | F21: Sin Opc. | G21: pieza | L21: 0 | M21: BE05926BK12
C22: MDMECA00030000 | D22: 15A RECEPTACLE, C HEIGHT,C1 ,COLOR -- BE52426-3-C-1-C | E22: - | F22: Sin Opc. | G22: pieza | H22: 45881 | I22: 90.73 | L22: 0 | M22: BE52426-3-C-1-C
C23: MDMPLO02020102 | D23: 2 PIEZAS LOGOTIPO LETRA "V" EN CORTE LASER DE 232 X 147 mm ESPESOR 3 mm EN ACRILICO ROJO, SEGUN PLANO, 8 PIEZAS RECTANGULARES DE 510 X 36 mm ESPESOR 3 mm EN ACRILICO ROJO y 2 KIT DE ILUMINACION PARA PEDESTAL VONHAUCKE -- COMEVH132-LOG | E23: - | F23: Sin Opc. | G23: pieza | H23: 45961 | I23: 6632 | L23: 0 | M23: BESMSTRT22EMWHU172LR
C24: MVLECA270000D7 | D24: 2 PUERTOS ELECTRICOS, 1 PUERTO VACIO Y UN USB DE CARGA DOBLE ESTRUCTURA MET. MONTAJE ALTURA DE LA SUPERF. DE TRABAJO, ACCESO A TODOS LOS PUERTOS 72" PULGADAS DE CABLE C/CLAVIJA DE 3 POLOS, SE COLOCA LATERAL, CON KIT DE ADAPTADORES-"BESMSTRT22EMWHU172LR" | E24: - | F24: Sin Opc. | G24: pieza | H24: 43650 | I24: 844.2 | L24: 0 | M24: G10044215
C25: MVLXET000000C1 | D25: 24" (620 mm) GLASS SHELF WITH EDGE STRIP AND LED STRIP (COMPLETE ITEM) 3000 KELVIN "100-442.15" - "G10044215" | E25: - | F25: Sin Opc. | G25: pieza | H25: 43706 | I25: 5217.37 | L25: 0
C26: MVLEEM08000000 | D26: 24" (620MM) GLASS SHELF WITH EDGE STRIP AND LED STRIP (COMPLETE ITEM) 3000 KELVIN "100-442.15" - "" | E26: - | F26: Sin Opc. | G26: pieza | H26: 43277 | I26: 272.06 | L26: 0
C27: MVLEEM03000000 | D27: 24V DISTRIBUTOR, 8-WAY WITH SWITCH INPUT 1640 mm (2x16W) WHITE (13899519) | E27: - | F27: Sin Opc. | G27: pieza | H27: 43642 | I27: 702.91 | L27: 0 | M27: PECANTV32ING
C28: MVLPPC015015E8 | D28: 25 METERS OF WALNUT EDGE BANDING -- "PECANTV32ING" | E28: - | F28: Sin Opc. | G28: m | L28: 0 | M28: DISCSOFT
C29: MVLADC07000000 | D29: 3M HOOKIT SOFT INTERFACE PAD CLAVE : 5777, DE 6" Ø - "DISCSOFT" | E29: - | F29: Sin Opc. | G29: pieza | H29: 43578 | I29: 181.03 | L29: 0 | M29: BE52463-3-42
C30: MDMECA00050000 | D30: 42" F/F PASS THRU -- BE52463-3-42 | E30: - | F30: Sin Opc. | G30: pieza | H30: 45867 | I30: 346.07 | L30: 0 | M30: BE52468-3-42
C31: MDMECA00040000 | D31: 42" F/F/M 3-WAY PASS THRU -- BE52468-3-42 | E31: - | F31: Sin Opc. | G31: pieza | H31: 45867 | I31: 370.39 | L31: 0 | M31: BE52463-3-48
C32: MDMECA00090000 | D32: 48" F/F PASS THRU -- BE52463-3-48 | E32: - | F32: Sin Opc. | G32: pieza | L32: 0 | M32: BE52463-3-54
C33: MDMECA00080000 | D33: 54" F/F PASS THRU -- BE52463-3-54 | E33: - | F33: Sin Opc. | G33: pieza | H33: 45867 | I33: 398.05 | L33: 0 | M33: BE52468-3-54
C34: MDMECA00070000 | D34: 54" F/F/M 3-WAY PASS THRU -- BE52468-3-54 | E34: - | F34: Sin Opc. | G34: pieza | H34: 45881 | I34: 388.81 | L34: 0 | M34: CP-JLR-004
C35: MVLEKE0000D500 | D35: 6 mm GLASS SHELF WITH LED/ALU PROFILE ON FRONT - CP-JLR-004 | E35: - | F35: Sin Opc. | G35: pieza | L35: 0
C36: MVLAKA00190000 | D36: 6mm ACM ILLUMINATED SHELF PR-EH-503 CUBIC - | E36: - | F36: Sin Opc. | G36: pieza | H36: 43342 | I36: 1842.5 | L36: 0 | M36: BE5325121STST15A72
C37: MLEECA00880000 | D37: 72" POWER INFEED CORD BE53251-2-1-ST-ST15A-72 - "BE5325121STST15A72" | E37: - | F37: Sin Opc. | G37: pieza | H37: 45195 | I37: 617.52 | L37: 0 | M37: BE0711672
C38: MLEECA00820000 | D38: 72" SMART INFEED BE07116-72 - "BE0711672" | E38: - | F38: Sin Opc. | G38: pieza | L38: 0 | M38: BE53251-3-1-ST-ST15A
C39: MDMECA00010000 | D39: 72" STRAIGHT CORDED POWER ENTRY, 15AMP, CIRCUIT 1 -- BE53251-3-1-ST-ST15A-72 | E39: - | F39: Sin Opc. | G39: pieza | H39: 45881 | I39: 662.75 | L39: 0
C40: MVLEEM04000000 | D40: 75 W LED CONVERTER WITH US PLUG "138-978.19" - "" | E40: - | F40: Sin Opc. | G40: pieza | H40: 43642 | I40: 2886.74 | L40: 0 | M40: ADVACEEM
C41: MLEXSA12S900G5 | D41: A EN CAJA MODELO ADVACE RESPALDO Y ASIENTO TAPIZADO EN MESH NEGRO, CON BASE DE TRINEO CROMADA, BRAZOS ES UNA SOLA PIEZA - "ADVACEEM" | E41: - | F41: Sin Opc. | G41: pieza | H41: 44215 | I41: 4319 | L41: 0 | M41: 70300701
C42: MLEXBA000000E4 | D42: ABHÄNGEARM D25 X 400 CHROM - PART N° 70300701 - "70300701" | E42: - | F42: Sin Opc. | G42: pieza | H42: 44417 | I42: 2185.78 | L42: 0 | M42: ABBÑPV
C43: MIACAB01000000 | D43: ABRASIVO EN POLVO BLANCO ESPAÑA -- ABBÑPV | E43: - | F43: Sin Opc. | G43: Kg | L43: 0 | M43: EAC525INE-C1BR
C44: MVLAAB01020066 | D44: ABRAZADERA "A" DE 130 X 40 mm, CON SAQUE EN UN EXTREMO Y 4 BARRENOS EN COLD ROLLED -- EAC525INE-C1BR | E44: - | F44: Sin Opc. | G44: pieza | H44: 45862 | I44: 860 | L44: 0 | M44: EAC525INE-CBR
C45: MVLAAB02020066 | D45: ABRAZADERA "B" DE 130 X 40 mm, CON SAQUE EN UN EXTREMO Y 4 BARRENOS EN COLD ROLLED -- EAC525INE-CBR | E45: - | F45: Sin Opc. | G45: pieza | H45: 45862 | I45: 860 | L45: 0 | M45: AID1143
C46: MIMCABID020000 | D46: ABRAZADERA IDEAL 1 1/4" - 3" -- AID1143 -- | E46: - | F46: Sin Opc. | G46: pza | L46: 0 | M46: AID134334
C47: MIMCABID030000 | D47: ABRAZADERA IDEAL 1 3/4" - 3 3/4"" -- AID134334 -- | E47: - | F47: Sin Opc. | G47: pza | L47: 0 | M47: AID13
C48: MIMCABID040000 | D48: ABRAZADERA IDEAL 1" - 3" -- AID13 -- | E48: - | F48: Sin Opc. | G48: pza | L48: 0 | M48: ADSF112
C49: MIMCABSF050000 | D49: ABRAZADERA SIN FIN 1 1/2" -- ADSF112 -- | E49: - | F49: Sin Opc. | G49: pza | L49: 0 | M49: ADSF134
C50: MIMCABSF060000 | D50: ABRAZADERA SIN FIN 1 3/4" -- ADSF134 -- | E50: - | F50: Sin Opc. | G50: pza | L50: 0 | M50: ADSF1
C51: MIMCABSF100000 | D51: ABRAZADERA SIN FIN 1" -- ADSF1 -- | E51: - | F51: Sin Opc. | G51: pza | L51: 0 | M51: ADSF14
C52: MIMCABSF070000 | D52: ABRAZADERA SIN FIN 1/4" -- ADSF14 -- | E52: - | F52: Sin Opc. | G52: pza | L52: 0 | M52: ABSF34
C53: MLEAAB03040000 | D53: ABRAZADERA SIN FIN 3/4" - "ABSF34" | E53: - | F53: Sin Opc. | G53: pieza | L53: 0 | M53: ADSF34
C54: MIMCABSF080000 | D54: ABRAZADERA SIN FIN 3/4" -- ADSF34 -- | E54: - | F54: Sin Opc. | G54: pza | L54: 0 | M54: ADSF38
C55: MIMCABSF110000 | D55: ABRAZADERA SIN FIN 3/8" -- ADSF38 -- | E55: - | F55: Sin Opc. | G55: pza | H55: 42116 | I55: 4.5 | L55: 0 | M55: GI14960
C56: MIMCABSF140000 | D56: ABRAZADERA SIN FIN Ø 1/4" -- GI14960 -- | E56: - | F56: Sin Opc. | G56: pza | H56: 42289 | I56: 12 | L56: 0 | M56: ADOM114
C57: MIMCABDOM100100 | D57: ABRAZADERA TIPO OMEGA 1 1/4" GALVANIZADA -- ADOM114 -- | E57: - | F57: Sin Opc. | G57: pza | H57: 42296 | I57: 3 | L57: 0 | M57: ADOM01
C58: MIMCABOM090100 | D58: ABRAZADERA TIPO OMEGA 1" GALVANIZADA -- ADOM01 -- | E58: - | F58: Sin Opc. | G58: pza | H58: 42284 | I58: 1.9 | L58: 0 | M58: ADOM12
C59: MIMCABOM110100 | D59: ABRAZADERA TIPO OMEGA 1/2" GALVANIZADA -- ADOM12 -- | E59: - | F59: Sin Opc. | G59: pza | H59: 42402 | I59: 1 | L59: 0 | M59: ADOM34
C60: MIMCABOM080100 | D60: ABRAZADERA TIPO OMEGA 3/4" GALVANIZADA -- ADOM34 -- | E60: - | F60: Sin Opc. | G60: pieza | H60: 45966 | I60: 2.9 | L60: 0 | M60: ABTP14
C61: MVLAABD1030000 | D61: ABRAZADERA TIPO PERRO DE Ø 1/4" - "ABTP14" | E61: - | F61: Sin Opc. | G61: pieza | H61: 44246 | I61: 8.49 | L61: 0 | M61: ABTP116
C62: MLEAABD1050000 | D62: ABRAZADERA TIPO PERRO Ø 1/16" - "ABTP116" | E62: - | F62: Sin Opc. | G62: pieza | H62: 44123 | I62: 3.5 | L62: 0 | M62: ABTP12
C63: MDACAB01000000 | D63: ABRAZADERA TIPO PERRO Ø 1/2" -- ABTP12 | E63: - | F63: Sin Opc. | G63: pieza | H63: 45547 | I63: 24 | L63: 0
C64: MLEAABD1810000 | D64: ABRAZADERA TIPO PERRO Ø 1/8" | E64: - | F64: Sin Opc. | G64: pieza | H64: 45440 | I64: 6 | L64: 0 | M64: ABTP316
C65: MLEAABD1010000 | D65: ABRAZADERA TIPO PERRO Ø 3/16" -- ABTP316 | E65: - | F65: Sin Opc. | G65: pieza | H65: 46042 | I65: 5 | L65: 0 | M65: AGTU12
C66: MIMCABTU090100 | D66: ABRAZADERA TIPO UÑA Ø 1/2" GALVANIZADA -- AGTU12 -- | E66: - | F66: Sin Opc. | G66: pza | H66: 41396 | I66: 1 | L66: 0 | M66: AGTU19
C67: MIMCABTU010100 | D67: ABRAZADERA TIPO UÑA Ø 19 mm GALVANIZADA -- AGTU19 -- | E67: - | F67: Sin Opc. | G67: pza | H67: 41355 | I67: 2 | L67: 0 | M67: ADUN13
C68: MIMCABUN120000 | D68: ABRAZADERA UNICANAL 13 mm -- ADUN13 -- | E68: - | F68: Sin Opc. | G68: pza | H68: 42408 | I68: 3.8 | L68: 0 | M68: ADUN19
C69: MIMCABUN130000 | D69: ABRAZADERA UNICANAL 19 mm -- ADUN19 -- | E69: - | F69: Sin Opc. | G69: pza | H69: 42408 | I69: 4.5 | L69: 0 | M69: HSFIX-POM
C70: MVLALL0000Ñ800 | D70: ABRIDOR MAGNETICO WHATLOCK HAFELE 245.41.798 - "HSFIX-POM" | E70: - | F70: Sin Opc. | G70: pieza | H70: 44778 | I70: 278.49 | L70: 0
C71: MDACAO01000000 | D71: ACBASMPEL35M-TRG -- | E71: - | F71: Sin Opc. | G71: pieza | L71: 0
C72: MDACAO02000000 | D72: ACBASMPOV55M-TRG -- | E72: - | F72: Sin Opc. | G72: pieza | L72: 0
C73: MDACAO03000000 | D73: ACBASMPTP45M-TRG -- | E73: - | F73: Sin Opc. | G73: pieza | L73: 0 | M73: 23744023
C74: MEREAC36950000 | D74: ACCIONADOR DE ARCHIVERO CODIGO "237.44.023" HAFELE - "23744023" | E74: - | F74: Sin Opc. | G74: pieza | L74: 0 | M74: MLEEAC35940030
C75: MLEEAC35940030 | D75: ACCIONADOR PARA CERRADURA ELECTRICA MARCA SOPRANO CON CAJA PLASTICA PARA PROTECCION A LA INTEMPERIE | E75: - | F75: Sin Opc. | G75: pieza | H75: 40396 | I75: 490 | L75: 0 | M75: ABVKOL
C76: MIIPAC00080008 | D76: ACEITE RIETSCHLE MULTILUBE 100 PARA BOMBA DE VAIO MAQUINA KOLMAG -- ABVKOL -- | E76: - | F76: Sin Opc. | G76: lt | L76: 0 | M76: GI1240
C77: MIIPAC00020302 | D77: ACEITE SAE 40 MARCA MOBIL MONOGRADO -- GI1240 -- | E77: - | F77: Sin Opc. | G77: lt | H77: 41415 | I77: 41.53 | L77: 0 | M77: ACS90M
C78: MIIPAC00030300 | D78: ACEITE SAE 90 MARCA MOBIL -- ACS90M -- | E78: - | F78: Sin Opc. | G78: lt | L78: 0 | M78: GI10357
C79: MIIPACAT010001 | D79: ACEITE ALTA TEMPERATURA EON 9000TH 28H109 CUBETA 18.9 LITROS -- GI10357 -- | E79: - | F79: Sin Opc. | G79: pza | L79: 0 | M79: AAMSAE2050W
C80: MIIPACAU090003 | D80: ACEITE AUTOMOTRIZ SAE-2050W CUBETA 19 LITROS -- AAMSAE2050W | E80: - | F80: Sin Opc. | G80: pza | H80: 42495 | I80: 1006.9 | L80: 0 | M80: TRI-X-100
C81: MIIQAC02020000 | D81: ACEITE DE CORTE REFRIGERANTE SOLUBLE EN AGUA TRI-X-100, CUBETA 22.71 LTS - "TRI-X-100" | E81: - | F81: Sin Opc. | G81: pieza | L81: 0 | M81: ACE290M
C82: MVLQAC01010000 | D82: ACEITE DE PENETRACION INSUPERABLE 290-MARCA METATRON (WD40) - "ACE290M" | E82: - | F82: Sin Opc. | G82: pza | H82: 45870 | I82: 542.14 | L82: 0 | M82: ADKOL
C83: MIIPACDI070007 | D83: ACEITE DIATERMICO SR 3, SR 4, SR PS SHELL Y THERMICA OIL B PARA MAQUINA KOLMAG -- ADKOL -- | E83: - | F83: Sin Opc. | G83: lt | L83: 0 | M83: ADTE24
C84: MIIPACHI060900 | D84: ACEITE HIDRAULICO DTE 24 MARCA MOBIL -- ADTE24 -- | E84: - | F84: Sin Opc. | G84: lt | L84: 0 | M84: ADTE24-200
C85: MIIPACHI060902 | D85: ACEITE HIDRAULICO DTE 24 MARCA MOBIL (PRESENTACION EN TAMBO 200 LITROS) -- ADTE24-200 -- | E85: - | F85: Sin Opc. | G85: pza | H85: 41488 | I85: 10072.42 | L85: 0 | M85: ADTE24-19
C86: MIIPACHI060903 | D86: ACEITE HIDRAULICO DTE 24 MARCA MOBIL CUBETA 19 LITROS -- ADTE24-19 -- | E86: - | F86: Sin Opc. | G86: pza | H86: 41488 | I86: 1007.76 | L86: 0 | M86: GI10750
C87: MIQUACHI040902 | D87: ACEITE HIDRAULICO DTE 25 MARCA MOBIL (PRESENTACION EN TAMBO 200 LITROS) -- GI10750 -- | E87: - | F87: Sin Opc. | G87: pza | H87: 42495 | I87: 63.45 | L87: 0 | M87: ADTE2519
C88: MIIPACHI040903 | D88: ACEITE HIDRAULICO DTE 25 MARCA MOBIL CUBETA 19 LITROS -- ADTE2519 -- | E88: - | F88: Sin Opc. | G88: pza | H88: 41711 | I88: 1154 | L88: 0 | M88: AKLRO
C89: MIIPACKL000005 | D89: ACEITE KLUBER PARA MAQUINA ROBER -- AKLRO -- | E89: - | F89: Sin Opc. | G89: pza | L89: 0 | M89: AMTRO
C90: MIIPACMT000005 | D90: ACEITE MOBIL TEMP PARA MAQUINA ROBER -- AMTRO -- | E90: - | F90: Sin Opc. | G90: pza | L90: 0 | M90: AMVO4
C91: MIIPACMB000104 | D91: ACEITE MOBIL VACTRA OIL NUMERO 4 -- AMVO4 | E91: - | F91: Sin Opc. | G91: lt | H91: 41346 | I91: 73.01 | L91: 0 | M91: ACMQBR
C92: MIIPACMB000000 | D92: ACEITE PARA MAQUINA BROTHER -- ACMQBR | E92: - | F92: Sin Opc. | G92: lt | H92: 42090 | I92: 70 | L92: 0 | M92: ACTCM60319
C93: MIIPACTC000409 | D93: ACEITE PARA TRANSFERENCIA DE CALOR MARCA MOBIL - MOBIL THERM 603 CUBETA 19 LITROS -- ACTCM60319 -- | E93: - | F93: Sin Opc. | G93: pza | H93: 42382 | I93: 1060 | L93: 0 | M93: GI12728
C94: MIIPACTR050003 | D94: ACEITE PARA TRANSMISION HD 80W-90 MOBIL (AUTOMATICA) CUBETA 19 LITROS -- GI12728 -- | E94: - | F94: Sin Opc. | G94: pza | L94: 0 | M94: ACPM290SP
C95: MIIPACPM000209 | D95: ACEITE PREMIUM MARCA PENETROL CODIGO M290-SP -- ACPM290SP -- | E95: - | F95: Sin Opc. | G95: lt | H95: 41838 | I95: 272.81 | L95: 0 | M95: GI11970
C96: MIIPACSM000000 | D96: ACEITE SOLUBLE PARA CORTE DE METAL BATRAK 10426 ROSHFRANS -- GI11970 -- | E96: - | F96: Sin Opc. | G96: pza | H96: 43510 | I96: 130.53 | L96: 0 | M96: ACHTCISO46
C97: MIIPACHT090010 | D97: ACEITE SUPER HTC (HIDRO-TURBINA-COMPRESOR) ISO46 CODIGO M612-E46 -- ACHTCISO46 -- | E97: - | F97: Sin Opc. | G97: lt | H97: 41849 | I97: 248.06 | L97: 0 | M97: ACEITERA
C98: MIMCAT00000000 | D98: ACEITERA -- ACEITERA -- | E98: - | F98: Sin Opc. | G98: pza | L98: 0 | M98: AACCPFA1791500
C99: MIQUAEAC000001 | D99: ACELERADOR PARA ADHESIVO CIANOCRILATO CODIGO PFA 1791 PRESENTACION 500 ml -- AACCPFA1791500 -- | E99: - | F99: Sin Opc. | G99: pza | H99: 46072 | I99: 395 | L99: 0 | M99: ACAD
C100: MIQUAEAC020000 | D100: ACELERADOR PARA ADHESIVO CIANOCRILATO TB1791B DE 500 ml -- ACAD -- | E100: - | F100: Sin Opc. | G100: pza | H100: 41327 | I100: 222 | L100: 0 | M100: ACBO
C101: MIIPAB00000000 | D101: ACIDO BORICO -- ACBO -- | E101: - | F101: Sin Opc. | G101: Kg | H101: 45701 | I101: 195 | L101: 0 | M101: ACBA
...

Sheet  (cuanti_mp)
C1: desarrollo y cantidad de pieza a calcular | J1: material | L1: especificación técnica de materia prima seleccionada | P1: consumos por piezas | S1: consumo total | W1: calculadora de aprovechamiento por tablero
C2: parte | D2: n° partes | E2: pieza | F2: n° piezas | G2: largo | H2: ancho | J2: articulo | K2: opción | L2: descripción | M2: u.m. | N2: largo | O2: ancho | P2: consumo de tablero | Q2: consumo de polvo | S2: articulo | T2: descripción | U2: consumo | W2: 3' x 8' | X2: cant. max | Y2: 3' x 10' | Z2: cant. max | AA2: 4' x 8' | AB2: cant. max | AC2: 4' x 10' | AD2: cant. max
A3: 1 | C3: loker | D3: 1 | E3: loker | F3: 23 | G3: 0.1 | H3: 1.22 | J3: MVLSLA05260502 | L3: =IFERROR(VLOOKUP(J3,articulo:clave_comercial,2,0)," ") -> LAMINA NEGRA HOJA 3 X 10 CALIBRE 20 ACERO 1008 - LN20310 | M3: =UPPER(IFERROR(VLOOKUP(J3,articulo:clave_comercial,5,0)," ")) -> HOJA | N3: =IFERROR(IF(VLOOKUP(J3,articulo:clave_comercial,8,0)=0," ",VLOOKUP(J3,articulo:clave_comercial,8,0))," ") | O3: =IFERROR(IF(VLOOKUP(J3,articulo:clave_comercial,9,0)=0," ",VLOOKUP(J3,articulo:clave_comercial,9,0))," ") | P3: =IFERROR(IF(M3="HOJA",(D3*F3)/MAX(ROUNDDOWN((N3/G3),0)*ROUNDDOWN((O3/H3),0),ROUNDDOWN((N3/H3),0)*ROUNDDOWN((O3/G3),0)),IF(M3="HOJA ",(D3*F3)/MAX(ROUNDDOWN((N3/G3),0)*ROUNDDOWN((O3/H3),0),ROUNDDOWN((N3/H3),0)*ROUNDDOWN((O3/G3),0)),IF(M3="M",G3,IF(AND(M3="PIEZA",G3<>0),(D3*F3)/ROUNDDOWN((N3/G3),0),IF(M3="PIEZA",(D3*F3),IF(M3="CAJA",(D3*F3),IF(M3="DM2",(D3*F3),IF(M3="FT",(D3*F3),IF(M3="JGO",(D3*F3),IF(M3="KG",(D3*F3),IF(M3="LB",(D3*F3),IF(M3="LT",(D3*F3),IF(M3="M2",(D3*F3),IF(M3="M3",(D3*F3),IF(M3="ROLLO",(D3*F3),IF(M3="SQYDS",(D3*F3),IF(M3="UD./SERV.",(D3*F3),IF(M3="YD",(D3*F3)," ")))))))))))))))))),"") | Q3: =IFERROR(IF(M3="HOJA",D3*F3*G3*H3*2*0.125,IF(AND(M3="PIEZA",H3=0),D3*F3*G3*VLOOKUP(J3,articulo:clave_comercial,10,0)*0.125,0))," ") -> 0.702 | S3: {=IFERROR(INDEX($J$3:$J$52,MATCH(0,INDEX(COUNTIF(S2:$S$2,$J$3:$J$52),0,0),0))," ")} -> MVLSLA05260502 | T3: {=IFERROR(INDEX($L$3:$L$52,MATCH(0,INDEX(COUNTIF($T2:T$2,$L$3:$L$52),0,0),0))," ")} -> LAMINA NEGRA HOJA 3 X 10 CALIBRE 20 ACERO 1008 - LN20310 | U3: =IFERROR(IF(AND(VLOOKUP(S3,$J$3:$Q$218,4,0)="KG",VLOOKUP(S3,$J$3:$Q$218,7,0)=0,VLOOKUP(S3,$J$3:$Q$218,8,0)=0),SUM($Q$3:$Q$218),SUMIF($J$3:$J$218,S3,$P$3:$P$218)),"") -> 0 | W3: =IFERROR(IF(OR(M3="HOJA",M3="HOJA "),((MAX(ROUNDDOWN((0.915/G3),0)*ROUNDDOWN((2.44/H3),0),ROUNDDOWN((0.915/H3),0)*ROUNDDOWN((2.44/G3),0)))*G3*H3)/(0.915*2.44),""),"") -> 0.98 | X3: =IFERROR(MAX(ROUNDDOWN((0.915/G3),0)*ROUNDDOWN((2.44/H3),0),ROUNDDOWN((0.915/H3),0)*ROUNDDOWN((2.44/G3),0)),"") -> 18 | Y3: =IFERROR(IF(OR(M3="HOJA",M3="HOJA "),((MAX(ROUNDDOWN((0.915/G3),0)*ROUNDDOWN((3.05/H3),0),ROUNDDOWN((0.915/H3),0)*ROUNDDOWN((3.05/G3),0)))*G3*H3)/(0.915*3.05),""),"") -> 0.79 | Z3: =IFERROR(MAX(ROUNDDOWN((0.915/G3),0)*ROUNDDOWN((3.05/H3),0),ROUNDDOWN((0.915/H3),0)*ROUNDDOWN((3.05/G3),0)),"") -> 18 | AA3: =IFERROR(IF(OR(M3="HOJA",M3="HOJA "),((MAX(ROUNDDOWN((1.22/G3),0)*ROUNDDOWN((2.44/H3),0),ROUNDDOWN((1.22/H3),0)*ROUNDDOWN((2.44/G3),0)))*G3*H3)/(1.22*2.44),""),"") -> 0.98 | AB3: =IFERROR(MAX(ROUNDDOWN((1.22/G3),0)*ROUNDDOWN((2.44/H3),0),ROUNDDOWN((1.22/H3),0)*ROUNDDOWN((2.44/G3),0)),"") -> 24 | AC3: =IFERROR(IF(OR(M3="HOJA",M3="HOJA "),((MAX(ROUNDDOWN((1.22/G3),0)*ROUNDDOWN((3.05/H3),0),ROUNDDOWN((1.22/H3),0)*ROUNDDOWN((3.05/G3),0)))*G3*H3)/(1.22*3.05),""),"") -> 0.98 | AD3: =IFERROR(MAX(ROUNDDOWN((1.22/G3),0)*ROUNDDOWN((3.05/H3),0),ROUNDDOWN((1.22/H3),0)*ROUNDDOWN((3.05/G3),0)),"") -> 30
L4: =IFERROR(VLOOKUP(J4,articulo:clave_comercial,2,0)," ") | M4: =UPPER(IFERROR(VLOOKUP(J4,articulo:clave_comercial,5,0)," ")) | N4: =IFERROR(IF(VLOOKUP(J4,articulo:clave_comercial,8,0)=0," ",VLOOKUP(J4,articulo:clave_comercial,8,0))," ") | O4: =IFERROR(IF(VLOOKUP(J4,articulo:clave_comercial,9,0)=0," ",VLOOKUP(J4,articulo:clave_comercial,9,0))," ") | P4: =IFERROR(IF(M4="HOJA",(D4*F4)/MAX(ROUNDDOWN((N4/G4),0)*ROUNDDOWN((O4/H4),0),ROUNDDOWN((N4/H4),0)*ROUNDDOWN((O4/G4),0)),IF(M4="HOJA ",(D4*F4)/MAX(ROUNDDOWN((N4/G4),0)*ROUNDDOWN((O4/H4),0),ROUNDDOWN((N4/H4),0)*ROUNDDOWN((O4/G4),0)),IF(M4="M",G4,IF(AND(M4="PIEZA",G4<>0),(D4*F4)/ROUNDDOWN((N4/G4),0),IF(M4="PIEZA",(D4*F4),IF(M4="CAJA",(D4*F4),IF(M4="DM2",(D4*F4),IF(M4="FT",(D4*F4),IF(M4="JGO",(D4*F4),IF(M4="KG",(D4*F4),IF(M4="LB",(D4*F4),IF(M4="LT",(D4*F4),IF(M4="M2",(D4*F4),IF(M4="M3",(D4*F4),IF(M4="ROLLO",(D4*F4),IF(M4="SQYDS",(D4*F4),IF(M4="UD./SERV.",(D4*F4),IF(M4="YD",(D4*F4)," ")))))))))))))))))),"") | Q4: =IFERROR(IF(M4="HOJA",D4*F4*G4*H4*2*0.125,IF(AND(M4="PIEZA",H4=0),D4*F4*G4*VLOOKUP(J4,articulo:clave_comercial,10,0)*0.125,0))," ") -> 0 | S4: {=IFERROR(INDEX($J$3:$J$52,MATCH(0,INDEX(COUNTIF(S$2:$S3,$J$3:$J$52),0,0),0))," ")} -> 0 | T4: {=IFERROR(INDEX($L$3:$L$52,MATCH(0,INDEX(COUNTIF($T$2:T3,$L$3:$L$52),0,0),0))," ")} | U4: =IFERROR(IF(AND(VLOOKUP(S4,$J$3:$Q$218,4,0)="KG",VLOOKUP(S4,$J$3:$Q$218,7,0)=0,VLOOKUP(S4,$J$3:$Q$218,8,0)=0),SUM($Q$3:$Q$218),SUMIF($J$3:$J$218,S4,$P$3:$P$218)),"") | W4: =IFERROR(IF(OR(M4="HOJA",M4="HOJA "),((MAX(ROUNDDOWN((0.915/G4),0)*ROUNDDOWN((2.44/H4),0),ROUNDDOWN((0.915/H4),0)*ROUNDDOWN((2.44/G4),0)))*G4*H4)/(0.915*2.44),""),"") | X4: =IFERROR(MAX(ROUNDDOWN((0.915/G4),0)*ROUNDDOWN((2.44/H4),0),ROUNDDOWN((0.915/H4),0)*ROUNDDOWN((2.44/G4),0)),"") | Y4: =IFERROR(IF(OR(M4="HOJA",M4="HOJA "),((MAX(ROUNDDOWN((0.915/G4),0)*ROUNDDOWN((3.05/H4),0),ROUNDDOWN((0.915/H4),0)*ROUNDDOWN((3.05/G4),0)))*G4*H4)/(0.915*3.05),""),"") | Z4: =IFERROR(MAX(ROUNDDOWN((0.915/G4),0)*ROUNDDOWN((3.05/H4),0),ROUNDDOWN((0.915/H4),0)*ROUNDDOWN((3.05/G4),0)),"") | AA4: =IFERROR(IF(OR(M4="HOJA",M4="HOJA "),((MAX(ROUNDDOWN((1.22/G4),0)*ROUNDDOWN((2.44/H4),0),ROUNDDOWN((1.22/H4),0)*ROUNDDOWN((2.44/G4),0)))*G4*H4)/(1.22*2.44),""),"") | AB4: =IFERROR(MAX(ROUNDDOWN((1.22/G4),0)*ROUNDDOWN((2.44/H4),0),ROUNDDOWN((1.22/H4),0)*ROUNDDOWN((2.44/G4),0)),"") | AC4: =IFERROR(IF(OR(M4="HOJA",M4="HOJA "),((MAX(ROUNDDOWN((1.22/G4),0)*ROUNDDOWN((3.05/H4),0),ROUNDDOWN((1.22/H4),0)*ROUNDDOWN((3.05/G4),0)))*G4*H4)/(1.22*3.05),""),"") | AD4: =IFERROR(MAX(ROUNDDOWN((1.22/G4),0)*ROUNDDOWN((3.05/H4),0),ROUNDDOWN((1.22/H4),0)*ROUNDDOWN((3.05/G4),0)),"")
L5: =IFERROR(VLOOKUP(J5,articulo:clave_comercial,2,0)," ") | M5: =UPPER(IFERROR(VLOOKUP(J5,articulo:clave_comercial,5,0)," ")) | N5: =IFERROR(IF(VLOOKUP(J5,articulo:clave_comercial,8,0)=0," ",VLOOKUP(J5,articulo:clave_comercial,8,0))," ") | O5: =IFERROR(IF(VLOOKUP(J5,articulo:clave_comercial,9,0)=0," ",VLOOKUP(J5,articulo:clave_comercial,9,0))," ") | P5: =IFERROR(IF(M5="HOJA",(D5*F5)/MAX(ROUNDDOWN((N5/G5),0)*ROUNDDOWN((O5/H5),0),ROUNDDOWN((N5/H5),0)*ROUNDDOWN((O5/G5),0)),IF(M5="HOJA ",(D5*F5)/MAX(ROUNDDOWN((N5/G5),0)*ROUNDDOWN((O5/H5),0),ROUNDDOWN((N5/H5),0)*ROUNDDOWN((O5/G5),0)),IF(M5="M",G5,IF(AND(M5="PIEZA",G5<>0),(D5*F5)/ROUNDDOWN((N5/G5),0),IF(M5="PIEZA",(D5*F5),IF(M5="CAJA",(D5*F5),IF(M5="DM2",(D5*F5),IF(M5="FT",(D5*F5),IF(M5="JGO",(D5*F5),IF(M5="KG",(D5*F5),IF(M5="LB",(D5*F5),IF(M5="LT",(D5*F5),IF(M5="M2",(D5*F5),IF(M5="M3",(D5*F5),IF(M5="ROLLO",(D5*F5),IF(M5="SQYDS",(D5*F5),IF(M5="UD./SERV.",(D5*F5),IF(M5="YD",(D5*F5)," ")))))))))))))))))),"") | Q5: =IFERROR(IF(M5="HOJA",D5*F5*G5*H5*2*0.125,IF(AND(M5="PIEZA",H5=0),D5*F5*G5*VLOOKUP(J5,articulo:clave_comercial,10,0)*0.125,0))," ") -> 0 | S5: {=IFERROR(INDEX($J$3:$J$52,MATCH(0,INDEX(COUNTIF(S$2:$S4,$J$3:$J$52),0,0),0))," ")} | T5: {=IFERROR(INDEX($L$3:$L$52,MATCH(0,INDEX(COUNTIF($T$2:T4,$L$3:$L$52),0,0),0))," ")} | U5: =IFERROR(IF(AND(VLOOKUP(S5,$J$3:$Q$218,4,0)="KG",VLOOKUP(S5,$J$3:$Q$218,7,0)=0,VLOOKUP(S5,$J$3:$Q$218,8,0)=0),SUM($Q$3:$Q$218),SUMIF($J$3:$J$218,S5,$P$3:$P$218)),"") | W5: =IFERROR(IF(OR(M5="HOJA",M5="HOJA "),((MAX(ROUNDDOWN((0.915/G5),0)*ROUNDDOWN((2.44/H5),0),ROUNDDOWN((0.915/H5),0)*ROUNDDOWN((2.44/G5),0)))*G5*H5)/(0.915*2.44),""),"") | X5: =IFERROR(MAX(ROUNDDOWN((0.915/G5),0)*ROUNDDOWN((2.44/H5),0),ROUNDDOWN((0.915/H5),0)*ROUNDDOWN((2.44/G5),0)),"") | Y5: =IFERROR(IF(OR(M5="HOJA",M5="HOJA "),((MAX(ROUNDDOWN((0.915/G5),0)*ROUNDDOWN((3.05/H5),0),ROUNDDOWN((0.915/H5),0)*ROUNDDOWN((3.05/G5),0)))*G5*H5)/(0.915*3.05),""),"") | Z5: =IFERROR(MAX(ROUNDDOWN((0.915/G5),0)*ROUNDDOWN((3.05/H5),0),ROUNDDOWN((0.915/H5),0)*ROUNDDOWN((3.05/G5),0)),"") | AA5: =IFERROR(IF(OR(M5="HOJA",M5="HOJA "),((MAX(ROUNDDOWN((1.22/G5),0)*ROUNDDOWN((2.44/H5),0),ROUNDDOWN((1.22/H5),0)*ROUNDDOWN((2.44/G5),0)))*G5*H5)/(1.22*2.44),""),"") | AB5: =IFERROR(MAX(ROUNDDOWN((1.22/G5),0)*ROUNDDOWN((2.44/H5),0),ROUNDDOWN((1.22/H5),0)*ROUNDDOWN((2.44/G5),0)),"") | AC5: =IFERROR(IF(OR(M5="HOJA",M5="HOJA "),((MAX(ROUNDDOWN((1.22/G5),0)*ROUNDDOWN((3.05/H5),0),ROUNDDOWN((1.22/H5),0)*ROUNDDOWN((3.05/G5),0)))*G5*H5)/(1.22*3.05),""),"") | AD5: =IFERROR(MAX(ROUNDDOWN((1.22/G5),0)*ROUNDDOWN((3.05/H5),0),ROUNDDOWN((1.22/H5),0)*ROUNDDOWN((3.05/G5),0)),"")
L6: =IFERROR(VLOOKUP(J6,articulo:clave_comercial,2,0)," ") | M6: =UPPER(IFERROR(VLOOKUP(J6,articulo:clave_comercial,5,0)," ")) | N6: =IFERROR(IF(VLOOKUP(J6,articulo:clave_comercial,8,0)=0," ",VLOOKUP(J6,articulo:clave_comercial,8,0))," ") | O6: =IFERROR(IF(VLOOKUP(J6,articulo:clave_comercial,9,0)=0," ",VLOOKUP(J6,articulo:clave_comercial,9,0))," ") | P6: =IFERROR(IF(M6="HOJA",(D6*F6)/MAX(ROUNDDOWN((N6/G6),0)*ROUNDDOWN((O6/H6),0),ROUNDDOWN((N6/H6),0)*ROUNDDOWN((O6/G6),0)),IF(M6="HOJA ",(D6*F6)/MAX(ROUNDDOWN((N6/G6),0)*ROUNDDOWN((O6/H6),0),ROUNDDOWN((N6/H6),0)*ROUNDDOWN((O6/G6),0)),IF(M6="M",G6,IF(AND(M6="PIEZA",G6<>0),(D6*F6)/ROUNDDOWN((N6/G6),0),IF(M6="PIEZA",(D6*F6),IF(M6="CAJA",(D6*F6),IF(M6="DM2",(D6*F6),IF(M6="FT",(D6*F6),IF(M6="JGO",(D6*F6),IF(M6="KG",(D6*F6),IF(M6="LB",(D6*F6),IF(M6="LT",(D6*F6),IF(M6="M2",(D6*F6),IF(M6="M3",(D6*F6),IF(M6="ROLLO",(D6*F6),IF(M6="SQYDS",(D6*F6),IF(M6="UD./SERV.",(D6*F6),IF(M6="YD",(D6*F6)," ")))))))))))))))))),"") | Q6: =IFERROR(IF(M6="HOJA",D6*F6*G6*H6*2*0.125,IF(AND(M6="PIEZA",H6=0),D6*F6*G6*VLOOKUP(J6,articulo:clave_comercial,10,0)*0.125,0))," ") -> 0 | S6: {=IFERROR(INDEX($J$3:$J$52,MATCH(0,INDEX(COUNTIF(S$2:$S5,$J$3:$J$52),0,0),0))," ")} | T6: {=IFERROR(INDEX($L$3:$L$52,MATCH(0,INDEX(COUNTIF($T$2:T5,$L$3:$L$52),0,0),0))," ")} | U6: =IFERROR(IF(AND(VLOOKUP(S6,$J$3:$Q$218,4,0)="KG",VLOOKUP(S6,$J$3:$Q$218,7,0)=0,VLOOKUP(S6,$J$3:$Q$218,8,0)=0),SUM($Q$3:$Q$218),SUMIF($J$3:$J$218,S6,$P$3:$P$218)),"") | W6: =IFERROR(IF(OR(M6="HOJA",M6="HOJA "),((MAX(ROUNDDOWN((0.915/G6),0)*ROUNDDOWN((2.44/H6),0),ROUNDDOWN((0.915/H6),0)*ROUNDDOWN((2.44/G6),0)))*G6*H6)/(0.915*2.44),""),"") | X6: =IFERROR(MAX(ROUNDDOWN((0.915/G6),0)*ROUNDDOWN((2.44/H6),0),ROUNDDOWN((0.915/H6),0)*ROUNDDOWN((2.44/G6),0)),"") | Y6: =IFERROR(IF(OR(M6="HOJA",M6="HOJA "),((MAX(ROUNDDOWN((0.915/G6),0)*ROUNDDOWN((3.05/H6),0),ROUNDDOWN((0.915/H6),0)*ROUNDDOWN((3.05/G6),0)))*G6*H6)/(0.915*3.05),""),"") | Z6: =IFERROR(MAX(ROUNDDOWN((0.915/G6),0)*ROUNDDOWN((3.05/H6),0),ROUNDDOWN((0.915/H6),0)*ROUNDDOWN((3.05/G6),0)),"") | AA6: =IFERROR(IF(OR(M6="HOJA",M6="HOJA "),((MAX(ROUNDDOWN((1.22/G6),0)*ROUNDDOWN((2.44/H6),0),ROUNDDOWN((1.22/H6),0)*ROUNDDOWN((2.44/G6),0)))*G6*H6)/(1.22*2.44),""),"") | AB6: =IFERROR(MAX(ROUNDDOWN((1.22/G6),0)*ROUNDDOWN((2.44/H6),0),ROUNDDOWN((1.22/H6),0)*ROUNDDOWN((2.44/G6),0)),"") | AC6: =IFERROR(IF(OR(M6="HOJA",M6="HOJA "),((MAX(ROUNDDOWN((1.22/G6),0)*ROUNDDOWN((3.05/H6),0),ROUNDDOWN((1.22/H6),0)*ROUNDDOWN((3.05/G6),0)))*G6*H6)/(1.22*3.05),""),"") | AD6: =IFERROR(MAX(ROUNDDOWN((1.22/G6),0)*ROUNDDOWN((3.05/H6),0),ROUNDDOWN((1.22/H6),0)*ROUNDDOWN((3.05/G6),0)),"")
L7: =IFERROR(VLOOKUP(J7,articulo:clave_comercial,2,0)," ") | M7: =UPPER(IFERROR(VLOOKUP(J7,articulo:clave_comercial,5,0)," ")) | N7: =IFERROR(IF(VLOOKUP(J7,articulo:clave_comercial,8,0)=0," ",VLOOKUP(J7,articulo:clave_comercial,8,0))," ") | O7: =IFERROR(IF(VLOOKUP(J7,articulo:clave_comercial,9,0)=0," ",VLOOKUP(J7,articulo:clave_comercial,9,0))," ") | P7: =IFERROR(IF(M7="HOJA",(D7*F7)/MAX(ROUNDDOWN((N7/G7),0)*ROUNDDOWN((O7/H7),0),ROUNDDOWN((N7/H7),0)*ROUNDDOWN((O7/G7),0)),IF(M7="HOJA ",(D7*F7)/MAX(ROUNDDOWN((N7/G7),0)*ROUNDDOWN((O7/H7),0),ROUNDDOWN((N7/H7),0)*ROUNDDOWN((O7/G7),0)),IF(M7="M",G7,IF(AND(M7="PIEZA",G7<>0),(D7*F7)/ROUNDDOWN((N7/G7),0),IF(M7="PIEZA",(D7*F7),IF(M7="CAJA",(D7*F7),IF(M7="DM2",(D7*F7),IF(M7="FT",(D7*F7),IF(M7="JGO",(D7*F7),IF(M7="KG",(D7*F7),IF(M7="LB",(D7*F7),IF(M7="LT",(D7*F7),IF(M7="M2",(D7*F7),IF(M7="M3",(D7*F7),IF(M7="ROLLO",(D7*F7),IF(M7="SQYDS",(D7*F7),IF(M7="UD./SERV.",(D7*F7),IF(M7="YD",(D7*F7)," ")))))))))))))))))),"") | Q7: =IFERROR(IF(M7="HOJA",D7*F7*G7*H7*2*0.125,IF(AND(M7="PIEZA",H7=0),D7*F7*G7*VLOOKUP(J7,articulo:clave_comercial,10,0)*0.125,0))," ") -> 0 | S7: {=IFERROR(INDEX($J$3:$J$52,MATCH(0,INDEX(COUNTIF(S$2:$S6,$J$3:$J$52),0,0),0))," ")} | T7: {=IFERROR(INDEX($L$3:$L$52,MATCH(0,INDEX(COUNTIF($T$2:T6,$L$3:$L$52),0,0),0))," ")} | U7: =IFERROR(IF(AND(VLOOKUP(S7,$J$3:$Q$218,4,0)="KG",VLOOKUP(S7,$J$3:$Q$218,7,0)=0,VLOOKUP(S7,$J$3:$Q$218,8,0)=0),SUM($Q$3:$Q$218),SUMIF($J$3:$J$218,S7,$P$3:$P$218)),"") | W7: =IFERROR(IF(OR(M7="HOJA",M7="HOJA "),((MAX(ROUNDDOWN((0.915/G7),0)*ROUNDDOWN((2.44/H7),0),ROUNDDOWN((0.915/H7),0)*ROUNDDOWN((2.44/G7),0)))*G7*H7)/(0.915*2.44),""),"") | X7: =IFERROR(MAX(ROUNDDOWN((0.915/G7),0)*ROUNDDOWN((2.44/H7),0),ROUNDDOWN((0.915/H7),0)*ROUNDDOWN((2.44/G7),0)),"") | Y7: =IFERROR(IF(OR(M7="HOJA",M7="HOJA "),((MAX(ROUNDDOWN((0.915/G7),0)*ROUNDDOWN((3.05/H7),0),ROUNDDOWN((0.915/H7),0)*ROUNDDOWN((3.05/G7),0)))*G7*H7)/(0.915*3.05),""),"") | Z7: =IFERROR(MAX(ROUNDDOWN((0.915/G7),0)*ROUNDDOWN((3.05/H7),0),ROUNDDOWN((0.915/H7),0)*ROUNDDOWN((3.05/G7),0)),"") | AA7: =IFERROR(IF(OR(M7="HOJA",M7="HOJA "),((MAX(ROUNDDOWN((1.22/G7),0)*ROUNDDOWN((2.44/H7),0),ROUNDDOWN((1.22/H7),0)*ROUNDDOWN((2.44/G7),0)))*G7*H7)/(1.22*2.44),""),"") | AB7: =IFERROR(MAX(ROUNDDOWN((1.22/G7),0)*ROUNDDOWN((2.44/H7),0),ROUNDDOWN((1.22/H7),0)*ROUNDDOWN((2.44/G7),0)),"") | AC7: =IFERROR(IF(OR(M7="HOJA",M7="HOJA "),((MAX(ROUNDDOWN((1.22/G7),0)*ROUNDDOWN((3.05/H7),0),ROUNDDOWN((1.22/H7),0)*ROUNDDOWN((3.05/G7),0)))*G7*H7)/(1.22*3.05),""),"") | AD7: =IFERROR(MAX(ROUNDDOWN((1.22/G7),0)*ROUNDDOWN((3.05/H7),0),ROUNDDOWN((1.22/H7),0)*ROUNDDOWN((3.05/G7),0)),"")
L8: =IFERROR(VLOOKUP(J8,articulo:clave_comercial,2,0)," ") | M8: =UPPER(IFERROR(VLOOKUP(J8,articulo:clave_comercial,5,0)," ")) | N8: =IFERROR(IF(VLOOKUP(J8,articulo:clave_comercial,8,0)=0," ",VLOOKUP(J8,articulo:clave_comercial,8,0))," ") | O8: =IFERROR(IF(VLOOKUP(J8,articulo:clave_comercial,9,0)=0," ",VLOOKUP(J8,articulo:clave_comercial,9,0))," ") | P8: =IFERROR(IF(M8="HOJA",(D8*F8)/MAX(ROUNDDOWN((N8/G8),0)*ROUNDDOWN((O8/H8),0),ROUNDDOWN((N8/H8),0)*ROUNDDOWN((O8/G8),0)),IF(M8="HOJA ",(D8*F8)/MAX(ROUNDDOWN((N8/G8),0)*ROUNDDOWN((O8/H8),0),ROUNDDOWN((N8/H8),0)*ROUNDDOWN((O8/G8),0)),IF(M8="M",G8,IF(AND(M8="PIEZA",G8<>0),(D8*F8)/ROUNDDOWN((N8/G8),0),IF(M8="PIEZA",(D8*F8),IF(M8="CAJA",(D8*F8),IF(M8="DM2",(D8*F8),IF(M8="FT",(D8*F8),IF(M8="JGO",(D8*F8),IF(M8="KG",(D8*F8),IF(M8="LB",(D8*F8),IF(M8="LT",(D8*F8),IF(M8="M2",(D8*F8),IF(M8="M3",(D8*F8),IF(M8="ROLLO",(D8*F8),IF(M8="SQYDS",(D8*F8),IF(M8="UD./SERV.",(D8*F8),IF(M8="YD",(D8*F8)," ")))))))))))))))))),"") | Q8: =IFERROR(IF(M8="HOJA",D8*F8*G8*H8*2*0.125,IF(AND(M8="PIEZA",H8=0),D8*F8*G8*VLOOKUP(J8,articulo:clave_comercial,10,0)*0.125,0))," ") -> 0 | S8: {=IFERROR(INDEX($J$3:$J$52,MATCH(0,INDEX(COUNTIF(S$2:$S7,$J$3:$J$52),0,0),0))," ")} | T8: {=IFERROR(INDEX($L$3:$L$52,MATCH(0,INDEX(COUNTIF($T$2:T7,$L$3:$L$52),0,0),0))," ")} | U8: =IFERROR(IF(AND(VLOOKUP(S8,$J$3:$Q$218,4,0)="KG",VLOOKUP(S8,$J$3:$Q$218,7,0)=0,VLOOKUP(S8,$J$3:$Q$218,8,0)=0),SUM($Q$3:$Q$218),SUMIF($J$3:$J$218,S8,$P$3:$P$218)),"") | W8: =IFERROR(IF(OR(M8="HOJA",M8="HOJA "),((MAX(ROUNDDOWN((0.915/G8),0)*ROUNDDOWN((2.44/H8),0),ROUNDDOWN((0.915/H8),0)*ROUNDDOWN((2.44/G8),0)))*G8*H8)/(0.915*2.44),""),"") | X8: =IFERROR(MAX(ROUNDDOWN((0.915/G8),0)*ROUNDDOWN((2.44/H8),0),ROUNDDOWN((0.915/H8),0)*ROUNDDOWN((2.44/G8),0)),"") | Y8: =IFERROR(IF(OR(M8="HOJA",M8="HOJA "),((MAX(ROUNDDOWN((0.915/G8),0)*ROUNDDOWN((3.05/H8),0),ROUNDDOWN((0.915/H8),0)*ROUNDDOWN((3.05/G8),0)))*G8*H8)/(0.915*3.05),""),"") | Z8: =IFERROR(MAX(ROUNDDOWN((0.915/G8),0)*ROUNDDOWN((3.05/H8),0),ROUNDDOWN((0.915/H8),0)*ROUNDDOWN((3.05/G8),0)),"") | AA8: =IFERROR(IF(OR(M8="HOJA",M8="HOJA "),((MAX(ROUNDDOWN((1.22/G8),0)*ROUNDDOWN((2.44/H8),0),ROUNDDOWN((1.22/H8),0)*ROUNDDOWN((2.44/G8),0)))*G8*H8)/(1.22*2.44),""),"") | AB8: =IFERROR(MAX(ROUNDDOWN((1.22/G8),0)*ROUNDDOWN((2.44/H8),0),ROUNDDOWN((1.22/H8),0)*ROUNDDOWN((2.44/G8),0)),"") | AC8: =IFERROR(IF(OR(M8="HOJA",M8="HOJA "),((MAX(ROUNDDOWN((1.22/G8),0)*ROUNDDOWN((3.05/H8),0),ROUNDDOWN((1.22/H8),0)*ROUNDDOWN((3.05/G8),0)))*G8*H8)/(1.22*3.05),""),"") | AD8: =IFERROR(MAX(ROUNDDOWN((1.22/G8),0)*ROUNDDOWN((3.05/H8),0),ROUNDDOWN((1.22/H8),0)*ROUNDDOWN((3.05/G8),0)),"")
A9: 2 | L9: =IFERROR(VLOOKUP(J9,articulo:clave_comercial,2,0)," ") | M9: =UPPER(IFERROR(VLOOKUP(J9,articulo:clave_comercial,5,0)," ")) | N9: =IFERROR(IF(VLOOKUP(J9,articulo:clave_comercial,8,0)=0," ",VLOOKUP(J9,articulo:clave_comercial,8,0))," ") | O9: =IFERROR(IF(VLOOKUP(J9,articulo:clave_comercial,9,0)=0," ",VLOOKUP(J9,articulo:clave_comercial,9,0))," ") | P9: =IFERROR(IF(M9="HOJA",(D9*F9)/MAX(ROUNDDOWN((N9/G9),0)*ROUNDDOWN((O9/H9),0),ROUNDDOWN((N9/H9),0)*ROUNDDOWN((O9/G9),0)),IF(M9="HOJA ",(D9*F9)/MAX(ROUNDDOWN((N9/G9),0)*ROUNDDOWN((O9/H9),0),ROUNDDOWN((N9/H9),0)*ROUNDDOWN((O9/G9),0)),IF(M9="M",G9,IF(AND(M9="PIEZA",G9<>0),(D9*F9)/ROUNDDOWN((N9/G9),0),IF(M9="PIEZA",(D9*F9),IF(M9="CAJA",(D9*F9),IF(M9="DM2",(D9*F9),IF(M9="FT",(D9*F9),IF(M9="JGO",(D9*F9),IF(M9="KG",(D9*F9),IF(M9="LB",(D9*F9),IF(M9="LT",(D9*F9),IF(M9="M2",(D9*F9),IF(M9="M3",(D9*F9),IF(M9="ROLLO",(D9*F9),IF(M9="SQYDS",(D9*F9),IF(M9="UD./SERV.",(D9*F9),IF(M9="YD",(D9*F9)," ")))))))))))))))))),"") | Q9: =IFERROR(IF(M9="HOJA",D9*F9*G9*H9*2*0.125,IF(AND(M9="PIEZA",H9=0),D9*F9*G9*VLOOKUP(J9,articulo:clave_comercial,10,0)*0.125,0))," ") -> 0 | S9: {=IFERROR(INDEX($J$3:$J$52,MATCH(0,INDEX(COUNTIF(S$2:$S8,$J$3:$J$52),0,0),0))," ")} | T9: {=IFERROR(INDEX($L$3:$L$52,MATCH(0,INDEX(COUNTIF($T$2:T8,$L$3:$L$52),0,0),0))," ")} | U9: =IFERROR(IF(AND(VLOOKUP(S9,$J$3:$Q$218,4,0)="KG",VLOOKUP(S9,$J$3:$Q$218,7,0)=0,VLOOKUP(S9,$J$3:$Q$218,8,0)=0),SUM($Q$3:$Q$218),SUMIF($J$3:$J$218,S9,$P$3:$P$218)),"") | W9: =IFERROR(IF(OR(M9="HOJA",M9="HOJA "),((MAX(ROUNDDOWN((0.915/G9),0)*ROUNDDOWN((2.44/H9),0),ROUNDDOWN((0.915/H9),0)*ROUNDDOWN((2.44/G9),0)))*G9*H9)/(0.915*2.44),""),"") | X9: =IFERROR(MAX(ROUNDDOWN((0.915/G9),0)*ROUNDDOWN((2.44/H9),0),ROUNDDOWN((0.915/H9),0)*ROUNDDOWN((2.44/G9),0)),"") | Y9: =IFERROR(IF(OR(M9="HOJA",M9="HOJA "),((MAX(ROUNDDOWN((0.915/G9),0)*ROUNDDOWN((3.05/H9),0),ROUNDDOWN((0.915/H9),0)*ROUNDDOWN((3.05/G9),0)))*G9*H9)/(0.915*3.05),""),"") | Z9: =IFERROR(MAX(ROUNDDOWN((0.915/G9),0)*ROUNDDOWN((3.05/H9),0),ROUNDDOWN((0.915/H9),0)*ROUNDDOWN((3.05/G9),0)),"") | AA9: =IFERROR(IF(OR(M9="HOJA",M9="HOJA "),((MAX(ROUNDDOWN((1.22/G9),0)*ROUNDDOWN((2.44/H9),0),ROUNDDOWN((1.22/H9),0)*ROUNDDOWN((2.44/G9),0)))*G9*H9)/(1.22*2.44),""),"") | AB9: =IFERROR(MAX(ROUNDDOWN((1.22/G9),0)*ROUNDDOWN((2.44/H9),0),ROUNDDOWN((1.22/H9),0)*ROUNDDOWN((2.44/G9),0)),"") | AC9: =IFERROR(IF(OR(M9="HOJA",M9="HOJA "),((MAX(ROUNDDOWN((1.22/G9),0)*ROUNDDOWN((3.05/H9),0),ROUNDDOWN((1.22/H9),0)*ROUNDDOWN((3.05/G9),0)))*G9*H9)/(1.22*3.05),""),"") | AD9: =IFERROR(MAX(ROUNDDOWN((1.22/G9),0)*ROUNDDOWN((3.05/H9),0),ROUNDDOWN((1.22/H9),0)*ROUNDDOWN((3.05/G9),0)),"")
L10: =IFERROR(VLOOKUP(J10,articulo:clave_comercial,2,0)," ") | M10: =UPPER(IFERROR(VLOOKUP(J10,articulo:clave_comercial,5,0)," ")) | N10: =IFERROR(IF(VLOOKUP(J10,articulo:clave_comercial,8,0)=0," ",VLOOKUP(J10,articulo:clave_comercial,8,0))," ") | O10: =IFERROR(IF(VLOOKUP(J10,articulo:clave_comercial,9,0)=0," ",VLOOKUP(J10,articulo:clave_comercial,9,0))," ") | P10: =IFERROR(IF(M10="HOJA",(D10*F10)/MAX(ROUNDDOWN((N10/G10),0)*ROUNDDOWN((O10/H10),0),ROUNDDOWN((N10/H10),0)*ROUNDDOWN((O10/G10),0)),IF(M10="HOJA ",(D10*F10)/MAX(ROUNDDOWN((N10/G10),0)*ROUNDDOWN((O10/H10),0),ROUNDDOWN((N10/H10),0)*ROUNDDOWN((O10/G10),0)),IF(M10="M",G10,IF(AND(M10="PIEZA",G10<>0),(D10*F10)/ROUNDDOWN((N10/G10),0),IF(M10="PIEZA",(D10*F10),IF(M10="CAJA",(D10*F10),IF(M10="DM2",(D10*F10),IF(M10="FT",(D10*F10),IF(M10="JGO",(D10*F10),IF(M10="KG",(D10*F10),IF(M10="LB",(D10*F10),IF(M10="LT",(D10*F10),IF(M10="M2",(D10*F10),IF(M10="M3",(D10*F10),IF(M10="ROLLO",(D10*F10),IF(M10="SQYDS",(D10*F10),IF(M10="UD./SERV.",(D10*F10),IF(M10="YD",(D10*F10)," ")))))))))))))))))),"") | Q10: =IFERROR(IF(M10="HOJA",D10*F10*G10*H10*2*0.125,IF(AND(M10="PIEZA",H10=0),D10*F10*G10*VLOOKUP(J10,articulo:clave_comercial,10,0)*0.125,0))," ") -> 0 | S10: {=IFERROR(INDEX($J$3:$J$52,MATCH(0,INDEX(COUNTIF(S$2:$S9,$J$3:$J$52),0,0),0))," ")} | T10: {=IFERROR(INDEX($L$3:$L$52,MATCH(0,INDEX(COUNTIF($T$2:T9,$L$3:$L$52),0,0),0))," ")} | U10: =IFERROR(IF(AND(VLOOKUP(S10,$J$3:$Q$218,4,0)="KG",VLOOKUP(S10,$J$3:$Q$218,7,0)=0,VLOOKUP(S10,$J$3:$Q$218,8,0)=0),SUM($Q$3:$Q$218),SUMIF($J$3:$J$218,S10,$P$3:$P$218)),"") | W10: =IFERROR(IF(OR(M10="HOJA",M10="HOJA "),((MAX(ROUNDDOWN((0.915/G10),0)*ROUNDDOWN((2.44/H10),0),ROUNDDOWN((0.915/H10),0)*ROUNDDOWN((2.44/G10),0)))*G10*H10)/(0.915*2.44),""),"") | X10: =IFERROR(MAX(ROUNDDOWN((0.915/G10),0)*ROUNDDOWN((2.44/H10),0),ROUNDDOWN((0.915/H10),0)*ROUNDDOWN((2.44/G10),0)),"") | Y10: =IFERROR(IF(OR(M10="HOJA",M10="HOJA "),((MAX(ROUNDDOWN((0.915/G10),0)*ROUNDDOWN((3.05/H10),0),ROUNDDOWN((0.915/H10),0)*ROUNDDOWN((3.05/G10),0)))*G10*H10)/(0.915*3.05),""),"") | Z10: =IFERROR(MAX(ROUNDDOWN((0.915/G10),0)*ROUNDDOWN((3.05/H10),0),ROUNDDOWN((0.915/H10),0)*ROUNDDOWN((3.05/G10),0)),"") | AA10: =IFERROR(IF(OR(M10="HOJA",M10="HOJA "),((MAX(ROUNDDOWN((1.22/G10),0)*ROUNDDOWN((2.44/H10),0),ROUNDDOWN((1.22/H10),0)*ROUNDDOWN((2.44/G10),0)))*G10*H10)/(1.22*2.44),""),"") | AB10: =IFERROR(MAX(ROUNDDOWN((1.22/G10),0)*ROUNDDOWN((2.44/H10),0),ROUNDDOWN((1.22/H10),0)*ROUNDDOWN((2.44/G10),0)),"") | AC10: =IFERROR(IF(OR(M10="HOJA",M10="HOJA "),((MAX(ROUNDDOWN((1.22/G10),0)*ROUNDDOWN((3.05/H10),0),ROUNDDOWN((1.22/H10),0)*ROUNDDOWN((3.05/G10),0)))*G10*H10)/(1.22*3.05),""),"") | AD10: =IFERROR(MAX(ROUNDDOWN((1.22/G10),0)*ROUNDDOWN((3.05/H10),0),ROUNDDOWN((1.22/H10),0)*ROUNDDOWN((3.05/G10),0)),"")
L11: =IFERROR(VLOOKUP(J11,articulo:clave_comercial,2,0)," ") | M11: =UPPER(IFERROR(VLOOKUP(J11,articulo:clave_comercial,5,0)," ")) | N11: =IFERROR(IF(VLOOKUP(J11,articulo:clave_comercial,8,0)=0," ",VLOOKUP(J11,articulo:clave_comercial,8,0))," ") | O11: =IFERROR(IF(VLOOKUP(J11,articulo:clave_comercial,9,0)=0," ",VLOOKUP(J11,articulo:clave_comercial,9,0))," ") | P11: =IFERROR(IF(M11="HOJA",(D11*F11)/MAX(ROUNDDOWN((N11/G11),0)*ROUNDDOWN((O11/H11),0),ROUNDDOWN((N11/H11),0)*ROUNDDOWN((O11/G11),0)),IF(M11="HOJA ",(D11*F11)/MAX(ROUNDDOWN((N11/G11),0)*ROUNDDOWN((O11/H11),0),ROUNDDOWN((N11/H11),0)*ROUNDDOWN((O11/G11),0)),IF(M11="M",G11,IF(AND(M11="PIEZA",G11<>0),(D11*F11)/ROUNDDOWN((N11/G11),0),IF(M11="PIEZA",(D11*F11),IF(M11="CAJA",(D11*F11),IF(M11="DM2",(D11*F11),IF(M11="FT",(D11*F11),IF(M11="JGO",(D11*F11),IF(M11="KG",(D11*F11),IF(M11="LB",(D11*F11),IF(M11="LT",(D11*F11),IF(M11="M2",(D11*F11),IF(M11="M3",(D11*F11),IF(M11="ROLLO",(D11*F11),IF(M11="SQYDS",(D11*F11),IF(M11="UD./SERV.",(D11*F11),IF(M11="YD",(D11*F11)," ")))))))))))))))))),"") | Q11: =IFERROR(IF(M11="HOJA",D11*F11*G11*H11*2*0.125,IF(AND(M11="PIEZA",H11=0),D11*F11*G11*VLOOKUP(J11,articulo:clave_comercial,10,0)*0.125,0))," ") -> 0 | S11: {=IFERROR(INDEX($J$3:$J$52,MATCH(0,INDEX(COUNTIF(S$2:$S10,$J$3:$J$52),0,0),0))," ")} | T11: {=IFERROR(INDEX($L$3:$L$52,MATCH(0,INDEX(COUNTIF($T$2:T10,$L$3:$L$52),0,0),0))," ")} | U11: =IFERROR(IF(AND(VLOOKUP(S11,$J$3:$Q$218,4,0)="KG",VLOOKUP(S11,$J$3:$Q$218,7,0)=0,VLOOKUP(S11,$J$3:$Q$218,8,0)=0),SUM($Q$3:$Q$218),SUMIF($J$3:$J$218,S11,$P$3:$P$218)),"") | W11: =IFERROR(IF(OR(M11="HOJA",M11="HOJA "),((MAX(ROUNDDOWN((0.915/G11),0)*ROUNDDOWN((2.44/H11),0),ROUNDDOWN((0.915/H11),0)*ROUNDDOWN((2.44/G11),0)))*G11*H11)/(0.915*2.44),""),"") | X11: =IFERROR(MAX(ROUNDDOWN((0.915/G11),0)*ROUNDDOWN((2.44/H11),0),ROUNDDOWN((0.915/H11),0)*ROUNDDOWN((2.44/G11),0)),"") | Y11: =IFERROR(IF(OR(M11="HOJA",M11="HOJA "),((MAX(ROUNDDOWN((0.915/G11),0)*ROUNDDOWN((3.05/H11),0),ROUNDDOWN((0.915/H11),0)*ROUNDDOWN((3.05/G11),0)))*G11*H11)/(0.915*3.05),""),"") | Z11: =IFERROR(MAX(ROUNDDOWN((0.915/G11),0)*ROUNDDOWN((3.05/H11),0),ROUNDDOWN((0.915/H11),0)*ROUNDDOWN((3.05/G11),0)),"") | AA11: =IFERROR(IF(OR(M11="HOJA",M11="HOJA "),((MAX(ROUNDDOWN((1.22/G11),0)*ROUNDDOWN((2.44/H11),0),ROUNDDOWN((1.22/H11),0)*ROUNDDOWN((2.44/G11),0)))*G11*H11)/(1.22*2.44),""),"") | AB11: =IFERROR(MAX(ROUNDDOWN((1.22/G11),0)*ROUNDDOWN((2.44/H11),0),ROUNDDOWN((1.22/H11),0)*ROUNDDOWN((2.44/G11),0)),"") | AC11: =IFERROR(IF(OR(M11="HOJA",M11="HOJA "),((MAX(ROUNDDOWN((1.22/G11),0)*ROUNDDOWN((3.05/H11),0),ROUNDDOWN((1.22/H11),0)*ROUNDDOWN((3.05/G11),0)))*G11*H11)/(1.22*3.05),""),"") | AD11: =IFERROR(MAX(ROUNDDOWN((1.22/G11),0)*ROUNDDOWN((3.05/H11),0),ROUNDDOWN((1.22/H11),0)*ROUNDDOWN((3.05/G11),0)),"")
L12: =IFERROR(VLOOKUP(J12,articulo:clave_comercial,2,0)," ") | M12: =UPPER(IFERROR(VLOOKUP(J12,articulo:clave_comercial,5,0)," ")) | N12: =IFERROR(IF(VLOOKUP(J12,articulo:clave_comercial,8,0)=0," ",VLOOKUP(J12,articulo:clave_comercial,8,0))," ") | O12: =IFERROR(IF(VLOOKUP(J12,articulo:clave_comercial,9,0)=0," ",VLOOKUP(J12,articulo:clave_comercial,9,0))," ") | P12: =IFERROR(IF(M12="HOJA",(D12*F12)/MAX(ROUNDDOWN((N12/G12),0)*ROUNDDOWN((O12/H12),0),ROUNDDOWN((N12/H12),0)*ROUNDDOWN((O12/G12),0)),IF(M12="HOJA ",(D12*F12)/MAX(ROUNDDOWN((N12/G12),0)*ROUNDDOWN((O12/H12),0),ROUNDDOWN((N12/H12),0)*ROUNDDOWN((O12/G12),0)),IF(M12="M",G12,IF(AND(M12="PIEZA",G12<>0),(D12*F12)/ROUNDDOWN((N12/G12),0),IF(M12="PIEZA",(D12*F12),IF(M12="CAJA",(D12*F12),IF(M12="DM2",(D12*F12),IF(M12="FT",(D12*F12),IF(M12="JGO",(D12*F12),IF(M12="KG",(D12*F12),IF(M12="LB",(D12*F12),IF(M12="LT",(D12*F12),IF(M12="M2",(D12*F12),IF(M12="M3",(D12*F12),IF(M12="ROLLO",(D12*F12),IF(M12="SQYDS",(D12*F12),IF(M12="UD./SERV.",(D12*F12),IF(M12="YD",(D12*F12)," ")))))))))))))))))),"") | Q12: =IFERROR(IF(M12="HOJA",D12*F12*G12*H12*2*0.125,IF(AND(M12="PIEZA",H12=0),D12*F12*G12*VLOOKUP(J12,articulo:clave_comercial,10,0)*0.125,0))," ") -> 0 | S12: {=IFERROR(INDEX($J$3:$J$52,MATCH(0,INDEX(COUNTIF(S$2:$S11,$J$3:$J$52),0,0),0))," ")} | T12: {=IFERROR(INDEX($L$3:$L$52,MATCH(0,INDEX(COUNTIF($T$2:T11,$L$3:$L$52),0,0),0))," ")} | U12: =IFERROR(IF(AND(VLOOKUP(S12,$J$3:$Q$218,4,0)="KG",VLOOKUP(S12,$J$3:$Q$218,7,0)=0,VLOOKUP(S12,$J$3:$Q$218,8,0)=0),SUM($Q$3:$Q$218),SUMIF($J$3:$J$218,S12,$P$3:$P$218)),"") | W12: =IFERROR(IF(OR(M12="HOJA",M12="HOJA "),((MAX(ROUNDDOWN((0.915/G12),0)*ROUNDDOWN((2.44/H12),0),ROUNDDOWN((0.915/H12),0)*ROUNDDOWN((2.44/G12),0)))*G12*H12)/(0.915*2.44),""),"") | X12: =IFERROR(MAX(ROUNDDOWN((0.915/G12),0)*ROUNDDOWN((2.44/H12),0),ROUNDDOWN((0.915/H12),0)*ROUNDDOWN((2.44/G12),0)),"") | Y12: =IFERROR(IF(OR(M12="HOJA",M12="HOJA "),((MAX(ROUNDDOWN((0.915/G12),0)*ROUNDDOWN((3.05/H12),0),ROUNDDOWN((0.915/H12),0)*ROUNDDOWN((3.05/G12),0)))*G12*H12)/(0.915*3.05),""),"") | Z12: =IFERROR(MAX(ROUNDDOWN((0.915/G12),0)*ROUNDDOWN((3.05/H12),0),ROUNDDOWN((0.915/H12),0)*ROUNDDOWN((3.05/G12),0)),"") | AA12: =IFERROR(IF(OR(M12="HOJA",M12="HOJA "),((MAX(ROUNDDOWN((1.22/G12),0)*ROUNDDOWN((2.44/H12),0),ROUNDDOWN((1.22/H12),0)*ROUNDDOWN((2.44/G12),0)))*G12*H12)/(1.22*2.44),""),"") | AB12: =IFERROR(MAX(ROUNDDOWN((1.22/G12),0)*ROUNDDOWN((2.44/H12),0),ROUNDDOWN((1.22/H12),0)*ROUNDDOWN((2.44/G12),0)),"") | AC12: =IFERROR(IF(OR(M12="HOJA",M12="HOJA "),((MAX(ROUNDDOWN((1.22/G12),0)*ROUNDDOWN((3.05/H12),0),ROUNDDOWN((1.22/H12),0)*ROUNDDOWN((3.05/G12),0)))*G12*H12)/(1.22*3.05),""),"") | AD12: =IFERROR(MAX(ROUNDDOWN((1.22/G12),0)*ROUNDDOWN((3.05/H12),0),ROUNDDOWN((1.22/H12),0)*ROUNDDOWN((3.05/G12),0)),"")
L13: =IFERROR(VLOOKUP(J13,articulo:clave_comercial,2,0)," ") | M13: =UPPER(IFERROR(VLOOKUP(J13,articulo:clave_comercial,5,0)," ")) | N13: =IFERROR(IF(VLOOKUP(J13,articulo:clave_comercial,8,0)=0," ",VLOOKUP(J13,articulo:clave_comercial,8,0))," ") | O13: =IFERROR(IF(VLOOKUP(J13,articulo:clave_comercial,9,0)=0," ",VLOOKUP(J13,articulo:clave_comercial,9,0))," ") | P13: =IFERROR(IF(M13="HOJA",(D13*F13)/MAX(ROUNDDOWN((N13/G13),0)*ROUNDDOWN((O13/H13),0),ROUNDDOWN((N13/H13),0)*ROUNDDOWN((O13/G13),0)),IF(M13="HOJA ",(D13*F13)/MAX(ROUNDDOWN((N13/G13),0)*ROUNDDOWN((O13/H13),0),ROUNDDOWN((N13/H13),0)*ROUNDDOWN((O13/G13),0)),IF(M13="M",G13,IF(AND(M13="PIEZA",G13<>0),(D13*F13)/ROUNDDOWN((N13/G13),0),IF(M13="PIEZA",(D13*F13),IF(M13="CAJA",(D13*F13),IF(M13="DM2",(D13*F13),IF(M13="FT",(D13*F13),IF(M13="JGO",(D13*F13),IF(M13="KG",(D13*F13),IF(M13="LB",(D13*F13),IF(M13="LT",(D13*F13),IF(M13="M2",(D13*F13),IF(M13="M3",(D13*F13),IF(M13="ROLLO",(D13*F13),IF(M13="SQYDS",(D13*F13),IF(M13="UD./SERV.",(D13*F13),IF(M13="YD",(D13*F13)," ")))))))))))))))))),"") | Q13: =IFERROR(IF(M13="HOJA",D13*F13*G13*H13*2*0.125,IF(AND(M13="PIEZA",H13=0),D13*F13*G13*VLOOKUP(J13,articulo:clave_comercial,10,0)*0.125,0))," ") -> 0 | S13: {=IFERROR(INDEX($J$3:$J$52,MATCH(0,INDEX(COUNTIF(S$2:$S12,$J$3:$J$52),0,0),0))," ")} | T13: {=IFERROR(INDEX($L$3:$L$52,MATCH(0,INDEX(COUNTIF($T$2:T12,$L$3:$L$52),0,0),0))," ")} | U13: =IFERROR(IF(AND(VLOOKUP(S13,$J$3:$Q$218,4,0)="KG",VLOOKUP(S13,$J$3:$Q$218,7,0)=0,VLOOKUP(S13,$J$3:$Q$218,8,0)=0),SUM($Q$3:$Q$218),SUMIF($J$3:$J$218,S13,$P$3:$P$218)),"") | W13: =IFERROR(IF(OR(M13="HOJA",M13="HOJA "),((MAX(ROUNDDOWN((0.915/G13),0)*ROUNDDOWN((2.44/H13),0),ROUNDDOWN((0.915/H13),0)*ROUNDDOWN((2.44/G13),0)))*G13*H13)/(0.915*2.44),""),"") | X13: =IFERROR(MAX(ROUNDDOWN((0.915/G13),0)*ROUNDDOWN((2.44/H13),0),ROUNDDOWN((0.915/H13),0)*ROUNDDOWN((2.44/G13),0)),"") | Y13: =IFERROR(IF(OR(M13="HOJA",M13="HOJA "),((MAX(ROUNDDOWN((0.915/G13),0)*ROUNDDOWN((3.05/H13),0),ROUNDDOWN((0.915/H13),0)*ROUNDDOWN((3.05/G13),0)))*G13*H13)/(0.915*3.05),""),"") | Z13: =IFERROR(MAX(ROUNDDOWN((0.915/G13),0)*ROUNDDOWN((3.05/H13),0),ROUNDDOWN((0.915/H13),0)*ROUNDDOWN((3.05/G13),0)),"") | AA13: =IFERROR(IF(OR(M13="HOJA",M13="HOJA "),((MAX(ROUNDDOWN((1.22/G13),0)*ROUNDDOWN((2.44/H13),0),ROUNDDOWN((1.22/H13),0)*ROUNDDOWN((2.44/G13),0)))*G13*H13)/(1.22*2.44),""),"") | AB13: =IFERROR(MAX(ROUNDDOWN((1.22/G13),0)*ROUNDDOWN((2.44/H13),0),ROUNDDOWN((1.22/H13),0)*ROUNDDOWN((2.44/G13),0)),"") | AC13: =IFERROR(IF(OR(M13="HOJA",M13="HOJA "),((MAX(ROUNDDOWN((1.22/G13),0)*ROUNDDOWN((3.05/H13),0),ROUNDDOWN((1.22/H13),0)*ROUNDDOWN((3.05/G13),0)))*G13*H13)/(1.22*3.05),""),"") | AD13: =IFERROR(MAX(ROUNDDOWN((1.22/G13),0)*ROUNDDOWN((3.05/H13),0),ROUNDDOWN((1.22/H13),0)*ROUNDDOWN((3.05/G13),0)),"")
L14: =IFERROR(VLOOKUP(J14,articulo:clave_comercial,2,0)," ") | M14: =UPPER(IFERROR(VLOOKUP(J14,articulo:clave_comercial,5,0)," ")) | N14: =IFERROR(IF(VLOOKUP(J14,articulo:clave_comercial,8,0)=0," ",VLOOKUP(J14,articulo:clave_comercial,8,0))," ") | O14: =IFERROR(IF(VLOOKUP(J14,articulo:clave_comercial,9,0)=0," ",VLOOKUP(J14,articulo:clave_comercial,9,0))," ") | P14: =IFERROR(IF(M14="HOJA",(D14*F14)/MAX(ROUNDDOWN((N14/G14),0)*ROUNDDOWN((O14/H14),0),ROUNDDOWN((N14/H14),0)*ROUNDDOWN((O14/G14),0)),IF(M14="HOJA ",(D14*F14)/MAX(ROUNDDOWN((N14/G14),0)*ROUNDDOWN((O14/H14),0),ROUNDDOWN((N14/H14),0)*ROUNDDOWN((O14/G14),0)),IF(M14="M",G14,IF(AND(M14="PIEZA",G14<>0),(D14*F14)/ROUNDDOWN((N14/G14),0),IF(M14="PIEZA",(D14*F14),IF(M14="CAJA",(D14*F14),IF(M14="DM2",(D14*F14),IF(M14="FT",(D14*F14),IF(M14="JGO",(D14*F14),IF(M14="KG",(D14*F14),IF(M14="LB",(D14*F14),IF(M14="LT",(D14*F14),IF(M14="M2",(D14*F14),IF(M14="M3",(D14*F14),IF(M14="ROLLO",(D14*F14),IF(M14="SQYDS",(D14*F14),IF(M14="UD./SERV.",(D14*F14),IF(M14="YD",(D14*F14)," ")))))))))))))))))),"") | Q14: =IFERROR(IF(M14="HOJA",D14*F14*G14*H14*2*0.125,IF(AND(M14="PIEZA",H14=0),D14*F14*G14*VLOOKUP(J14,articulo:clave_comercial,10,0)*0.125,0))," ") -> 0 | S14: {=IFERROR(INDEX($J$3:$J$52,MATCH(0,INDEX(COUNTIF(S$2:$S13,$J$3:$J$52),0,0),0))," ")} | T14: {=IFERROR(INDEX($L$3:$L$52,MATCH(0,INDEX(COUNTIF($T$2:T13,$L$3:$L$52),0,0),0))," ")} | U14: =IFERROR(IF(AND(VLOOKUP(S14,$J$3:$Q$218,4,0)="KG",VLOOKUP(S14,$J$3:$Q$218,7,0)=0,VLOOKUP(S14,$J$3:$Q$218,8,0)=0),SUM($Q$3:$Q$218),SUMIF($J$3:$J$218,S14,$P$3:$P$218)),"") | W14: =IFERROR(IF(OR(M14="HOJA",M14="HOJA "),((MAX(ROUNDDOWN((0.915/G14),0)*ROUNDDOWN((2.44/H14),0),ROUNDDOWN((0.915/H14),0)*ROUNDDOWN((2.44/G14),0)))*G14*H14)/(0.915*2.44),""),"") | X14: =IFERROR(MAX(ROUNDDOWN((0.915/G14),0)*ROUNDDOWN((2.44/H14),0),ROUNDDOWN((0.915/H14),0)*ROUNDDOWN((2.44/G14),0)),"") | Y14: =IFERROR(IF(OR(M14="HOJA",M14="HOJA "),((MAX(ROUNDDOWN((0.915/G14),0)*ROUNDDOWN((3.05/H14),0),ROUNDDOWN((0.915/H14),0)*ROUNDDOWN((3.05/G14),0)))*G14*H14)/(0.915*3.05),""),"") | Z14: =IFERROR(MAX(ROUNDDOWN((0.915/G14),0)*ROUNDDOWN((3.05/H14),0),ROUNDDOWN((0.915/H14),0)*ROUNDDOWN((3.05/G14),0)),"") | AA14: =IFERROR(IF(OR(M14="HOJA",M14="HOJA "),((MAX(ROUNDDOWN((1.22/G14),0)*ROUNDDOWN((2.44/H14),0),ROUNDDOWN((1.22/H14),0)*ROUNDDOWN((2.44/G14),0)))*G14*H14)/(1.22*2.44),""),"") | AB14: =IFERROR(MAX(ROUNDDOWN((1.22/G14),0)*ROUNDDOWN((2.44/H14),0),ROUNDDOWN((1.22/H14),0)*ROUNDDOWN((2.44/G14),0)),"") | AC14: =IFERROR(IF(OR(M14="HOJA",M14="HOJA "),((MAX(ROUNDDOWN((1.22/G14),0)*ROUNDDOWN((3.05/H14),0),ROUNDDOWN((1.22/H14),0)*ROUNDDOWN((3.05/G14),0)))*G14*H14)/(1.22*3.05),""),"") | AD14: =IFERROR(MAX(ROUNDDOWN((1.22/G14),0)*ROUNDDOWN((3.05/H14),0),ROUNDDOWN((1.22/H14),0)*ROUNDDOWN((3.05/G14),0)),"")
A15: 3 | L15: =IFERROR(VLOOKUP(J15,articulo:clave_comercial,2,0)," ") | M15: =UPPER(IFERROR(VLOOKUP(J15,articulo:clave_comercial,5,0)," ")) | N15: =IFERROR(IF(VLOOKUP(J15,articulo:clave_comercial,8,0)=0," ",VLOOKUP(J15,articulo:clave_comercial,8,0))," ") | O15: =IFERROR(IF(VLOOKUP(J15,articulo:clave_comercial,9,0)=0," ",VLOOKUP(J15,articulo:clave_comercial,9,0))," ") | P15: =IFERROR(IF(M15="HOJA",(D15*F15)/MAX(ROUNDDOWN((N15/G15),0)*ROUNDDOWN((O15/H15),0),ROUNDDOWN((N15/H15),0)*ROUNDDOWN((O15/G15),0)),IF(M15="HOJA ",(D15*F15)/MAX(ROUNDDOWN((N15/G15),0)*ROUNDDOWN((O15/H15),0),ROUNDDOWN((N15/H15),0)*ROUNDDOWN((O15/G15),0)),IF(M15="M",G15,IF(AND(M15="PIEZA",G15<>0),(D15*F15)/ROUNDDOWN((N15/G15),0),IF(M15="PIEZA",(D15*F15),IF(M15="CAJA",(D15*F15),IF(M15="DM2",(D15*F15),IF(M15="FT",(D15*F15),IF(M15="JGO",(D15*F15),IF(M15="KG",(D15*F15),IF(M15="LB",(D15*F15),IF(M15="LT",(D15*F15),IF(M15="M2",(D15*F15),IF(M15="M3",(D15*F15),IF(M15="ROLLO",(D15*F15),IF(M15="SQYDS",(D15*F15),IF(M15="UD./SERV.",(D15*F15),IF(M15="YD",(D15*F15)," ")))))))))))))))))),"") | Q15: =IFERROR(IF(M15="HOJA",D15*F15*G15*H15*2*0.125,IF(AND(M15="PIEZA",H15=0),D15*F15*G15*VLOOKUP(J15,articulo:clave_comercial,10,0)*0.125,0))," ") -> 0 | S15: {=IFERROR(INDEX($J$3:$J$52,MATCH(0,INDEX(COUNTIF(S$2:$S14,$J$3:$J$52),0,0),0))," ")} | T15: {=IFERROR(INDEX($L$3:$L$52,MATCH(0,INDEX(COUNTIF($T$2:T14,$L$3:$L$52),0,0),0))," ")} | U15: =IFERROR(IF(AND(VLOOKUP(S15,$J$3:$Q$218,4,0)="KG",VLOOKUP(S15,$J$3:$Q$218,7,0)=0,VLOOKUP(S15,$J$3:$Q$218,8,0)=0),SUM($Q$3:$Q$218),SUMIF($J$3:$J$218,S15,$P$3:$P$218)),"") | W15: =IFERROR(IF(OR(M15="HOJA",M15="HOJA "),((MAX(ROUNDDOWN((0.915/G15),0)*ROUNDDOWN((2.44/H15),0),ROUNDDOWN((0.915/H15),0)*ROUNDDOWN((2.44/G15),0)))*G15*H15)/(0.915*2.44),""),"") | X15: =IFERROR(MAX(ROUNDDOWN((0.915/G15),0)*ROUNDDOWN((2.44/H15),0),ROUNDDOWN((0.915/H15),0)*ROUNDDOWN((2.44/G15),0)),"") | Y15: =IFERROR(IF(OR(M15="HOJA",M15="HOJA "),((MAX(ROUNDDOWN((0.915/G15),0)*ROUNDDOWN((3.05/H15),0),ROUNDDOWN((0.915/H15),0)*ROUNDDOWN((3.05/G15),0)))*G15*H15)/(0.915*3.05),""),"") | Z15: =IFERROR(MAX(ROUNDDOWN((0.915/G15),0)*ROUNDDOWN((3.05/H15),0),ROUNDDOWN((0.915/H15),0)*ROUNDDOWN((3.05/G15),0)),"") | AA15: =IFERROR(IF(OR(M15="HOJA",M15="HOJA "),((MAX(ROUNDDOWN((1.22/G15),0)*ROUNDDOWN((2.44/H15),0),ROUNDDOWN((1.22/H15),0)*ROUNDDOWN((2.44/G15),0)))*G15*H15)/(1.22*2.44),""),"") | AB15: =IFERROR(MAX(ROUNDDOWN((1.22/G15),0)*ROUNDDOWN((2.44/H15),0),ROUNDDOWN((1.22/H15),0)*ROUNDDOWN((2.44/G15),0)),"") | AC15: =IFERROR(IF(OR(M15="HOJA",M15="HOJA "),((MAX(ROUNDDOWN((1.22/G15),0)*ROUNDDOWN((3.05/H15),0),ROUNDDOWN((1.22/H15),0)*ROUNDDOWN((3.05/G15),0)))*G15*H15)/(1.22*3.05),""),"") | AD15: =IFERROR(MAX(ROUNDDOWN((1.22/G15),0)*ROUNDDOWN((3.05/H15),0),ROUNDDOWN((1.22/H15),0)*ROUNDDOWN((3.05/G15),0)),"")
L16: =IFERROR(VLOOKUP(J16,articulo:clave_comercial,2,0)," ") | M16: =UPPER(IFERROR(VLOOKUP(J16,articulo:clave_comercial,5,0)," ")) | N16: =IFERROR(IF(VLOOKUP(J16,articulo:clave_comercial,8,0)=0," ",VLOOKUP(J16,articulo:clave_comercial,8,0))," ") | O16: =IFERROR(IF(VLOOKUP(J16,articulo:clave_comercial,9,0)=0," ",VLOOKUP(J16,articulo:clave_comercial,9,0))," ") | P16: =IFERROR(IF(M16="HOJA",(D16*F16)/MAX(ROUNDDOWN((N16/G16),0)*ROUNDDOWN((O16/H16),0),ROUNDDOWN((N16/H16),0)*ROUNDDOWN((O16/G16),0)),IF(M16="HOJA ",(D16*F16)/MAX(ROUNDDOWN((N16/G16),0)*ROUNDDOWN((O16/H16),0),ROUNDDOWN((N16/H16),0)*ROUNDDOWN((O16/G16),0)),IF(M16="M",G16,IF(AND(M16="PIEZA",G16<>0),(D16*F16)/ROUNDDOWN((N16/G16),0),IF(M16="PIEZA",(D16*F16),IF(M16="CAJA",(D16*F16),IF(M16="DM2",(D16*F16),IF(M16="FT",(D16*F16),IF(M16="JGO",(D16*F16),IF(M16="KG",(D16*F16),IF(M16="LB",(D16*F16),IF(M16="LT",(D16*F16),IF(M16="M2",(D16*F16),IF(M16="M3",(D16*F16),IF(M16="ROLLO",(D16*F16),IF(M16="SQYDS",(D16*F16),IF(M16="UD./SERV.",(D16*F16),IF(M16="YD",(D16*F16)," ")))))))))))))))))),"") | Q16: =IFERROR(IF(M16="HOJA",D16*F16*G16*H16*2*0.125,IF(AND(M16="PIEZA",H16=0),D16*F16*G16*VLOOKUP(J16,articulo:clave_comercial,10,0)*0.125,0))," ") -> 0 | S16: {=IFERROR(INDEX($J$3:$J$52,MATCH(0,INDEX(COUNTIF(S$2:$S15,$J$3:$J$52),0,0),0))," ")} | T16: {=IFERROR(INDEX($L$3:$L$52,MATCH(0,INDEX(COUNTIF($T$2:T15,$L$3:$L$52),0,0),0))," ")} | U16: =IFERROR(IF(AND(VLOOKUP(S16,$J$3:$Q$218,4,0)="KG",VLOOKUP(S16,$J$3:$Q$218,7,0)=0,VLOOKUP(S16,$J$3:$Q$218,8,0)=0),SUM($Q$3:$Q$218),SUMIF($J$3:$J$218,S16,$P$3:$P$218)),"") | W16: =IFERROR(IF(OR(M16="HOJA",M16="HOJA "),((MAX(ROUNDDOWN((0.915/G16),0)*ROUNDDOWN((2.44/H16),0),ROUNDDOWN((0.915/H16),0)*ROUNDDOWN((2.44/G16),0)))*G16*H16)/(0.915*2.44),""),"") | X16: =IFERROR(MAX(ROUNDDOWN((0.915/G16),0)*ROUNDDOWN((2.44/H16),0),ROUNDDOWN((0.915/H16),0)*ROUNDDOWN((2.44/G16),0)),"") | Y16: =IFERROR(IF(OR(M16="HOJA",M16="HOJA "),((MAX(ROUNDDOWN((0.915/G16),0)*ROUNDDOWN((3.05/H16),0),ROUNDDOWN((0.915/H16),0)*ROUNDDOWN((3.05/G16),0)))*G16*H16)/(0.915*3.05),""),"") | Z16: =IFERROR(MAX(ROUNDDOWN((0.915/G16),0)*ROUNDDOWN((3.05/H16),0),ROUNDDOWN((0.915/H16),0)*ROUNDDOWN((3.05/G16),0)),"") | AA16: =IFERROR(IF(OR(M16="HOJA",M16="HOJA "),((MAX(ROUNDDOWN((1.22/G16),0)*ROUNDDOWN((2.44/H16),0),ROUNDDOWN((1.22/H16),0)*ROUNDDOWN((2.44/G16),0)))*G16*H16)/(1.22*2.44),""),"") | AB16: =IFERROR(MAX(ROUNDDOWN((1.22/G16),0)*ROUNDDOWN((2.44/H16),0),ROUNDDOWN((1.22/H16),0)*ROUNDDOWN((2.44/G16),0)),"") | AC16: =IFERROR(IF(OR(M16="HOJA",M16="HOJA "),((MAX(ROUNDDOWN((1.22/G16),0)*ROUNDDOWN((3.05/H16),0),ROUNDDOWN((1.22/H16),0)*ROUNDDOWN((3.05/G16),0)))*G16*H16)/(1.22*3.05),""),"") | AD16: =IFERROR(MAX(ROUNDDOWN((1.22/G16),0)*ROUNDDOWN((3.05/H16),0),ROUNDDOWN((1.22/H16),0)*ROUNDDOWN((3.05/G16),0)),"")
L17: =IFERROR(VLOOKUP(J17,articulo:clave_comercial,2,0)," ") | M17: =UPPER(IFERROR(VLOOKUP(J17,articulo:clave_comercial,5,0)," ")) | N17: =IFERROR(IF(VLOOKUP(J17,articulo:clave_comercial,8,0)=0," ",VLOOKUP(J17,articulo:clave_comercial,8,0))," ") | O17: =IFERROR(IF(VLOOKUP(J17,articulo:clave_comercial,9,0)=0," ",VLOOKUP(J17,articulo:clave_comercial,9,0))," ") | P17: =IFERROR(IF(M17="HOJA",(D17*F17)/MAX(ROUNDDOWN((N17/G17),0)*ROUNDDOWN((O17/H17),0),ROUNDDOWN((N17/H17),0)*ROUNDDOWN((O17/G17),0)),IF(M17="HOJA ",(D17*F17)/MAX(ROUNDDOWN((N17/G17),0)*ROUNDDOWN((O17/H17),0),ROUNDDOWN((N17/H17),0)*ROUNDDOWN((O17/G17),0)),IF(M17="M",G17,IF(AND(M17="PIEZA",G17<>0),(D17*F17)/ROUNDDOWN((N17/G17),0),IF(M17="PIEZA",(D17*F17),IF(M17="CAJA",(D17*F17),IF(M17="DM2",(D17*F17),IF(M17="FT",(D17*F17),IF(M17="JGO",(D17*F17),IF(M17="KG",(D17*F17),IF(M17="LB",(D17*F17),IF(M17="LT",(D17*F17),IF(M17="M2",(D17*F17),IF(M17="M3",(D17*F17),IF(M17="ROLLO",(D17*F17),IF(M17="SQYDS",(D17*F17),IF(M17="UD./SERV.",(D17*F17),IF(M17="YD",(D17*F17)," ")))))))))))))))))),"") | Q17: =IFERROR(IF(M17="HOJA",D17*F17*G17*H17*2*0.125,IF(AND(M17="PIEZA",H17=0),D17*F17*G17*VLOOKUP(J17,articulo:clave_comercial,10,0)*0.125,0))," ") -> 0 | S17: {=IFERROR(INDEX($J$3:$J$52,MATCH(0,INDEX(COUNTIF(S$2:$S16,$J$3:$J$52),0,0),0))," ")} | T17: {=IFERROR(INDEX($L$3:$L$52,MATCH(0,INDEX(COUNTIF($T$2:T16,$L$3:$L$52),0,0),0))," ")} | U17: =IFERROR(IF(AND(VLOOKUP(S17,$J$3:$Q$218,4,0)="KG",VLOOKUP(S17,$J$3:$Q$218,7,0)=0,VLOOKUP(S17,$J$3:$Q$218,8,0)=0),SUM($Q$3:$Q$218),SUMIF($J$3:$J$218,S17,$P$3:$P$218)),"") | W17: =IFERROR(IF(OR(M17="HOJA",M17="HOJA "),((MAX(ROUNDDOWN((0.915/G17),0)*ROUNDDOWN((2.44/H17),0),ROUNDDOWN((0.915/H17),0)*ROUNDDOWN((2.44/G17),0)))*G17*H17)/(0.915*2.44),""),"") | X17: =IFERROR(MAX(ROUNDDOWN((0.915/G17),0)*ROUNDDOWN((2.44/H17),0),ROUNDDOWN((0.915/H17),0)*ROUNDDOWN((2.44/G17),0)),"") | Y17: =IFERROR(IF(OR(M17="HOJA",M17="HOJA "),((MAX(ROUNDDOWN((0.915/G17),0)*ROUNDDOWN((3.05/H17),0),ROUNDDOWN((0.915/H17),0)*ROUNDDOWN((3.05/G17),0)))*G17*H17)/(0.915*3.05),""),"") | Z17: =IFERROR(MAX(ROUNDDOWN((0.915/G17),0)*ROUNDDOWN((3.05/H17),0),ROUNDDOWN((0.915/H17),0)*ROUNDDOWN((3.05/G17),0)),"") | AA17: =IFERROR(IF(OR(M17="HOJA",M17="HOJA "),((MAX(ROUNDDOWN((1.22/G17),0)*ROUNDDOWN((2.44/H17),0),ROUNDDOWN((1.22/H17),0)*ROUNDDOWN((2.44/G17),0)))*G17*H17)/(1.22*2.44),""),"") | AB17: =IFERROR(MAX(ROUNDDOWN((1.22/G17),0)*ROUNDDOWN((2.44/H17),0),ROUNDDOWN((1.22/H17),0)*ROUNDDOWN((2.44/G17),0)),"") | AC17: =IFERROR(IF(OR(M17="HOJA",M17="HOJA "),((MAX(ROUNDDOWN((1.22/G17),0)*ROUNDDOWN((3.05/H17),0),ROUNDDOWN((1.22/H17),0)*ROUNDDOWN((3.05/G17),0)))*G17*H17)/(1.22*3.05),""),"") | AD17: =IFERROR(MAX(ROUNDDOWN((1.22/G17),0)*ROUNDDOWN((3.05/H17),0),ROUNDDOWN((1.22/H17),0)*ROUNDDOWN((3.05/G17),0)),"")
L18: =IFERROR(VLOOKUP(J18,articulo:clave_comercial,2,0)," ") | M18: =UPPER(IFERROR(VLOOKUP(J18,articulo:clave_comercial,5,0)," ")) | N18: =IFERROR(IF(VLOOKUP(J18,articulo:clave_comercial,8,0)=0," ",VLOOKUP(J18,articulo:clave_comercial,8,0))," ") | O18: =IFERROR(IF(VLOOKUP(J18,articulo:clave_comercial,9,0)=0," ",VLOOKUP(J18,articulo:clave_comercial,9,0))," ") | P18: =IFERROR(IF(M18="HOJA",(D18*F18)/MAX(ROUNDDOWN((N18/G18),0)*ROUNDDOWN((O18/H18),0),ROUNDDOWN((N18/H18),0)*ROUNDDOWN((O18/G18),0)),IF(M18="HOJA ",(D18*F18)/MAX(ROUNDDOWN((N18/G18),0)*ROUNDDOWN((O18/H18),0),ROUNDDOWN((N18/H18),0)*ROUNDDOWN((O18/G18),0)),IF(M18="M",G18,IF(AND(M18="PIEZA",G18<>0),(D18*F18)/ROUNDDOWN((N18/G18),0),IF(M18="PIEZA",(D18*F18),IF(M18="CAJA",(D18*F18),IF(M18="DM2",(D18*F18),IF(M18="FT",(D18*F18),IF(M18="JGO",(D18*F18),IF(M18="KG",(D18*F18),IF(M18="LB",(D18*F18),IF(M18="LT",(D18*F18),IF(M18="M2",(D18*F18),IF(M18="M3",(D18*F18),IF(M18="ROLLO",(D18*F18),IF(M18="SQYDS",(D18*F18),IF(M18="UD./SERV.",(D18*F18),IF(M18="YD",(D18*F18)," ")))))))))))))))))),"") | Q18: =IFERROR(IF(M18="HOJA",D18*F18*G18*H18*2*0.125,IF(AND(M18="PIEZA",H18=0),D18*F18*G18*VLOOKUP(J18,articulo:clave_comercial,10,0)*0.125,0))," ") -> 0 | S18: {=IFERROR(INDEX($J$3:$J$52,MATCH(0,INDEX(COUNTIF(S$2:$S16,$J$3:$J$52),0,0),0))," ")} | T18: {=IFERROR(INDEX($L$3:$L$52,MATCH(0,INDEX(COUNTIF($T$2:T16,$L$3:$L$52),0,0),0))," ")} | U18: =IFERROR(IF(AND(VLOOKUP(S18,$J$3:$Q$218,4,0)="KG",VLOOKUP(S18,$J$3:$Q$218,7,0)=0,VLOOKUP(S18,$J$3:$Q$218,8,0)=0),SUM($Q$3:$Q$218),SUMIF($J$3:$J$218,S18,$P$3:$P$218)),"") | W18: =IFERROR(IF(OR(M18="HOJA",M18="HOJA "),((MAX(ROUNDDOWN((0.915/G18),0)*ROUNDDOWN((2.44/H18),0),ROUNDDOWN((0.915/H18),0)*ROUNDDOWN((2.44/G18),0)))*G18*H18)/(0.915*2.44),""),"") | X18: =IFERROR(MAX(ROUNDDOWN((0.915/G18),0)*ROUNDDOWN((2.44/H18),0),ROUNDDOWN((0.915/H18),0)*ROUNDDOWN((2.44/G18),0)),"") | Y18: =IFERROR(IF(OR(M18="HOJA",M18="HOJA "),((MAX(ROUNDDOWN((0.915/G18),0)*ROUNDDOWN((3.05/H18),0),ROUNDDOWN((0.915/H18),0)*ROUNDDOWN((3.05/G18),0)))*G18*H18)/(0.915*3.05),""),"") | Z18: =IFERROR(MAX(ROUNDDOWN((0.915/G18),0)*ROUNDDOWN((3.05/H18),0),ROUNDDOWN((0.915/H18),0)*ROUNDDOWN((3.05/G18),0)),"") | AA18: =IFERROR(IF(OR(M18="HOJA",M18="HOJA "),((MAX(ROUNDDOWN((1.22/G18),0)*ROUNDDOWN((2.44/H18),0),ROUNDDOWN((1.22/H18),0)*ROUNDDOWN((2.44/G18),0)))*G18*H18)/(1.22*2.44),""),"") | AB18: =IFERROR(MAX(ROUNDDOWN((1.22/G18),0)*ROUNDDOWN((2.44/H18),0),ROUNDDOWN((1.22/H18),0)*ROUNDDOWN((2.44/G18),0)),"") | AC18: =IFERROR(IF(OR(M18="HOJA",M18="HOJA "),((MAX(ROUNDDOWN((1.22/G18),0)*ROUNDDOWN((3.05/H18),0),ROUNDDOWN((1.22/H18),0)*ROUNDDOWN((3.05/G18),0)))*G18*H18)/(1.22*3.05),""),"") | AD18: =IFERROR(MAX(ROUNDDOWN((1.22/G18),0)*ROUNDDOWN((3.05/H18),0),ROUNDDOWN((1.22/H18),0)*ROUNDDOWN((3.05/G18),0)),"")
L19: =IFERROR(VLOOKUP(J19,articulo:clave_comercial,2,0)," ") | M19: =UPPER(IFERROR(VLOOKUP(J19,articulo:clave_comercial,5,0)," ")) | N19: =IFERROR(IF(VLOOKUP(J19,articulo:clave_comercial,8,0)=0," ",VLOOKUP(J19,articulo:clave_comercial,8,0))," ") | O19: =IFERROR(IF(VLOOKUP(J19,articulo:clave_comercial,9,0)=0," ",VLOOKUP(J19,articulo:clave_comercial,9,0))," ") | P19: =IFERROR(IF(M19="HOJA",(D19*F19)/MAX(ROUNDDOWN((N19/G19),0)*ROUNDDOWN((O19/H19),0),ROUNDDOWN((N19/H19),0)*ROUNDDOWN((O19/G19),0)),IF(M19="HOJA ",(D19*F19)/MAX(ROUNDDOWN((N19/G19),0)*ROUNDDOWN((O19/H19),0),ROUNDDOWN((N19/H19),0)*ROUNDDOWN((O19/G19),0)),IF(M19="M",G19,IF(AND(M19="PIEZA",G19<>0),(D19*F19)/ROUNDDOWN((N19/G19),0),IF(M19="PIEZA",(D19*F19),IF(M19="CAJA",(D19*F19),IF(M19="DM2",(D19*F19),IF(M19="FT",(D19*F19),IF(M19="JGO",(D19*F19),IF(M19="KG",(D19*F19),IF(M19="LB",(D19*F19),IF(M19="LT",(D19*F19),IF(M19="M2",(D19*F19),IF(M19="M3",(D19*F19),IF(M19="ROLLO",(D19*F19),IF(M19="SQYDS",(D19*F19),IF(M19="UD./SERV.",(D19*F19),IF(M19="YD",(D19*F19)," ")))))))))))))))))),"") | Q19: =IFERROR(IF(M19="HOJA",D19*F19*G19*H19*2*0.125,IF(AND(M19="PIEZA",H19=0),D19*F19*G19*VLOOKUP(J19,articulo:clave_comercial,10,0)*0.125,0))," ") -> 0 | S19: {=IFERROR(INDEX($J$3:$J$52,MATCH(0,INDEX(COUNTIF(S$2:$S17,$J$3:$J$52),0,0),0))," ")} | T19: {=IFERROR(INDEX($L$3:$L$52,MATCH(0,INDEX(COUNTIF($T$2:T17,$L$3:$L$52),0,0),0))," ")} | U19: =IFERROR(IF(AND(VLOOKUP(S19,$J$3:$Q$218,4,0)="KG",VLOOKUP(S19,$J$3:$Q$218,7,0)=0,VLOOKUP(S19,$J$3:$Q$218,8,0)=0),SUM($Q$3:$Q$218),SUMIF($J$3:$J$218,S19,$P$3:$P$218)),"") | W19: =IFERROR(IF(OR(M19="HOJA",M19="HOJA "),((MAX(ROUNDDOWN((0.915/G19),0)*ROUNDDOWN((2.44/H19),0),ROUNDDOWN((0.915/H19),0)*ROUNDDOWN((2.44/G19),0)))*G19*H19)/(0.915*2.44),""),"") | X19: =IFERROR(MAX(ROUNDDOWN((0.915/G19),0)*ROUNDDOWN((2.44/H19),0),ROUNDDOWN((0.915/H19),0)*ROUNDDOWN((2.44/G19),0)),"") | Y19: =IFERROR(IF(OR(M19="HOJA",M19="HOJA "),((MAX(ROUNDDOWN((0.915/G19),0)*ROUNDDOWN((3.05/H19),0),ROUNDDOWN((0.915/H19),0)*ROUNDDOWN((3.05/G19),0)))*G19*H19)/(0.915*3.05),""),"") | Z19: =IFERROR(MAX(ROUNDDOWN((0.915/G19),0)*ROUNDDOWN((3.05/H19),0),ROUNDDOWN((0.915/H19),0)*ROUNDDOWN((3.05/G19),0)),"") | AA19: =IFERROR(IF(OR(M19="HOJA",M19="HOJA "),((MAX(ROUNDDOWN((1.22/G19),0)*ROUNDDOWN((2.44/H19),0),ROUNDDOWN((1.22/H19),0)*ROUNDDOWN((2.44/G19),0)))*G19*H19)/(1.22*2.44),""),"") | AB19: =IFERROR(MAX(ROUNDDOWN((1.22/G19),0)*ROUNDDOWN((2.44/H19),0),ROUNDDOWN((1.22/H19),0)*ROUNDDOWN((2.44/G19),0)),"") | AC19: =IFERROR(IF(OR(M19="HOJA",M19="HOJA "),((MAX(ROUNDDOWN((1.22/G19),0)*ROUNDDOWN((3.05/H19),0),ROUNDDOWN((1.22/H19),0)*ROUNDDOWN((3.05/G19),0)))*G19*H19)/(1.22*3.05),""),"") | AD19: =IFERROR(MAX(ROUNDDOWN((1.22/G19),0)*ROUNDDOWN((3.05/H19),0),ROUNDDOWN((1.22/H19),0)*ROUNDDOWN((3.05/G19),0)),"")
L20: =IFERROR(VLOOKUP(J20,articulo:clave_comercial,2,0)," ") | M20: =UPPER(IFERROR(VLOOKUP(J20,articulo:clave_comercial,5,0)," ")) | N20: =IFERROR(IF(VLOOKUP(J20,articulo:clave_comercial,8,0)=0," ",VLOOKUP(J20,articulo:clave_comercial,8,0))," ") | O20: =IFERROR(IF(VLOOKUP(J20,articulo:clave_comercial,9,0)=0," ",VLOOKUP(J20,articulo:clave_comercial,9,0))," ") | P20: =IFERROR(IF(M20="HOJA",(D20*F20)/MAX(ROUNDDOWN((N20/G20),0)*ROUNDDOWN((O20/H20),0),ROUNDDOWN((N20/H20),0)*ROUNDDOWN((O20/G20),0)),IF(M20="HOJA ",(D20*F20)/MAX(ROUNDDOWN((N20/G20),0)*ROUNDDOWN((O20/H20),0),ROUNDDOWN((N20/H20),0)*ROUNDDOWN((O20/G20),0)),IF(M20="M",G20,IF(AND(M20="PIEZA",G20<>0),(D20*F20)/ROUNDDOWN((N20/G20),0),IF(M20="PIEZA",(D20*F20),IF(M20="CAJA",(D20*F20),IF(M20="DM2",(D20*F20),IF(M20="FT",(D20*F20),IF(M20="JGO",(D20*F20),IF(M20="KG",(D20*F20),IF(M20="LB",(D20*F20),IF(M20="LT",(D20*F20),IF(M20="M2",(D20*F20),IF(M20="M3",(D20*F20),IF(M20="ROLLO",(D20*F20),IF(M20="SQYDS",(D20*F20),IF(M20="UD./SERV.",(D20*F20),IF(M20="YD",(D20*F20)," ")))))))))))))))))),"") | Q20: =IFERROR(IF(M20="HOJA",D20*F20*G20*H20*2*0.125,IF(AND(M20="PIEZA",H20=0),D20*F20*G20*VLOOKUP(J20,articulo:clave_comercial,10,0)*0.125,0))," ") -> 0 | S20: {=IFERROR(INDEX($J$3:$J$52,MATCH(0,INDEX(COUNTIF(S$2:$S19,$J$3:$J$52),0,0),0))," ")} | T20: {=IFERROR(INDEX($L$3:$L$52,MATCH(0,INDEX(COUNTIF($T$2:T19,$L$3:$L$52),0,0),0))," ")} | U20: =IFERROR(IF(AND(VLOOKUP(S20,$J$3:$Q$218,4,0)="KG",VLOOKUP(S20,$J$3:$Q$218,7,0)=0,VLOOKUP(S20,$J$3:$Q$218,8,0)=0),SUM($Q$3:$Q$218),SUMIF($J$3:$J$218,S20,$P$3:$P$218)),"") | W20: =IFERROR(IF(OR(M20="HOJA",M20="HOJA "),((MAX(ROUNDDOWN((0.915/G20),0)*ROUNDDOWN((2.44/H20),0),ROUNDDOWN((0.915/H20),0)*ROUNDDOWN((2.44/G20),0)))*G20*H20)/(0.915*2.44),""),"") | X20: =IFERROR(MAX(ROUNDDOWN((0.915/G20),0)*ROUNDDOWN((2.44/H20),0),ROUNDDOWN((0.915/H20),0)*ROUNDDOWN((2.44/G20),0)),"") | Y20: =IFERROR(IF(OR(M20="HOJA",M20="HOJA "),((MAX(ROUNDDOWN((0.915/G20),0)*ROUNDDOWN((3.05/H20),0),ROUNDDOWN((0.915/H20),0)*ROUNDDOWN((3.05/G20),0)))*G20*H20)/(0.915*3.05),""),"") | Z20: =IFERROR(MAX(ROUNDDOWN((0.915/G20),0)*ROUNDDOWN((3.05/H20),0),ROUNDDOWN((0.915/H20),0)*ROUNDDOWN((3.05/G20),0)),"") | AA20: =IFERROR(IF(OR(M20="HOJA",M20="HOJA "),((MAX(ROUNDDOWN((1.22/G20),0)*ROUNDDOWN((2.44/H20),0),ROUNDDOWN((1.22/H20),0)*ROUNDDOWN((2.44/G20),0)))*G20*H20)/(1.22*2.44),""),"") | AB20: =IFERROR(MAX(ROUNDDOWN((1.22/G20),0)*ROUNDDOWN((2.44/H20),0),ROUNDDOWN((1.22/H20),0)*ROUNDDOWN((2.44/G20),0)),"") | AC20: =IFERROR(IF(OR(M20="HOJA",M20="HOJA "),((MAX(ROUNDDOWN((1.22/G20),0)*ROUNDDOWN((3.05/H20),0),ROUNDDOWN((1.22/H20),0)*ROUNDDOWN((3.05/G20),0)))*G20*H20)/(1.22*3.05),""),"") | AD20: =IFERROR(MAX(ROUNDDOWN((1.22/G20),0)*ROUNDDOWN((3.05/H20),0),ROUNDDOWN((1.22/H20),0)*ROUNDDOWN((3.05/G20),0)),"")
A21: 4 | L21: =IFERROR(VLOOKUP(J21,articulo:clave_comercial,2,0)," ") | M21: =UPPER(IFERROR(VLOOKUP(J21,articulo:clave_comercial,5,0)," ")) | N21: =IFERROR(IF(VLOOKUP(J21,articulo:clave_comercial,8,0)=0," ",VLOOKUP(J21,articulo:clave_comercial,8,0))," ") | O21: =IFERROR(IF(VLOOKUP(J21,articulo:clave_comercial,9,0)=0," ",VLOOKUP(J21,articulo:clave_comercial,9,0))," ") | P21: =IFERROR(IF(M21="HOJA",(D21*F21)/MAX(ROUNDDOWN((N21/G21),0)*ROUNDDOWN((O21/H21),0),ROUNDDOWN((N21/H21),0)*ROUNDDOWN((O21/G21),0)),IF(M21="HOJA ",(D21*F21)/MAX(ROUNDDOWN((N21/G21),0)*ROUNDDOWN((O21/H21),0),ROUNDDOWN((N21/H21),0)*ROUNDDOWN((O21/G21),0)),IF(M21="M",G21,IF(AND(M21="PIEZA",G21<>0),(D21*F21)/ROUNDDOWN((N21/G21),0),IF(M21="PIEZA",(D21*F21),IF(M21="CAJA",(D21*F21),IF(M21="DM2",(D21*F21),IF(M21="FT",(D21*F21),IF(M21="JGO",(D21*F21),IF(M21="KG",(D21*F21),IF(M21="LB",(D21*F21),IF(M21="LT",(D21*F21),IF(M21="M2",(D21*F21),IF(M21="M3",(D21*F21),IF(M21="ROLLO",(D21*F21),IF(M21="SQYDS",(D21*F21),IF(M21="UD./SERV.",(D21*F21),IF(M21="YD",(D21*F21)," ")))))))))))))))))),"") | Q21: =IFERROR(IF(M21="HOJA",D21*F21*G21*H21*2*0.125,IF(AND(M21="PIEZA",H21=0),D21*F21*G21*VLOOKUP(J21,articulo:clave_comercial,10,0)*0.125,0))," ") -> 0 | S21: {=IFERROR(INDEX($J$3:$J$52,MATCH(0,INDEX(COUNTIF(S$2:$S20,$J$3:$J$52),0,0),0))," ")} | T21: {=IFERROR(INDEX($L$3:$L$52,MATCH(0,INDEX(COUNTIF($T$2:T20,$L$3:$L$52),0,0),0))," ")} | U21: =IFERROR(IF(AND(VLOOKUP(S21,$J$3:$Q$218,4,0)="KG",VLOOKUP(S21,$J$3:$Q$218,7,0)=0,VLOOKUP(S21,$J$3:$Q$218,8,0)=0),SUM($Q$3:$Q$218),SUMIF($J$3:$J$218,S21,$P$3:$P$218)),"") | W21: =IFERROR(IF(OR(M21="HOJA",M21="HOJA "),((MAX(ROUNDDOWN((0.915/G21),0)*ROUNDDOWN((2.44/H21),0),ROUNDDOWN((0.915/H21),0)*ROUNDDOWN((2.44/G21),0)))*G21*H21)/(0.915*2.44),""),"") | X21: =IFERROR(MAX(ROUNDDOWN((0.915/G21),0)*ROUNDDOWN((2.44/H21),0),ROUNDDOWN((0.915/H21),0)*ROUNDDOWN((2.44/G21),0)),"") | Y21: =IFERROR(IF(OR(M21="HOJA",M21="HOJA "),((MAX(ROUNDDOWN((0.915/G21),0)*ROUNDDOWN((3.05/H21),0),ROUNDDOWN((0.915/H21),0)*ROUNDDOWN((3.05/G21),0)))*G21*H21)/(0.915*3.05),""),"") | Z21: =IFERROR(MAX(ROUNDDOWN((0.915/G21),0)*ROUNDDOWN((3.05/H21),0),ROUNDDOWN((0.915/H21),0)*ROUNDDOWN((3.05/G21),0)),"") | AA21: =IFERROR(IF(OR(M21="HOJA",M21="HOJA "),((MAX(ROUNDDOWN((1.22/G21),0)*ROUNDDOWN((2.44/H21),0),ROUNDDOWN((1.22/H21),0)*ROUNDDOWN((2.44/G21),0)))*G21*H21)/(1.22*2.44),""),"") | AB21: =IFERROR(MAX(ROUNDDOWN((1.22/G21),0)*ROUNDDOWN((2.44/H21),0),ROUNDDOWN((1.22/H21),0)*ROUNDDOWN((2.44/G21),0)),"") | AC21: =IFERROR(IF(OR(M21="HOJA",M21="HOJA "),((MAX(ROUNDDOWN((1.22/G21),0)*ROUNDDOWN((3.05/H21),0),ROUNDDOWN((1.22/H21),0)*ROUNDDOWN((3.05/G21),0)))*G21*H21)/(1.22*3.05),""),"") | AD21: =IFERROR(MAX(ROUNDDOWN((1.22/G21),0)*ROUNDDOWN((3.05/H21),0),ROUNDDOWN((1.22/H21),0)*ROUNDDOWN((3.05/G21),0)),"")
L22: =IFERROR(VLOOKUP(J22,articulo:clave_comercial,2,0)," ") | M22: =UPPER(IFERROR(VLOOKUP(J22,articulo:clave_comercial,5,0)," ")) | N22: =IFERROR(IF(VLOOKUP(J22,articulo:clave_comercial,8,0)=0," ",VLOOKUP(J22,articulo:clave_comercial,8,0))," ") | O22: =IFERROR(IF(VLOOKUP(J22,articulo:clave_comercial,9,0)=0," ",VLOOKUP(J22,articulo:clave_comercial,9,0))," ") | P22: =IFERROR(IF(M22="HOJA",(D22*F22)/MAX(ROUNDDOWN((N22/G22),0)*ROUNDDOWN((O22/H22),0),ROUNDDOWN((N22/H22),0)*ROUNDDOWN((O22/G22),0)),IF(M22="HOJA ",(D22*F22)/MAX(ROUNDDOWN((N22/G22),0)*ROUNDDOWN((O22/H22),0),ROUNDDOWN((N22/H22),0)*ROUNDDOWN((O22/G22),0)),IF(M22="M",G22,IF(AND(M22="PIEZA",G22<>0),(D22*F22)/ROUNDDOWN((N22/G22),0),IF(M22="PIEZA",(D22*F22),IF(M22="CAJA",(D22*F22),IF(M22="DM2",(D22*F22),IF(M22="FT",(D22*F22),IF(M22="JGO",(D22*F22),IF(M22="KG",(D22*F22),IF(M22="LB",(D22*F22),IF(M22="LT",(D22*F22),IF(M22="M2",(D22*F22),IF(M22="M3",(D22*F22),IF(M22="ROLLO",(D22*F22),IF(M22="SQYDS",(D22*F22),IF(M22="UD./SERV.",(D22*F22),IF(M22="YD",(D22*F22)," ")))))))))))))))))),"") | Q22: =IFERROR(IF(M22="HOJA",D22*F22*G22*H22*2*0.125,IF(AND(M22="PIEZA",H22=0),D22*F22*G22*VLOOKUP(J22,articulo:clave_comercial,10,0)*0.125,0))," ") -> 0 | S22: {=IFERROR(INDEX($J$3:$J$52,MATCH(0,INDEX(COUNTIF(S$2:$S21,$J$3:$J$52),0,0),0))," ")} | T22: {=IFERROR(INDEX($L$3:$L$52,MATCH(0,INDEX(COUNTIF($T$2:T21,$L$3:$L$52),0,0),0))," ")} | U22: =IFERROR(IF(AND(VLOOKUP(S22,$J$3:$Q$218,4,0)="KG",VLOOKUP(S22,$J$3:$Q$218,7,0)=0,VLOOKUP(S22,$J$3:$Q$218,8,0)=0),SUM($Q$3:$Q$218),SUMIF($J$3:$J$218,S22,$P$3:$P$218)),"") | W22: =IFERROR(IF(OR(M22="HOJA",M22="HOJA "),((MAX(ROUNDDOWN((0.915/G22),0)*ROUNDDOWN((2.44/H22),0),ROUNDDOWN((0.915/H22),0)*ROUNDDOWN((2.44/G22),0)))*G22*H22)/(0.915*2.44),""),"") | X22: =IFERROR(MAX(ROUNDDOWN((0.915/G22),0)*ROUNDDOWN((2.44/H22),0),ROUNDDOWN((0.915/H22),0)*ROUNDDOWN((2.44/G22),0)),"") | Y22: =IFERROR(IF(OR(M22="HOJA",M22="HOJA "),((MAX(ROUNDDOWN((0.915/G22),0)*ROUNDDOWN((3.05/H22),0),ROUNDDOWN((0.915/H22),0)*ROUNDDOWN((3.05/G22),0)))*G22*H22)/(0.915*3.05),""),"") | Z22: =IFERROR(MAX(ROUNDDOWN((0.915/G22),0)*ROUNDDOWN((3.05/H22),0),ROUNDDOWN((0.915/H22),0)*ROUNDDOWN((3.05/G22),0)),"") | AA22: =IFERROR(IF(OR(M22="HOJA",M22="HOJA "),((MAX(ROUNDDOWN((1.22/G22),0)*ROUNDDOWN((2.44/H22),0),ROUNDDOWN((1.22/H22),0)*ROUNDDOWN((2.44/G22),0)))*G22*H22)/(1.22*2.44),""),"") | AB22: =IFERROR(MAX(ROUNDDOWN((1.22/G22),0)*ROUNDDOWN((2.44/H22),0),ROUNDDOWN((1.22/H22),0)*ROUNDDOWN((2.44/G22),0)),"") | AC22: =IFERROR(IF(OR(M22="HOJA",M22="HOJA "),((MAX(ROUNDDOWN((1.22/G22),0)*ROUNDDOWN((3.05/H22),0),ROUNDDOWN((1.22/H22),0)*ROUNDDOWN((3.05/G22),0)))*G22*H22)/(1.22*3.05),""),"") | AD22: =IFERROR(MAX(ROUNDDOWN((1.22/G22),0)*ROUNDDOWN((3.05/H22),0),ROUNDDOWN((1.22/H22),0)*ROUNDDOWN((3.05/G22),0)),"")
L23: =IFERROR(VLOOKUP(J23,articulo:clave_comercial,2,0)," ") | M23: =UPPER(IFERROR(VLOOKUP(J23,articulo:clave_comercial,5,0)," ")) | N23: =IFERROR(IF(VLOOKUP(J23,articulo:clave_comercial,8,0)=0," ",VLOOKUP(J23,articulo:clave_comercial,8,0))," ") | O23: =IFERROR(IF(VLOOKUP(J23,articulo:clave_comercial,9,0)=0," ",VLOOKUP(J23,articulo:clave_comercial,9,0))," ") | P23: =IFERROR(IF(M23="HOJA",(D23*F23)/MAX(ROUNDDOWN((N23/G23),0)*ROUNDDOWN((O23/H23),0),ROUNDDOWN((N23/H23),0)*ROUNDDOWN((O23/G23),0)),IF(M23="HOJA ",(D23*F23)/MAX(ROUNDDOWN((N23/G23),0)*ROUNDDOWN((O23/H23),0),ROUNDDOWN((N23/H23),0)*ROUNDDOWN((O23/G23),0)),IF(M23="M",G23,IF(AND(M23="PIEZA",G23<>0),(D23*F23)/ROUNDDOWN((N23/G23),0),IF(M23="PIEZA",(D23*F23),IF(M23="CAJA",(D23*F23),IF(M23="DM2",(D23*F23),IF(M23="FT",(D23*F23),IF(M23="JGO",(D23*F23),IF(M23="KG",(D23*F23),IF(M23="LB",(D23*F23),IF(M23="LT",(D23*F23),IF(M23="M2",(D23*F23),IF(M23="M3",(D23*F23),IF(M23="ROLLO",(D23*F23),IF(M23="SQYDS",(D23*F23),IF(M23="UD./SERV.",(D23*F23),IF(M23="YD",(D23*F23)," ")))))))))))))))))),"") | Q23: =IFERROR(IF(M23="HOJA",D23*F23*G23*H23*2*0.125,IF(AND(M23="PIEZA",H23=0),D23*F23*G23*VLOOKUP(J23,articulo:clave_comercial,10,0)*0.125,0))," ") -> 0 | S23: {=IFERROR(INDEX($J$3:$J$52,MATCH(0,INDEX(COUNTIF(S$2:$S22,$J$3:$J$52),0,0),0))," ")} | T23: {=IFERROR(INDEX($L$3:$L$52,MATCH(0,INDEX(COUNTIF($T$2:T22,$L$3:$L$52),0,0),0))," ")} | U23: =IFERROR(IF(AND(VLOOKUP(S23,$J$3:$Q$218,4,0)="KG",VLOOKUP(S23,$J$3:$Q$218,7,0)=0,VLOOKUP(S23,$J$3:$Q$218,8,0)=0),SUM($Q$3:$Q$218),SUMIF($J$3:$J$218,S23,$P$3:$P$218)),"") | W23: =IFERROR(IF(OR(M23="HOJA",M23="HOJA "),((MAX(ROUNDDOWN((0.915/G23),0)*ROUNDDOWN((2.44/H23),0),ROUNDDOWN((0.915/H23),0)*ROUNDDOWN((2.44/G23),0)))*G23*H23)/(0.915*2.44),""),"") | X23: =IFERROR(MAX(ROUNDDOWN((0.915/G23),0)*ROUNDDOWN((2.44/H23),0),ROUNDDOWN((0.915/H23),0)*ROUNDDOWN((2.44/G23),0)),"") | Y23: =IFERROR(IF(OR(M23="HOJA",M23="HOJA "),((MAX(ROUNDDOWN((0.915/G23),0)*ROUNDDOWN((3.05/H23),0),ROUNDDOWN((0.915/H23),0)*ROUNDDOWN((3.05/G23),0)))*G23*H23)/(0.915*3.05),""),"") | Z23: =IFERROR(MAX(ROUNDDOWN((0.915/G23),0)*ROUNDDOWN((3.05/H23),0),ROUNDDOWN((0.915/H23),0)*ROUNDDOWN((3.05/G23),0)),"") | AA23: =IFERROR(IF(OR(M23="HOJA",M23="HOJA "),((MAX(ROUNDDOWN((1.22/G23),0)*ROUNDDOWN((2.44/H23),0),ROUNDDOWN((1.22/H23),0)*ROUNDDOWN((2.44/G23),0)))*G23*H23)/(1.22*2.44),""),"") | AB23: =IFERROR(MAX(ROUNDDOWN((1.22/G23),0)*ROUNDDOWN((2.44/H23),0),ROUNDDOWN((1.22/H23),0)*ROUNDDOWN((2.44/G23),0)),"") | AC23: =IFERROR(IF(OR(M23="HOJA",M23="HOJA "),((MAX(ROUNDDOWN((1.22/G23),0)*ROUNDDOWN((3.05/H23),0),ROUNDDOWN((1.22/H23),0)*ROUNDDOWN((3.05/G23),0)))*G23*H23)/(1.22*3.05),""),"") | AD23: =IFERROR(MAX(ROUNDDOWN((1.22/G23),0)*ROUNDDOWN((3.05/H23),0),ROUNDDOWN((1.22/H23),0)*ROUNDDOWN((3.05/G23),0)),"")
L24: =IFERROR(VLOOKUP(J24,articulo:clave_comercial,2,0)," ") | M24: =UPPER(IFERROR(VLOOKUP(J24,articulo:clave_comercial,5,0)," ")) | N24: =IFERROR(IF(VLOOKUP(J24,articulo:clave_comercial,8,0)=0," ",VLOOKUP(J24,articulo:clave_comercial,8,0))," ") | O24: =IFERROR(IF(VLOOKUP(J24,articulo:clave_comercial,9,0)=0," ",VLOOKUP(J24,articulo:clave_comercial,9,0))," ") | P24: =IFERROR(IF(M24="HOJA",(D24*F24)/MAX(ROUNDDOWN((N24/G24),0)*ROUNDDOWN((O24/H24),0),ROUNDDOWN((N24/H24),0)*ROUNDDOWN((O24/G24),0)),IF(M24="HOJA ",(D24*F24)/MAX(ROUNDDOWN((N24/G24),0)*ROUNDDOWN((O24/H24),0),ROUNDDOWN((N24/H24),0)*ROUNDDOWN((O24/G24),0)),IF(M24="M",G24,IF(AND(M24="PIEZA",G24<>0),(D24*F24)/ROUNDDOWN((N24/G24),0),IF(M24="PIEZA",(D24*F24),IF(M24="CAJA",(D24*F24),IF(M24="DM2",(D24*F24),IF(M24="FT",(D24*F24),IF(M24="JGO",(D24*F24),IF(M24="KG",(D24*F24),IF(M24="LB",(D24*F24),IF(M24="LT",(D24*F24),IF(M24="M2",(D24*F24),IF(M24="M3",(D24*F24),IF(M24="ROLLO",(D24*F24),IF(M24="SQYDS",(D24*F24),IF(M24="UD./SERV.",(D24*F24),IF(M24="YD",(D24*F24)," ")))))))))))))))))),"") | Q24: =IFERROR(IF(M24="HOJA",D24*F24*G24*H24*2*0.125,IF(AND(M24="PIEZA",H24=0),D24*F24*G24*VLOOKUP(J24,articulo:clave_comercial,10,0)*0.125,0))," ") -> 0 | S24: {=IFERROR(INDEX($J$3:$J$52,MATCH(0,INDEX(COUNTIF(S$2:$S23,$J$3:$J$52),0,0),0))," ")} | T24: {=IFERROR(INDEX($L$3:$L$52,MATCH(0,INDEX(COUNTIF($T$2:T23,$L$3:$L$52),0,0),0))," ")} | U24: =IFERROR(IF(AND(VLOOKUP(S24,$J$3:$Q$218,4,0)="KG",VLOOKUP(S24,$J$3:$Q$218,7,0)=0,VLOOKUP(S24,$J$3:$Q$218,8,0)=0),SUM($Q$3:$Q$218),SUMIF($J$3:$J$218,S24,$P$3:$P$218)),"") | W24: =IFERROR(IF(OR(M24="HOJA",M24="HOJA "),((MAX(ROUNDDOWN((0.915/G24),0)*ROUNDDOWN((2.44/H24),0),ROUNDDOWN((0.915/H24),0)*ROUNDDOWN((2.44/G24),0)))*G24*H24)/(0.915*2.44),""),"") | X24: =IFERROR(MAX(ROUNDDOWN((0.915/G24),0)*ROUNDDOWN((2.44/H24),0),ROUNDDOWN((0.915/H24),0)*ROUNDDOWN((2.44/G24),0)),"") | Y24: =IFERROR(IF(OR(M24="HOJA",M24="HOJA "),((MAX(ROUNDDOWN((0.915/G24),0)*ROUNDDOWN((3.05/H24),0),ROUNDDOWN((0.915/H24),0)*ROUNDDOWN((3.05/G24),0)))*G24*H24)/(0.915*3.05),""),"") | Z24: =IFERROR(MAX(ROUNDDOWN((0.915/G24),0)*ROUNDDOWN((3.05/H24),0),ROUNDDOWN((0.915/H24),0)*ROUNDDOWN((3.05/G24),0)),"") | AA24: =IFERROR(IF(OR(M24="HOJA",M24="HOJA "),((MAX(ROUNDDOWN((1.22/G24),0)*ROUNDDOWN((2.44/H24),0),ROUNDDOWN((1.22/H24),0)*ROUNDDOWN((2.44/G24),0)))*G24*H24)/(1.22*2.44),""),"") | AB24: =IFERROR(MAX(ROUNDDOWN((1.22/G24),0)*ROUNDDOWN((2.44/H24),0),ROUNDDOWN((1.22/H24),0)*ROUNDDOWN((2.44/G24),0)),"") | AC24: =IFERROR(IF(OR(M24="HOJA",M24="HOJA "),((MAX(ROUNDDOWN((1.22/G24),0)*ROUNDDOWN((3.05/H24),0),ROUNDDOWN((1.22/H24),0)*ROUNDDOWN((3.05/G24),0)))*G24*H24)/(1.22*3.05),""),"") | AD24: =IFERROR(MAX(ROUNDDOWN((1.22/G24),0)*ROUNDDOWN((3.05/H24),0),ROUNDDOWN((1.22/H24),0)*ROUNDDOWN((3.05/G24),0)),"")
L25: =IFERROR(VLOOKUP(J25,articulo:clave_comercial,2,0)," ") | M25: =UPPER(IFERROR(VLOOKUP(J25,articulo:clave_comercial,5,0)," ")) | N25: =IFERROR(IF(VLOOKUP(J25,articulo:clave_comercial,8,0)=0," ",VLOOKUP(J25,articulo:clave_comercial,8,0))," ") | O25: =IFERROR(IF(VLOOKUP(J25,articulo:clave_comercial,9,0)=0," ",VLOOKUP(J25,articulo:clave_comercial,9,0))," ") | P25: =IFERROR(IF(M25="HOJA",(D25*F25)/MAX(ROUNDDOWN((N25/G25),0)*ROUNDDOWN((O25/H25),0),ROUNDDOWN((N25/H25),0)*ROUNDDOWN((O25/G25),0)),IF(M25="HOJA ",(D25*F25)/MAX(ROUNDDOWN((N25/G25),0)*ROUNDDOWN((O25/H25),0),ROUNDDOWN((N25/H25),0)*ROUNDDOWN((O25/G25),0)),IF(M25="M",G25,IF(AND(M25="PIEZA",G25<>0),(D25*F25)/ROUNDDOWN((N25/G25),0),IF(M25="PIEZA",(D25*F25),IF(M25="CAJA",(D25*F25),IF(M25="DM2",(D25*F25),IF(M25="FT",(D25*F25),IF(M25="JGO",(D25*F25),IF(M25="KG",(D25*F25),IF(M25="LB",(D25*F25),IF(M25="LT",(D25*F25),IF(M25="M2",(D25*F25),IF(M25="M3",(D25*F25),IF(M25="ROLLO",(D25*F25),IF(M25="SQYDS",(D25*F25),IF(M25="UD./SERV.",(D25*F25),IF(M25="YD",(D25*F25)," ")))))))))))))))))),"") | Q25: =IFERROR(IF(M25="HOJA",D25*F25*G25*H25*2*0.125,IF(AND(M25="PIEZA",H25=0),D25*F25*G25*VLOOKUP(J25,articulo:clave_comercial,10,0)*0.125,0))," ") -> 0 | S25: {=IFERROR(INDEX($J$3:$J$52,MATCH(0,INDEX(COUNTIF(S$2:$S24,$J$3:$J$52),0,0),0))," ")} | T25: {=IFERROR(INDEX($L$3:$L$52,MATCH(0,INDEX(COUNTIF($T$2:T24,$L$3:$L$52),0,0),0))," ")} | U25: =IFERROR(IF(AND(VLOOKUP(S25,$J$3:$Q$218,4,0)="KG",VLOOKUP(S25,$J$3:$Q$218,7,0)=0,VLOOKUP(S25,$J$3:$Q$218,8,0)=0),SUM($Q$3:$Q$218),SUMIF($J$3:$J$218,S25,$P$3:$P$218)),"") | W25: =IFERROR(IF(OR(M25="HOJA",M25="HOJA "),((MAX(ROUNDDOWN((0.915/G25),0)*ROUNDDOWN((2.44/H25),0),ROUNDDOWN((0.915/H25),0)*ROUNDDOWN((2.44/G25),0)))*G25*H25)/(0.915*2.44),""),"") | X25: =IFERROR(MAX(ROUNDDOWN((0.915/G25),0)*ROUNDDOWN((2.44/H25),0),ROUNDDOWN((0.915/H25),0)*ROUNDDOWN((2.44/G25),0)),"") | Y25: =IFERROR(IF(OR(M25="HOJA",M25="HOJA "),((MAX(ROUNDDOWN((0.915/G25),0)*ROUNDDOWN((3.05/H25),0),ROUNDDOWN((0.915/H25),0)*ROUNDDOWN((3.05/G25),0)))*G25*H25)/(0.915*3.05),""),"") | Z25: =IFERROR(MAX(ROUNDDOWN((0.915/G25),0)*ROUNDDOWN((3.05/H25),0),ROUNDDOWN((0.915/H25),0)*ROUNDDOWN((3.05/G25),0)),"") | AA25: =IFERROR(IF(OR(M25="HOJA",M25="HOJA "),((MAX(ROUNDDOWN((1.22/G25),0)*ROUNDDOWN((2.44/H25),0),ROUNDDOWN((1.22/H25),0)*ROUNDDOWN((2.44/G25),0)))*G25*H25)/(1.22*2.44),""),"") | AB25: =IFERROR(MAX(ROUNDDOWN((1.22/G25),0)*ROUNDDOWN((2.44/H25),0),ROUNDDOWN((1.22/H25),0)*ROUNDDOWN((2.44/G25),0)),"") | AC25: =IFERROR(IF(OR(M25="HOJA",M25="HOJA "),((MAX(ROUNDDOWN((1.22/G25),0)*ROUNDDOWN((3.05/H25),0),ROUNDDOWN((1.22/H25),0)*ROUNDDOWN((3.05/G25),0)))*G25*H25)/(1.22*3.05),""),"") | AD25: =IFERROR(MAX(ROUNDDOWN((1.22/G25),0)*ROUNDDOWN((3.05/H25),0),ROUNDDOWN((1.22/H25),0)*ROUNDDOWN((3.05/G25),0)),"")
L26: =IFERROR(VLOOKUP(J26,articulo:clave_comercial,2,0)," ") | M26: =UPPER(IFERROR(VLOOKUP(J26,articulo:clave_comercial,5,0)," ")) | N26: =IFERROR(IF(VLOOKUP(J26,articulo:clave_comercial,8,0)=0," ",VLOOKUP(J26,articulo:clave_comercial,8,0))," ") | O26: =IFERROR(IF(VLOOKUP(J26,articulo:clave_comercial,9,0)=0," ",VLOOKUP(J26,articulo:clave_comercial,9,0))," ") | P26: =IFERROR(IF(M26="HOJA",(D26*F26)/MAX(ROUNDDOWN((N26/G26),0)*ROUNDDOWN((O26/H26),0),ROUNDDOWN((N26/H26),0)*ROUNDDOWN((O26/G26),0)),IF(M26="HOJA ",(D26*F26)/MAX(ROUNDDOWN((N26/G26),0)*ROUNDDOWN((O26/H26),0),ROUNDDOWN((N26/H26),0)*ROUNDDOWN((O26/G26),0)),IF(M26="M",G26,IF(AND(M26="PIEZA",G26<>0),(D26*F26)/ROUNDDOWN((N26/G26),0),IF(M26="PIEZA",(D26*F26),IF(M26="CAJA",(D26*F26),IF(M26="DM2",(D26*F26),IF(M26="FT",(D26*F26),IF(M26="JGO",(D26*F26),IF(M26="KG",(D26*F26),IF(M26="LB",(D26*F26),IF(M26="LT",(D26*F26),IF(M26="M2",(D26*F26),IF(M26="M3",(D26*F26),IF(M26="ROLLO",(D26*F26),IF(M26="SQYDS",(D26*F26),IF(M26="UD./SERV.",(D26*F26),IF(M26="YD",(D26*F26)," ")))))))))))))))))),"") | Q26: =IFERROR(IF(M26="HOJA",D26*F26*G26*H26*2*0.125,IF(AND(M26="PIEZA",H26=0),D26*F26*G26*VLOOKUP(J26,articulo:clave_comercial,10,0)*0.125,0))," ") -> 0 | S26: {=IFERROR(INDEX($J$3:$J$52,MATCH(0,INDEX(COUNTIF(S$2:$S25,$J$3:$J$52),0,0),0))," ")} | T26: {=IFERROR(INDEX($L$3:$L$52,MATCH(0,INDEX(COUNTIF($T$2:T25,$L$3:$L$52),0,0),0))," ")} | U26: =IFERROR(IF(AND(VLOOKUP(S26,$J$3:$Q$218,4,0)="KG",VLOOKUP(S26,$J$3:$Q$218,7,0)=0,VLOOKUP(S26,$J$3:$Q$218,8,0)=0),SUM($Q$3:$Q$218),SUMIF($J$3:$J$218,S26,$P$3:$P$218)),"") | W26: =IFERROR(IF(OR(M26="HOJA",M26="HOJA "),((MAX(ROUNDDOWN((0.915/G26),0)*ROUNDDOWN((2.44/H26),0),ROUNDDOWN((0.915/H26),0)*ROUNDDOWN((2.44/G26),0)))*G26*H26)/(0.915*2.44),""),"") | X26: =IFERROR(MAX(ROUNDDOWN((0.915/G26),0)*ROUNDDOWN((2.44/H26),0),ROUNDDOWN((0.915/H26),0)*ROUNDDOWN((2.44/G26),0)),"") | Y26: =IFERROR(IF(OR(M26="HOJA",M26="HOJA "),((MAX(ROUNDDOWN((0.915/G26),0)*ROUNDDOWN((3.05/H26),0),ROUNDDOWN((0.915/H26),0)*ROUNDDOWN((3.05/G26),0)))*G26*H26)/(0.915*3.05),""),"") | Z26: =IFERROR(MAX(ROUNDDOWN((0.915/G26),0)*ROUNDDOWN((3.05/H26),0),ROUNDDOWN((0.915/H26),0)*ROUNDDOWN((3.05/G26),0)),"") | AA26: =IFERROR(IF(OR(M26="HOJA",M26="HOJA "),((MAX(ROUNDDOWN((1.22/G26),0)*ROUNDDOWN((2.44/H26),0),ROUNDDOWN((1.22/H26),0)*ROUNDDOWN((2.44/G26),0)))*G26*H26)/(1.22*2.44),""),"") | AB26: =IFERROR(MAX(ROUNDDOWN((1.22/G26),0)*ROUNDDOWN((2.44/H26),0),ROUNDDOWN((1.22/H26),0)*ROUNDDOWN((2.44/G26),0)),"") | AC26: =IFERROR(IF(OR(M26="HOJA",M26="HOJA "),((MAX(ROUNDDOWN((1.22/G26),0)*ROUNDDOWN((3.05/H26),0),ROUNDDOWN((1.22/H26),0)*ROUNDDOWN((3.05/G26),0)))*G26*H26)/(1.22*3.05),""),"") | AD26: =IFERROR(MAX(ROUNDDOWN((1.22/G26),0)*ROUNDDOWN((3.05/H26),0),ROUNDDOWN((1.22/H26),0)*ROUNDDOWN((3.05/G26),0)),"")
A27: 5 | L27: =IFERROR(VLOOKUP(J27,articulo:clave_comercial,2,0)," ") | M27: =UPPER(IFERROR(VLOOKUP(J27,articulo:clave_comercial,5,0)," ")) | N27: =IFERROR(IF(VLOOKUP(J27,articulo:clave_comercial,8,0)=0," ",VLOOKUP(J27,articulo:clave_comercial,8,0))," ") | O27: =IFERROR(IF(VLOOKUP(J27,articulo:clave_comercial,9,0)=0," ",VLOOKUP(J27,articulo:clave_comercial,9,0))," ") | P27: =IFERROR(IF(M27="HOJA",(D27*F27)/MAX(ROUNDDOWN((N27/G27),0)*ROUNDDOWN((O27/H27),0),ROUNDDOWN((N27/H27),0)*ROUNDDOWN((O27/G27),0)),IF(M27="HOJA ",(D27*F27)/MAX(ROUNDDOWN((N27/G27),0)*ROUNDDOWN((O27/H27),0),ROUNDDOWN((N27/H27),0)*ROUNDDOWN((O27/G27),0)),IF(M27="M",G27,IF(AND(M27="PIEZA",G27<>0),(D27*F27)/ROUNDDOWN((N27/G27),0),IF(M27="PIEZA",(D27*F27),IF(M27="CAJA",(D27*F27),IF(M27="DM2",(D27*F27),IF(M27="FT",(D27*F27),IF(M27="JGO",(D27*F27),IF(M27="KG",(D27*F27),IF(M27="LB",(D27*F27),IF(M27="LT",(D27*F27),IF(M27="M2",(D27*F27),IF(M27="M3",(D27*F27),IF(M27="ROLLO",(D27*F27),IF(M27="SQYDS",(D27*F27),IF(M27="UD./SERV.",(D27*F27),IF(M27="YD",(D27*F27)," ")))))))))))))))))),"") | Q27: =IFERROR(IF(M27="HOJA",D27*F27*G27*H27*2*0.125,IF(AND(M27="PIEZA",H27=0),D27*F27*G27*VLOOKUP(J27,articulo:clave_comercial,10,0)*0.125,0))," ") -> 0 | S27: {=IFERROR(INDEX($J$3:$J$52,MATCH(0,INDEX(COUNTIF(S$2:$S26,$J$3:$J$52),0,0),0))," ")} | T27: {=IFERROR(INDEX($L$3:$L$52,MATCH(0,INDEX(COUNTIF($T$2:T26,$L$3:$L$52),0,0),0))," ")} | U27: =IFERROR(IF(AND(VLOOKUP(S27,$J$3:$Q$218,4,0)="KG",VLOOKUP(S27,$J$3:$Q$218,7,0)=0,VLOOKUP(S27,$J$3:$Q$218,8,0)=0),SUM($Q$3:$Q$218),SUMIF($J$3:$J$218,S27,$P$3:$P$218)),"") | W27: =IFERROR(IF(OR(M27="HOJA",M27="HOJA "),((MAX(ROUNDDOWN((0.915/G27),0)*ROUNDDOWN((2.44/H27),0),ROUNDDOWN((0.915/H27),0)*ROUNDDOWN((2.44/G27),0)))*G27*H27)/(0.915*2.44),""),"") | X27: =IFERROR(MAX(ROUNDDOWN((0.915/G27),0)*ROUNDDOWN((2.44/H27),0),ROUNDDOWN((0.915/H27),0)*ROUNDDOWN((2.44/G27),0)),"") | Y27: =IFERROR(IF(OR(M27="HOJA",M27="HOJA "),((MAX(ROUNDDOWN((0.915/G27),0)*ROUNDDOWN((3.05/H27),0),ROUNDDOWN((0.915/H27),0)*ROUNDDOWN((3.05/G27),0)))*G27*H27)/(0.915*3.05),""),"") | Z27: =IFERROR(MAX(ROUNDDOWN((0.915/G27),0)*ROUNDDOWN((3.05/H27),0),ROUNDDOWN((0.915/H27),0)*ROUNDDOWN((3.05/G27),0)),"") | AA27: =IFERROR(IF(OR(M27="HOJA",M27="HOJA "),((MAX(ROUNDDOWN((1.22/G27),0)*ROUNDDOWN((2.44/H27),0),ROUNDDOWN((1.22/H27),0)*ROUNDDOWN((2.44/G27),0)))*G27*H27)/(1.22*2.44),""),"") | AB27: =IFERROR(MAX(ROUNDDOWN((1.22/G27),0)*ROUNDDOWN((2.44/H27),0),ROUNDDOWN((1.22/H27),0)*ROUNDDOWN((2.44/G27),0)),"") | AC27: =IFERROR(IF(OR(M27="HOJA",M27="HOJA "),((MAX(ROUNDDOWN((1.22/G27),0)*ROUNDDOWN((3.05/H27),0),ROUNDDOWN((1.22/H27),0)*ROUNDDOWN((3.05/G27),0)))*G27*H27)/(1.22*3.05),""),"") | AD27: =IFERROR(MAX(ROUNDDOWN((1.22/G27),0)*ROUNDDOWN((3.05/H27),0),ROUNDDOWN((1.22/H27),0)*ROUNDDOWN((3.05/G27),0)),"")
L28: =IFERROR(VLOOKUP(J28,articulo:clave_comercial,2,0)," ") | M28: =UPPER(IFERROR(VLOOKUP(J28,articulo:clave_comercial,5,0)," ")) | N28: =IFERROR(IF(VLOOKUP(J28,articulo:clave_comercial,8,0)=0," ",VLOOKUP(J28,articulo:clave_comercial,8,0))," ") | O28: =IFERROR(IF(VLOOKUP(J28,articulo:clave_comercial,9,0)=0," ",VLOOKUP(J28,articulo:clave_comercial,9,0))," ") | P28: =IFERROR(IF(M28="HOJA",(D28*F28)/MAX(ROUNDDOWN((N28/G28),0)*ROUNDDOWN((O28/H28),0),ROUNDDOWN((N28/H28),0)*ROUNDDOWN((O28/G28),0)),IF(M28="HOJA ",(D28*F28)/MAX(ROUNDDOWN((N28/G28),0)*ROUNDDOWN((O28/H28),0),ROUNDDOWN((N28/H28),0)*ROUNDDOWN((O28/G28),0)),IF(M28="M",G28,IF(AND(M28="PIEZA",G28<>0),(D28*F28)/ROUNDDOWN((N28/G28),0),IF(M28="PIEZA",(D28*F28),IF(M28="CAJA",(D28*F28),IF(M28="DM2",(D28*F28),IF(M28="FT",(D28*F28),IF(M28="JGO",(D28*F28),IF(M28="KG",(D28*F28),IF(M28="LB",(D28*F28),IF(M28="LT",(D28*F28),IF(M28="M2",(D28*F28),IF(M28="M3",(D28*F28),IF(M28="ROLLO",(D28*F28),IF(M28="SQYDS",(D28*F28),IF(M28="UD./SERV.",(D28*F28),IF(M28="YD",(D28*F28)," ")))))))))))))))))),"") | Q28: =IFERROR(IF(M28="HOJA",D28*F28*G28*H28*2*0.125,IF(AND(M28="PIEZA",H28=0),D28*F28*G28*VLOOKUP(J28,articulo:clave_comercial,10,0)*0.125,0))," ") -> 0 | S28: {=IFERROR(INDEX($J$3:$J$52,MATCH(0,INDEX(COUNTIF(S$2:$S27,$J$3:$J$52),0,0),0))," ")} | T28: {=IFERROR(INDEX($L$3:$L$52,MATCH(0,INDEX(COUNTIF($T$2:T27,$L$3:$L$52),0,0),0))," ")} | U28: =IFERROR(IF(AND(VLOOKUP(S28,$J$3:$Q$218,4,0)="KG",VLOOKUP(S28,$J$3:$Q$218,7,0)=0,VLOOKUP(S28,$J$3:$Q$218,8,0)=0),SUM($Q$3:$Q$218),SUMIF($J$3:$J$218,S28,$P$3:$P$218)),"") | W28: =IFERROR(IF(OR(M28="HOJA",M28="HOJA "),((MAX(ROUNDDOWN((0.915/G28),0)*ROUNDDOWN((2.44/H28),0),ROUNDDOWN((0.915/H28),0)*ROUNDDOWN((2.44/G28),0)))*G28*H28)/(0.915*2.44),""),"") | X28: =IFERROR(MAX(ROUNDDOWN((0.915/G28),0)*ROUNDDOWN((2.44/H28),0),ROUNDDOWN((0.915/H28),0)*ROUNDDOWN((2.44/G28),0)),"") | Y28: =IFERROR(IF(OR(M28="HOJA",M28="HOJA "),((MAX(ROUNDDOWN((0.915/G28),0)*ROUNDDOWN((3.05/H28),0),ROUNDDOWN((0.915/H28),0)*ROUNDDOWN((3.05/G28),0)))*G28*H28)/(0.915*3.05),""),"") | Z28: =IFERROR(MAX(ROUNDDOWN((0.915/G28),0)*ROUNDDOWN((3.05/H28),0),ROUNDDOWN((0.915/H28),0)*ROUNDDOWN((3.05/G28),0)),"") | AA28: =IFERROR(IF(OR(M28="HOJA",M28="HOJA "),((MAX(ROUNDDOWN((1.22/G28),0)*ROUNDDOWN((2.44/H28),0),ROUNDDOWN((1.22/H28),0)*ROUNDDOWN((2.44/G28),0)))*G28*H28)/(1.22*2.44),""),"") | AB28: =IFERROR(MAX(ROUNDDOWN((1.22/G28),0)*ROUNDDOWN((2.44/H28),0),ROUNDDOWN((1.22/H28),0)*ROUNDDOWN((2.44/G28),0)),"") | AC28: =IFERROR(IF(OR(M28="HOJA",M28="HOJA "),((MAX(ROUNDDOWN((1.22/G28),0)*ROUNDDOWN((3.05/H28),0),ROUNDDOWN((1.22/H28),0)*ROUNDDOWN((3.05/G28),0)))*G28*H28)/(1.22*3.05),""),"") | AD28: =IFERROR(MAX(ROUNDDOWN((1.22/G28),0)*ROUNDDOWN((3.05/H28),0),ROUNDDOWN((1.22/H28),0)*ROUNDDOWN((3.05/G28),0)),"")
L29: =IFERROR(VLOOKUP(J29,articulo:clave_comercial,2,0)," ") | M29: =UPPER(IFERROR(VLOOKUP(J29,articulo:clave_comercial,5,0)," ")) | N29: =IFERROR(IF(VLOOKUP(J29,articulo:clave_comercial,8,0)=0," ",VLOOKUP(J29,articulo:clave_comercial,8,0))," ") | O29: =IFERROR(IF(VLOOKUP(J29,articulo:clave_comercial,9,0)=0," ",VLOOKUP(J29,articulo:clave_comercial,9,0))," ") | P29: =IFERROR(IF(M29="HOJA",(D29*F29)/MAX(ROUNDDOWN((N29/G29),0)*ROUNDDOWN((O29/H29),0),ROUNDDOWN((N29/H29),0)*ROUNDDOWN((O29/G29),0)),IF(M29="HOJA ",(D29*F29)/MAX(ROUNDDOWN((N29/G29),0)*ROUNDDOWN((O29/H29),0),ROUNDDOWN((N29/H29),0)*ROUNDDOWN((O29/G29),0)),IF(M29="M",G29,IF(AND(M29="PIEZA",G29<>0),(D29*F29)/ROUNDDOWN((N29/G29),0),IF(M29="PIEZA",(D29*F29),IF(M29="CAJA",(D29*F29),IF(M29="DM2",(D29*F29),IF(M29="FT",(D29*F29),IF(M29="JGO",(D29*F29),IF(M29="KG",(D29*F29),IF(M29="LB",(D29*F29),IF(M29="LT",(D29*F29),IF(M29="M2",(D29*F29),IF(M29="M3",(D29*F29),IF(M29="ROLLO",(D29*F29),IF(M29="SQYDS",(D29*F29),IF(M29="UD./SERV.",(D29*F29),IF(M29="YD",(D29*F29)," ")))))))))))))))))),"") | Q29: =IFERROR(IF(M29="HOJA",D29*F29*G29*H29*2*0.125,IF(AND(M29="PIEZA",H29=0),D29*F29*G29*VLOOKUP(J29,articulo:clave_comercial,10,0)*0.125,0))," ") -> 0 | S29: {=IFERROR(INDEX($J$3:$J$52,MATCH(0,INDEX(COUNTIF(S$2:$S28,$J$3:$J$52),0,0),0))," ")} | T29: {=IFERROR(INDEX($L$3:$L$52,MATCH(0,INDEX(COUNTIF($T$2:T28,$L$3:$L$52),0,0),0))," ")} | U29: =IFERROR(IF(AND(VLOOKUP(S29,$J$3:$Q$218,4,0)="KG",VLOOKUP(S29,$J$3:$Q$218,7,0)=0,VLOOKUP(S29,$J$3:$Q$218,8,0)=0),SUM($Q$3:$Q$218),SUMIF($J$3:$J$218,S29,$P$3:$P$218)),"") | W29: =IFERROR(IF(OR(M29="HOJA",M29="HOJA "),((MAX(ROUNDDOWN((0.915/G29),0)*ROUNDDOWN((2.44/H29),0),ROUNDDOWN((0.915/H29),0)*ROUNDDOWN((2.44/G29),0)))*G29*H29)/(0.915*2.44),""),"") | X29: =IFERROR(MAX(ROUNDDOWN((0.915/G29),0)*ROUNDDOWN((2.44/H29),0),ROUNDDOWN((0.915/H29),0)*ROUNDDOWN((2.44/G29),0)),"") | Y29: =IFERROR(IF(OR(M29="HOJA",M29="HOJA "),((MAX(ROUNDDOWN((0.915/G29),0)*ROUNDDOWN((3.05/H29),0),ROUNDDOWN((0.915/H29),0)*ROUNDDOWN((3.05/G29),0)))*G29*H29)/(0.915*3.05),""),"") | Z29: =IFERROR(MAX(ROUNDDOWN((0.915/G29),0)*ROUNDDOWN((3.05/H29),0),ROUNDDOWN((0.915/H29),0)*ROUNDDOWN((3.05/G29),0)),"") | AA29: =IFERROR(IF(OR(M29="HOJA",M29="HOJA "),((MAX(ROUNDDOWN((1.22/G29),0)*ROUNDDOWN((2.44/H29),0),ROUNDDOWN((1.22/H29),0)*ROUNDDOWN((2.44/G29),0)))*G29*H29)/(1.22*2.44),""),"") | AB29: =IFERROR(MAX(ROUNDDOWN((1.22/G29),0)*ROUNDDOWN((2.44/H29),0),ROUNDDOWN((1.22/H29),0)*ROUNDDOWN((2.44/G29),0)),"") | AC29: =IFERROR(IF(OR(M29="HOJA",M29="HOJA "),((MAX(ROUNDDOWN((1.22/G29),0)*ROUNDDOWN((3.05/H29),0),ROUNDDOWN((1.22/H29),0)*ROUNDDOWN((3.05/G29),0)))*G29*H29)/(1.22*3.05),""),"") | AD29: =IFERROR(MAX(ROUNDDOWN((1.22/G29),0)*ROUNDDOWN((3.05/H29),0),ROUNDDOWN((1.22/H29),0)*ROUNDDOWN((3.05/G29),0)),"")
L30: =IFERROR(VLOOKUP(J30,articulo:clave_comercial,2,0)," ") | M30: =UPPER(IFERROR(VLOOKUP(J30,articulo:clave_comercial,5,0)," ")) | N30: =IFERROR(IF(VLOOKUP(J30,articulo:clave_comercial,8,0)=0," ",VLOOKUP(J30,articulo:clave_comercial,8,0))," ") | O30: =IFERROR(IF(VLOOKUP(J30,articulo:clave_comercial,9,0)=0," ",VLOOKUP(J30,articulo:clave_comercial,9,0))," ") | P30: =IFERROR(IF(M30="HOJA",(D30*F30)/MAX(ROUNDDOWN((N30/G30),0)*ROUNDDOWN((O30/H30),0),ROUNDDOWN((N30/H30),0)*ROUNDDOWN((O30/G30),0)),IF(M30="HOJA ",(D30*F30)/MAX(ROUNDDOWN((N30/G30),0)*ROUNDDOWN((O30/H30),0),ROUNDDOWN((N30/H30),0)*ROUNDDOWN((O30/G30),0)),IF(M30="M",G30,IF(AND(M30="PIEZA",G30<>0),(D30*F30)/ROUNDDOWN((N30/G30),0),IF(M30="PIEZA",(D30*F30),IF(M30="CAJA",(D30*F30),IF(M30="DM2",(D30*F30),IF(M30="FT",(D30*F30),IF(M30="JGO",(D30*F30),IF(M30="KG",(D30*F30),IF(M30="LB",(D30*F30),IF(M30="LT",(D30*F30),IF(M30="M2",(D30*F30),IF(M30="M3",(D30*F30),IF(M30="ROLLO",(D30*F30),IF(M30="SQYDS",(D30*F30),IF(M30="UD./SERV.",(D30*F30),IF(M30="YD",(D30*F30)," ")))))))))))))))))),"") | Q30: =IFERROR(IF(M30="HOJA",D30*F30*G30*H30*2*0.125,IF(AND(M30="PIEZA",H30=0),D30*F30*G30*VLOOKUP(J30,articulo:clave_comercial,10,0)*0.125,0))," ") -> 0 | S30: {=IFERROR(INDEX($J$3:$J$52,MATCH(0,INDEX(COUNTIF(S$2:$S29,$J$3:$J$52),0,0),0))," ")} | T30: {=IFERROR(INDEX($L$3:$L$52,MATCH(0,INDEX(COUNTIF($T$2:T29,$L$3:$L$52),0,0),0))," ")} | U30: =IFERROR(IF(AND(VLOOKUP(S30,$J$3:$Q$218,4,0)="KG",VLOOKUP(S30,$J$3:$Q$218,7,0)=0,VLOOKUP(S30,$J$3:$Q$218,8,0)=0),SUM($Q$3:$Q$218),SUMIF($J$3:$J$218,S30,$P$3:$P$218)),"") | W30: =IFERROR(IF(OR(M30="HOJA",M30="HOJA "),((MAX(ROUNDDOWN((0.915/G30),0)*ROUNDDOWN((2.44/H30),0),ROUNDDOWN((0.915/H30),0)*ROUNDDOWN((2.44/G30),0)))*G30*H30)/(0.915*2.44),""),"") | X30: =IFERROR(MAX(ROUNDDOWN((0.915/G30),0)*ROUNDDOWN((2.44/H30),0),ROUNDDOWN((0.915/H30),0)*ROUNDDOWN((2.44/G30),0)),"") | Y30: =IFERROR(IF(OR(M30="HOJA",M30="HOJA "),((MAX(ROUNDDOWN((0.915/G30),0)*ROUNDDOWN((3.05/H30),0),ROUNDDOWN((0.915/H30),0)*ROUNDDOWN((3.05/G30),0)))*G30*H30)/(0.915*3.05),""),"") | Z30: =IFERROR(MAX(ROUNDDOWN((0.915/G30),0)*ROUNDDOWN((3.05/H30),0),ROUNDDOWN((0.915/H30),0)*ROUNDDOWN((3.05/G30),0)),"") | AA30: =IFERROR(IF(OR(M30="HOJA",M30="HOJA "),((MAX(ROUNDDOWN((1.22/G30),0)*ROUNDDOWN((2.44/H30),0),ROUNDDOWN((1.22/H30),0)*ROUNDDOWN((2.44/G30),0)))*G30*H30)/(1.22*2.44),""),"") | AB30: =IFERROR(MAX(ROUNDDOWN((1.22/G30),0)*ROUNDDOWN((2.44/H30),0),ROUNDDOWN((1.22/H30),0)*ROUNDDOWN((2.44/G30),0)),"") | AC30: =IFERROR(IF(OR(M30="HOJA",M30="HOJA "),((MAX(ROUNDDOWN((1.22/G30),0)*ROUNDDOWN((3.05/H30),0),ROUNDDOWN((1.22/H30),0)*ROUNDDOWN((3.05/G30),0)))*G30*H30)/(1.22*3.05),""),"") | AD30: =IFERROR(MAX(ROUNDDOWN((1.22/G30),0)*ROUNDDOWN((3.05/H30),0),ROUNDDOWN((1.22/H30),0)*ROUNDDOWN((3.05/G30),0)),"")
L31: =IFERROR(VLOOKUP(J31,articulo:clave_comercial,2,0)," ") | M31: =UPPER(IFERROR(VLOOKUP(J31,articulo:clave_comercial,5,0)," ")) | N31: =IFERROR(IF(VLOOKUP(J31,articulo:clave_comercial,8,0)=0," ",VLOOKUP(J31,articulo:clave_comercial,8,0))," ") | O31: =IFERROR(IF(VLOOKUP(J31,articulo:clave_comercial,9,0)=0," ",VLOOKUP(J31,articulo:clave_comercial,9,0))," ") | P31: =IFERROR(IF(M31="HOJA",(D31*F31)/MAX(ROUNDDOWN((N31/G31),0)*ROUNDDOWN((O31/H31),0),ROUNDDOWN((N31/H31),0)*ROUNDDOWN((O31/G31),0)),IF(M31="HOJA ",(D31*F31)/MAX(ROUNDDOWN((N31/G31),0)*ROUNDDOWN((O31/H31),0),ROUNDDOWN((N31/H31),0)*ROUNDDOWN((O31/G31),0)),IF(M31="M",G31,IF(AND(M31="PIEZA",G31<>0),(D31*F31)/ROUNDDOWN((N31/G31),0),IF(M31="PIEZA",(D31*F31),IF(M31="CAJA",(D31*F31),IF(M31="DM2",(D31*F31),IF(M31="FT",(D31*F31),IF(M31="JGO",(D31*F31),IF(M31="KG",(D31*F31),IF(M31="LB",(D31*F31),IF(M31="LT",(D31*F31),IF(M31="M2",(D31*F31),IF(M31="M3",(D31*F31),IF(M31="ROLLO",(D31*F31),IF(M31="SQYDS",(D31*F31),IF(M31="UD./SERV.",(D31*F31),IF(M31="YD",(D31*F31)," ")))))))))))))))))),"") | Q31: =IFERROR(IF(M31="HOJA",D31*F31*G31*H31*2*0.125,IF(AND(M31="PIEZA",H31=0),D31*F31*G31*VLOOKUP(J31,articulo:clave_comercial,10,0)*0.125,0))," ") -> 0 | S31: {=IFERROR(INDEX($J$3:$J$52,MATCH(0,INDEX(COUNTIF(S$2:$S30,$J$3:$J$52),0,0),0))," ")} | T31: {=IFERROR(INDEX($L$3:$L$52,MATCH(0,INDEX(COUNTIF($T$2:T30,$L$3:$L$52),0,0),0))," ")} | U31: =IFERROR(IF(AND(VLOOKUP(S31,$J$3:$Q$218,4,0)="KG",VLOOKUP(S31,$J$3:$Q$218,7,0)=0,VLOOKUP(S31,$J$3:$Q$218,8,0)=0),SUM($Q$3:$Q$218),SUMIF($J$3:$J$218,S31,$P$3:$P$218)),"") | W31: =IFERROR(IF(OR(M31="HOJA",M31="HOJA "),((MAX(ROUNDDOWN((0.915/G31),0)*ROUNDDOWN((2.44/H31),0),ROUNDDOWN((0.915/H31),0)*ROUNDDOWN((2.44/G31),0)))*G31*H31)/(0.915*2.44),""),"") | X31: =IFERROR(MAX(ROUNDDOWN((0.915/G31),0)*ROUNDDOWN((2.44/H31),0),ROUNDDOWN((0.915/H31),0)*ROUNDDOWN((2.44/G31),0)),"") | Y31: =IFERROR(IF(OR(M31="HOJA",M31="HOJA "),((MAX(ROUNDDOWN((0.915/G31),0)*ROUNDDOWN((3.05/H31),0),ROUNDDOWN((0.915/H31),0)*ROUNDDOWN((3.05/G31),0)))*G31*H31)/(0.915*3.05),""),"") | Z31: =IFERROR(MAX(ROUNDDOWN((0.915/G31),0)*ROUNDDOWN((3.05/H31),0),ROUNDDOWN((0.915/H31),0)*ROUNDDOWN((3.05/G31),0)),"") | AA31: =IFERROR(IF(OR(M31="HOJA",M31="HOJA "),((MAX(ROUNDDOWN((1.22/G31),0)*ROUNDDOWN((2.44/H31),0),ROUNDDOWN((1.22/H31),0)*ROUNDDOWN((2.44/G31),0)))*G31*H31)/(1.22*2.44),""),"") | AB31: =IFERROR(MAX(ROUNDDOWN((1.22/G31),0)*ROUNDDOWN((2.44/H31),0),ROUNDDOWN((1.22/H31),0)*ROUNDDOWN((2.44/G31),0)),"") | AC31: =IFERROR(IF(OR(M31="HOJA",M31="HOJA "),((MAX(ROUNDDOWN((1.22/G31),0)*ROUNDDOWN((3.05/H31),0),ROUNDDOWN((1.22/H31),0)*ROUNDDOWN((3.05/G31),0)))*G31*H31)/(1.22*3.05),""),"") | AD31: =IFERROR(MAX(ROUNDDOWN((1.22/G31),0)*ROUNDDOWN((3.05/H31),0),ROUNDDOWN((1.22/H31),0)*ROUNDDOWN((3.05/G31),0)),"")
L32: =IFERROR(VLOOKUP(J32,articulo:clave_comercial,2,0)," ") | M32: =UPPER(IFERROR(VLOOKUP(J32,articulo:clave_comercial,5,0)," ")) | N32: =IFERROR(IF(VLOOKUP(J32,articulo:clave_comercial,8,0)=0," ",VLOOKUP(J32,articulo:clave_comercial,8,0))," ") | O32: =IFERROR(IF(VLOOKUP(J32,articulo:clave_comercial,9,0)=0," ",VLOOKUP(J32,articulo:clave_comercial,9,0))," ") | P32: =IFERROR(IF(M32="HOJA",(D32*F32)/MAX(ROUNDDOWN((N32/G32),0)*ROUNDDOWN((O32/H32),0),ROUNDDOWN((N32/H32),0)*ROUNDDOWN((O32/G32),0)),IF(M32="HOJA ",(D32*F32)/MAX(ROUNDDOWN((N32/G32),0)*ROUNDDOWN((O32/H32),0),ROUNDDOWN((N32/H32),0)*ROUNDDOWN((O32/G32),0)),IF(M32="M",G32,IF(AND(M32="PIEZA",G32<>0),(D32*F32)/ROUNDDOWN((N32/G32),0),IF(M32="PIEZA",(D32*F32),IF(M32="CAJA",(D32*F32),IF(M32="DM2",(D32*F32),IF(M32="FT",(D32*F32),IF(M32="JGO",(D32*F32),IF(M32="KG",(D32*F32),IF(M32="LB",(D32*F32),IF(M32="LT",(D32*F32),IF(M32="M2",(D32*F32),IF(M32="M3",(D32*F32),IF(M32="ROLLO",(D32*F32),IF(M32="SQYDS",(D32*F32),IF(M32="UD./SERV.",(D32*F32),IF(M32="YD",(D32*F32)," ")))))))))))))))))),"") | Q32: =IFERROR(IF(M32="HOJA",D32*F32*G32*H32*2*0.125,IF(AND(M32="PIEZA",H32=0),D32*F32*G32*VLOOKUP(J32,articulo:clave_comercial,10,0)*0.125,0))," ") -> 0 | S32: {=IFERROR(INDEX($J$3:$J$52,MATCH(0,INDEX(COUNTIF(S$2:$S31,$J$3:$J$52),0,0),0))," ")} | T32: {=IFERROR(INDEX($L$3:$L$52,MATCH(0,INDEX(COUNTIF($T$2:T31,$L$3:$L$52),0,0),0))," ")} | U32: =IFERROR(IF(AND(VLOOKUP(S32,$J$3:$Q$218,4,0)="KG",VLOOKUP(S32,$J$3:$Q$218,7,0)=0,VLOOKUP(S32,$J$3:$Q$218,8,0)=0),SUM($Q$3:$Q$218),SUMIF($J$3:$J$218,S32,$P$3:$P$218)),"") | W32: =IFERROR(IF(OR(M32="HOJA",M32="HOJA "),((MAX(ROUNDDOWN((0.915/G32),0)*ROUNDDOWN((2.44/H32),0),ROUNDDOWN((0.915/H32),0)*ROUNDDOWN((2.44/G32),0)))*G32*H32)/(0.915*2.44),""),"") | X32: =IFERROR(MAX(ROUNDDOWN((0.915/G32),0)*ROUNDDOWN((2.44/H32),0),ROUNDDOWN((0.915/H32),0)*ROUNDDOWN((2.44/G32),0)),"") | Y32: =IFERROR(IF(OR(M32="HOJA",M32="HOJA "),((MAX(ROUNDDOWN((0.915/G32),0)*ROUNDDOWN((3.05/H32),0),ROUNDDOWN((0.915/H32),0)*ROUNDDOWN((3.05/G32),0)))*G32*H32)/(0.915*3.05),""),"") | Z32: =IFERROR(MAX(ROUNDDOWN((0.915/G32),0)*ROUNDDOWN((3.05/H32),0),ROUNDDOWN((0.915/H32),0)*ROUNDDOWN((3.05/G32),0)),"") | AA32: =IFERROR(IF(OR(M32="HOJA",M32="HOJA "),((MAX(ROUNDDOWN((1.22/G32),0)*ROUNDDOWN((2.44/H32),0),ROUNDDOWN((1.22/H32),0)*ROUNDDOWN((2.44/G32),0)))*G32*H32)/(1.22*2.44),""),"") | AB32: =IFERROR(MAX(ROUNDDOWN((1.22/G32),0)*ROUNDDOWN((2.44/H32),0),ROUNDDOWN((1.22/H32),0)*ROUNDDOWN((2.44/G32),0)),"") | AC32: =IFERROR(IF(OR(M32="HOJA",M32="HOJA "),((MAX(ROUNDDOWN((1.22/G32),0)*ROUNDDOWN((3.05/H32),0),ROUNDDOWN((1.22/H32),0)*ROUNDDOWN((3.05/G32),0)))*G32*H32)/(1.22*3.05),""),"") | AD32: =IFERROR(MAX(ROUNDDOWN((1.22/G32),0)*ROUNDDOWN((3.05/H32),0),ROUNDDOWN((1.22/H32),0)*ROUNDDOWN((3.05/G32),0)),"")
L33: =IFERROR(VLOOKUP(J33,articulo:clave_comercial,2,0)," ") | M33: =UPPER(IFERROR(VLOOKUP(J33,articulo:clave_comercial,5,0)," ")) | N33: =IFERROR(IF(VLOOKUP(J33,articulo:clave_comercial,8,0)=0," ",VLOOKUP(J33,articulo:clave_comercial,8,0))," ") | O33: =IFERROR(IF(VLOOKUP(J33,articulo:clave_comercial,9,0)=0," ",VLOOKUP(J33,articulo:clave_comercial,9,0))," ") | P33: =IFERROR(IF(M33="HOJA",(D33*F33)/MAX(ROUNDDOWN((N33/G33),0)*ROUNDDOWN((O33/H33),0),ROUNDDOWN((N33/H33),0)*ROUNDDOWN((O33/G33),0)),IF(M33="HOJA ",(D33*F33)/MAX(ROUNDDOWN((N33/G33),0)*ROUNDDOWN((O33/H33),0),ROUNDDOWN((N33/H33),0)*ROUNDDOWN((O33/G33),0)),IF(M33="M",G33,IF(AND(M33="PIEZA",G33<>0),(D33*F33)/ROUNDDOWN((N33/G33),0),IF(M33="PIEZA",(D33*F33),IF(M33="CAJA",(D33*F33),IF(M33="DM2",(D33*F33),IF(M33="FT",(D33*F33),IF(M33="JGO",(D33*F33),IF(M33="KG",(D33*F33),IF(M33="LB",(D33*F33),IF(M33="LT",(D33*F33),IF(M33="M2",(D33*F33),IF(M33="M3",(D33*F33),IF(M33="ROLLO",(D33*F33),IF(M33="SQYDS",(D33*F33),IF(M33="UD./SERV.",(D33*F33),IF(M33="YD",(D33*F33)," ")))))))))))))))))),"") | Q33: =IFERROR(IF(M33="HOJA",D33*F33*G33*H33*2*0.125,IF(AND(M33="PIEZA",H33=0),D33*F33*G33*VLOOKUP(J33,articulo:clave_comercial,10,0)*0.125,0))," ") -> 0 | S33: {=IFERROR(INDEX($J$3:$J$52,MATCH(0,INDEX(COUNTIF(S$2:$S32,$J$3:$J$52),0,0),0))," ")} | T33: {=IFERROR(INDEX($L$3:$L$52,MATCH(0,INDEX(COUNTIF($T$2:T32,$L$3:$L$52),0,0),0))," ")} | U33: =IFERROR(IF(AND(VLOOKUP(S33,$J$3:$Q$218,4,0)="KG",VLOOKUP(S33,$J$3:$Q$218,7,0)=0,VLOOKUP(S33,$J$3:$Q$218,8,0)=0),SUM($Q$3:$Q$218),SUMIF($J$3:$J$218,S33,$P$3:$P$218)),"") | W33: =IFERROR(IF(OR(M33="HOJA",M33="HOJA "),((MAX(ROUNDDOWN((0.915/G33),0)*ROUNDDOWN((2.44/H33),0),ROUNDDOWN((0.915/H33),0)*ROUNDDOWN((2.44/G33),0)))*G33*H33)/(0.915*2.44),""),"") | X33: =IFERROR(MAX(ROUNDDOWN((0.915/G33),0)*ROUNDDOWN((2.44/H33),0),ROUNDDOWN((0.915/H33),0)*ROUNDDOWN((2.44/G33),0)),"") | Y33: =IFERROR(IF(OR(M33="HOJA",M33="HOJA "),((MAX(ROUNDDOWN((0.915/G33),0)*ROUNDDOWN((3.05/H33),0),ROUNDDOWN((0.915/H33),0)*ROUNDDOWN((3.05/G33),0)))*G33*H33)/(0.915*3.05),""),"") | Z33: =IFERROR(MAX(ROUNDDOWN((0.915/G33),0)*ROUNDDOWN((3.05/H33),0),ROUNDDOWN((0.915/H33),0)*ROUNDDOWN((3.05/G33),0)),"") | AA33: =IFERROR(IF(OR(M33="HOJA",M33="HOJA "),((MAX(ROUNDDOWN((1.22/G33),0)*ROUNDDOWN((2.44/H33),0),ROUNDDOWN((1.22/H33),0)*ROUNDDOWN((2.44/G33),0)))*G33*H33)/(1.22*2.44),""),"") | AB33: =IFERROR(MAX(ROUNDDOWN((1.22/G33),0)*ROUNDDOWN((2.44/H33),0),ROUNDDOWN((1.22/H33),0)*ROUNDDOWN((2.44/G33),0)),"") | AC33: =IFERROR(IF(OR(M33="HOJA",M33="HOJA "),((MAX(ROUNDDOWN((1.22/G33),0)*ROUNDDOWN((3.05/H33),0),ROUNDDOWN((1.22/H33),0)*ROUNDDOWN((3.05/G33),0)))*G33*H33)/(1.22*3.05),""),"") | AD33: =IFERROR(MAX(ROUNDDOWN((1.22/G33),0)*ROUNDDOWN((3.05/H33),0),ROUNDDOWN((1.22/H33),0)*ROUNDDOWN((3.05/G33),0)),"")
L34: =IFERROR(VLOOKUP(J34,articulo:clave_comercial,2,0)," ") | M34: =UPPER(IFERROR(VLOOKUP(J34,articulo:clave_comercial,5,0)," ")) | N34: =IFERROR(IF(VLOOKUP(J34,articulo:clave_comercial,8,0)=0," ",VLOOKUP(J34,articulo:clave_comercial,8,0))," ") | O34: =IFERROR(IF(VLOOKUP(J34,articulo:clave_comercial,9,0)=0," ",VLOOKUP(J34,articulo:clave_comercial,9,0))," ") | P34: =IFERROR(IF(M34="HOJA",(D34*F34)/MAX(ROUNDDOWN((N34/G34),0)*ROUNDDOWN((O34/H34),0),ROUNDDOWN((N34/H34),0)*ROUNDDOWN((O34/G34),0)),IF(M34="HOJA ",(D34*F34)/MAX(ROUNDDOWN((N34/G34),0)*ROUNDDOWN((O34/H34),0),ROUNDDOWN((N34/H34),0)*ROUNDDOWN((O34/G34),0)),IF(M34="M",G34,IF(AND(M34="PIEZA",G34<>0),(D34*F34)/ROUNDDOWN((N34/G34),0),IF(M34="PIEZA",(D34*F34),IF(M34="CAJA",(D34*F34),IF(M34="DM2",(D34*F34),IF(M34="FT",(D34*F34),IF(M34="JGO",(D34*F34),IF(M34="KG",(D34*F34),IF(M34="LB",(D34*F34),IF(M34="LT",(D34*F34),IF(M34="M2",(D34*F34),IF(M34="M3",(D34*F34),IF(M34="ROLLO",(D34*F34),IF(M34="SQYDS",(D34*F34),IF(M34="UD./SERV.",(D34*F34),IF(M34="YD",(D34*F34)," ")))))))))))))))))),"") | Q34: =IFERROR(IF(M34="HOJA",D34*F34*G34*H34*2*0.125,IF(AND(M34="PIEZA",H34=0),D34*F34*G34*VLOOKUP(J34,articulo:clave_comercial,10,0)*0.125,0))," ") -> 0 | S34: {=IFERROR(INDEX($J$3:$J$52,MATCH(0,INDEX(COUNTIF(S$2:$S33,$J$3:$J$52),0,0),0))," ")} | T34: {=IFERROR(INDEX($L$3:$L$52,MATCH(0,INDEX(COUNTIF($T$2:T33,$L$3:$L$52),0,0),0))," ")} | U34: =IFERROR(IF(AND(VLOOKUP(S34,$J$3:$Q$218,4,0)="KG",VLOOKUP(S34,$J$3:$Q$218,7,0)=0,VLOOKUP(S34,$J$3:$Q$218,8,0)=0),SUM($Q$3:$Q$218),SUMIF($J$3:$J$218,S34,$P$3:$P$218)),"") | W34: =IFERROR(IF(OR(M34="HOJA",M34="HOJA "),((MAX(ROUNDDOWN((0.915/G34),0)*ROUNDDOWN((2.44/H34),0),ROUNDDOWN((0.915/H34),0)*ROUNDDOWN((2.44/G34),0)))*G34*H34)/(0.915*2.44),""),"") | X34: =IFERROR(MAX(ROUNDDOWN((0.915/G34),0)*ROUNDDOWN((2.44/H34),0),ROUNDDOWN((0.915/H34),0)*ROUNDDOWN((2.44/G34),0)),"") | Y34: =IFERROR(IF(OR(M34="HOJA",M34="HOJA "),((MAX(ROUNDDOWN((0.915/G34),0)*ROUNDDOWN((3.05/H34),0),ROUNDDOWN((0.915/H34),0)*ROUNDDOWN((3.05/G34),0)))*G34*H34)/(0.915*3.05),""),"") | Z34: =IFERROR(MAX(ROUNDDOWN((0.915/G34),0)*ROUNDDOWN((3.05/H34),0),ROUNDDOWN((0.915/H34),0)*ROUNDDOWN((3.05/G34),0)),"") | AA34: =IFERROR(IF(OR(M34="HOJA",M34="HOJA "),((MAX(ROUNDDOWN((1.22/G34),0)*ROUNDDOWN((2.44/H34),0),ROUNDDOWN((1.22/H34),0)*ROUNDDOWN((2.44/G34),0)))*G34*H34)/(1.22*2.44),""),"") | AB34: =IFERROR(MAX(ROUNDDOWN((1.22/G34),0)*ROUNDDOWN((2.44/H34),0),ROUNDDOWN((1.22/H34),0)*ROUNDDOWN((2.44/G34),0)),"") | AC34: =IFERROR(IF(OR(M34="HOJA",M34="HOJA "),((MAX(ROUNDDOWN((1.22/G34),0)*ROUNDDOWN((3.05/H34),0),ROUNDDOWN((1.22/H34),0)*ROUNDDOWN((3.05/G34),0)))*G34*H34)/(1.22*3.05),""),"") | AD34: =IFERROR(MAX(ROUNDDOWN((1.22/G34),0)*ROUNDDOWN((3.05/H34),0),ROUNDDOWN((1.22/H34),0)*ROUNDDOWN((3.05/G34),0)),"")
A35: 6 | L35: =IFERROR(VLOOKUP(J35,articulo:clave_comercial,2,0)," ") | M35: =UPPER(IFERROR(VLOOKUP(J35,articulo:clave_comercial,5,0)," ")) | N35: =IFERROR(IF(VLOOKUP(J35,articulo:clave_comercial,8,0)=0," ",VLOOKUP(J35,articulo:clave_comercial,8,0))," ") | O35: =IFERROR(IF(VLOOKUP(J35,articulo:clave_comercial,9,0)=0," ",VLOOKUP(J35,articulo:clave_comercial,9,0))," ") | P35: =IFERROR(IF(M35="HOJA",(D35*F35)/MAX(ROUNDDOWN((N35/G35),0)*ROUNDDOWN((O35/H35),0),ROUNDDOWN((N35/H35),0)*ROUNDDOWN((O35/G35),0)),IF(M35="HOJA ",(D35*F35)/MAX(ROUNDDOWN((N35/G35),0)*ROUNDDOWN((O35/H35),0),ROUNDDOWN((N35/H35),0)*ROUNDDOWN((O35/G35),0)),IF(M35="M",G35,IF(AND(M35="PIEZA",G35<>0),(D35*F35)/ROUNDDOWN((N35/G35),0),IF(M35="PIEZA",(D35*F35),IF(M35="CAJA",(D35*F35),IF(M35="DM2",(D35*F35),IF(M35="FT",(D35*F35),IF(M35="JGO",(D35*F35),IF(M35="KG",(D35*F35),IF(M35="LB",(D35*F35),IF(M35="LT",(D35*F35),IF(M35="M2",(D35*F35),IF(M35="M3",(D35*F35),IF(M35="ROLLO",(D35*F35),IF(M35="SQYDS",(D35*F35),IF(M35="UD./SERV.",(D35*F35),IF(M35="YD",(D35*F35)," ")))))))))))))))))),"") | Q35: =IFERROR(IF(M35="HOJA",D35*F35*G35*H35*2*0.125,IF(AND(M35="PIEZA",H35=0),D35*F35*G35*VLOOKUP(J35,articulo:clave_comercial,10,0)*0.125,0))," ") -> 0 | S35: {=IFERROR(INDEX($J$3:$J$52,MATCH(0,INDEX(COUNTIF(S$2:$S34,$J$3:$J$52),0,0),0))," ")} | T35: {=IFERROR(INDEX($L$3:$L$52,MATCH(0,INDEX(COUNTIF($T$2:T34,$L$3:$L$52),0,0),0))," ")} | U35: =IFERROR(IF(AND(VLOOKUP(S35,$J$3:$Q$218,4,0)="KG",VLOOKUP(S35,$J$3:$Q$218,7,0)=0,VLOOKUP(S35,$J$3:$Q$218,8,0)=0),SUM($Q$3:$Q$218),SUMIF($J$3:$J$218,S35,$P$3:$P$218)),"") | W35: =IFERROR(IF(OR(M35="HOJA",M35="HOJA "),((MAX(ROUNDDOWN((0.915/G35),0)*ROUNDDOWN((2.44/H35),0),ROUNDDOWN((0.915/H35),0)*ROUNDDOWN((2.44/G35),0)))*G35*H35)/(0.915*2.44),""),"") | X35: =IFERROR(MAX(ROUNDDOWN((0.915/G35),0)*ROUNDDOWN((2.44/H35),0),ROUNDDOWN((0.915/H35),0)*ROUNDDOWN((2.44/G35),0)),"") | Y35: =IFERROR(IF(OR(M35="HOJA",M35="HOJA "),((MAX(ROUNDDOWN((0.915/G35),0)*ROUNDDOWN((3.05/H35),0),ROUNDDOWN((0.915/H35),0)*ROUNDDOWN((3.05/G35),0)))*G35*H35)/(0.915*3.05),""),"") | Z35: =IFERROR(MAX(ROUNDDOWN((0.915/G35),0)*ROUNDDOWN((3.05/H35),0),ROUNDDOWN((0.915/H35),0)*ROUNDDOWN((3.05/G35),0)),"") | AA35: =IFERROR(IF(OR(M35="HOJA",M35="HOJA "),((MAX(ROUNDDOWN((1.22/G35),0)*ROUNDDOWN((2.44/H35),0),ROUNDDOWN((1.22/H35),0)*ROUNDDOWN((2.44/G35),0)))*G35*H35)/(1.22*2.44),""),"") | AB35: =IFERROR(MAX(ROUNDDOWN((1.22/G35),0)*ROUNDDOWN((2.44/H35),0),ROUNDDOWN((1.22/H35),0)*ROUNDDOWN((2.44/G35),0)),"") | AC35: =IFERROR(IF(OR(M35="HOJA",M35="HOJA "),((MAX(ROUNDDOWN((1.22/G35),0)*ROUNDDOWN((3.05/H35),0),ROUNDDOWN((1.22/H35),0)*ROUNDDOWN((3.05/G35),0)))*G35*H35)/(1.22*3.05),""),"") | AD35: =IFERROR(MAX(ROUNDDOWN((1.22/G35),0)*ROUNDDOWN((3.05/H35),0),ROUNDDOWN((1.22/H35),0)*ROUNDDOWN((3.05/G35),0)),"")
L36: =IFERROR(VLOOKUP(J36,articulo:clave_comercial,2,0)," ") | M36: =UPPER(IFERROR(VLOOKUP(J36,articulo:clave_comercial,5,0)," ")) | N36: =IFERROR(IF(VLOOKUP(J36,articulo:clave_comercial,8,0)=0," ",VLOOKUP(J36,articulo:clave_comercial,8,0))," ") | O36: =IFERROR(IF(VLOOKUP(J36,articulo:clave_comercial,9,0)=0," ",VLOOKUP(J36,articulo:clave_comercial,9,0))," ") | P36: =IFERROR(IF(M36="HOJA",(D36*F36)/MAX(ROUNDDOWN((N36/G36),0)*ROUNDDOWN((O36/H36),0),ROUNDDOWN((N36/H36),0)*ROUNDDOWN((O36/G36),0)),IF(M36="HOJA ",(D36*F36)/MAX(ROUNDDOWN((N36/G36),0)*ROUNDDOWN((O36/H36),0),ROUNDDOWN((N36/H36),0)*ROUNDDOWN((O36/G36),0)),IF(M36="M",G36,IF(AND(M36="PIEZA",G36<>0),(D36*F36)/ROUNDDOWN((N36/G36),0),IF(M36="PIEZA",(D36*F36),IF(M36="CAJA",(D36*F36),IF(M36="DM2",(D36*F36),IF(M36="FT",(D36*F36),IF(M36="JGO",(D36*F36),IF(M36="KG",(D36*F36),IF(M36="LB",(D36*F36),IF(M36="LT",(D36*F36),IF(M36="M2",(D36*F36),IF(M36="M3",(D36*F36),IF(M36="ROLLO",(D36*F36),IF(M36="SQYDS",(D36*F36),IF(M36="UD./SERV.",(D36*F36),IF(M36="YD",(D36*F36)," ")))))))))))))))))),"") | Q36: =IFERROR(IF(M36="HOJA",D36*F36*G36*H36*2*0.125,IF(AND(M36="PIEZA",H36=0),D36*F36*G36*VLOOKUP(J36,articulo:clave_comercial,10,0)*0.125,0))," ") -> 0 | S36: {=IFERROR(INDEX($J$3:$J$52,MATCH(0,INDEX(COUNTIF(S$2:$S35,$J$3:$J$52),0,0),0))," ")} | T36: {=IFERROR(INDEX($L$3:$L$52,MATCH(0,INDEX(COUNTIF($T$2:T35,$L$3:$L$52),0,0),0))," ")} | U36: =IFERROR(IF(AND(VLOOKUP(S36,$J$3:$Q$218,4,0)="KG",VLOOKUP(S36,$J$3:$Q$218,7,0)=0,VLOOKUP(S36,$J$3:$Q$218,8,0)=0),SUM($Q$3:$Q$218),SUMIF($J$3:$J$218,S36,$P$3:$P$218)),"") | W36: =IFERROR(IF(OR(M36="HOJA",M36="HOJA "),((MAX(ROUNDDOWN((0.915/G36),0)*ROUNDDOWN((2.44/H36),0),ROUNDDOWN((0.915/H36),0)*ROUNDDOWN((2.44/G36),0)))*G36*H36)/(0.915*2.44),""),"") | X36: =IFERROR(MAX(ROUNDDOWN((0.915/G36),0)*ROUNDDOWN((2.44/H36),0),ROUNDDOWN((0.915/H36),0)*ROUNDDOWN((2.44/G36),0)),"") | Y36: =IFERROR(IF(OR(M36="HOJA",M36="HOJA "),((MAX(ROUNDDOWN((0.915/G36),0)*ROUNDDOWN((3.05/H36),0),ROUNDDOWN((0.915/H36),0)*ROUNDDOWN((3.05/G36),0)))*G36*H36)/(0.915*3.05),""),"") | Z36: =IFERROR(MAX(ROUNDDOWN((0.915/G36),0)*ROUNDDOWN((3.05/H36),0),ROUNDDOWN((0.915/H36),0)*ROUNDDOWN((3.05/G36),0)),"") | AA36: =IFERROR(IF(OR(M36="HOJA",M36="HOJA "),((MAX(ROUNDDOWN((1.22/G36),0)*ROUNDDOWN((2.44/H36),0),ROUNDDOWN((1.22/H36),0)*ROUNDDOWN((2.44/G36),0)))*G36*H36)/(1.22*2.44),""),"") | AB36: =IFERROR(MAX(ROUNDDOWN((1.22/G36),0)*ROUNDDOWN((2.44/H36),0),ROUNDDOWN((1.22/H36),0)*ROUNDDOWN((2.44/G36),0)),"") | AC36: =IFERROR(IF(OR(M36="HOJA",M36="HOJA "),((MAX(ROUNDDOWN((1.22/G36),0)*ROUNDDOWN((3.05/H36),0),ROUNDDOWN((1.22/H36),0)*ROUNDDOWN((3.05/G36),0)))*G36*H36)/(1.22*3.05),""),"") | AD36: =IFERROR(MAX(ROUNDDOWN((1.22/G36),0)*ROUNDDOWN((3.05/H36),0),ROUNDDOWN((1.22/H36),0)*ROUNDDOWN((3.05/G36),0)),"")
L37: =IFERROR(VLOOKUP(J37,articulo:clave_comercial,2,0)," ") | M37: =UPPER(IFERROR(VLOOKUP(J37,articulo:clave_comercial,5,0)," ")) | N37: =IFERROR(IF(VLOOKUP(J37,articulo:clave_comercial,8,0)=0," ",VLOOKUP(J37,articulo:clave_comercial,8,0))," ") | O37: =IFERROR(IF(VLOOKUP(J37,articulo:clave_comercial,9,0)=0," ",VLOOKUP(J37,articulo:clave_comercial,9,0))," ") | P37: =IFERROR(IF(M37="HOJA",(D37*F37)/MAX(ROUNDDOWN((N37/G37),0)*ROUNDDOWN((O37/H37),0),ROUNDDOWN((N37/H37),0)*ROUNDDOWN((O37/G37),0)),IF(M37="HOJA ",(D37*F37)/MAX(ROUNDDOWN((N37/G37),0)*ROUNDDOWN((O37/H37),0),ROUNDDOWN((N37/H37),0)*ROUNDDOWN((O37/G37),0)),IF(M37="M",G37,IF(AND(M37="PIEZA",G37<>0),(D37*F37)/ROUNDDOWN((N37/G37),0),IF(M37="PIEZA",(D37*F37),IF(M37="CAJA",(D37*F37),IF(M37="DM2",(D37*F37),IF(M37="FT",(D37*F37),IF(M37="JGO",(D37*F37),IF(M37="KG",(D37*F37),IF(M37="LB",(D37*F37),IF(M37="LT",(D37*F37),IF(M37="M2",(D37*F37),IF(M37="M3",(D37*F37),IF(M37="ROLLO",(D37*F37),IF(M37="SQYDS",(D37*F37),IF(M37="UD./SERV.",(D37*F37),IF(M37="YD",(D37*F37)," ")))))))))))))))))),"") | Q37: =IFERROR(IF(M37="HOJA",D37*F37*G37*H37*2*0.125,IF(AND(M37="PIEZA",H37=0),D37*F37*G37*VLOOKUP(J37,articulo:clave_comercial,10,0)*0.125,0))," ") -> 0 | S37: {=IFERROR(INDEX($J$3:$J$52,MATCH(0,INDEX(COUNTIF(S$2:$S36,$J$3:$J$52),0,0),0))," ")} | T37: {=IFERROR(INDEX($L$3:$L$52,MATCH(0,INDEX(COUNTIF($T$2:T36,$L$3:$L$52),0,0),0))," ")} | U37: =IFERROR(IF(AND(VLOOKUP(S37,$J$3:$Q$218,4,0)="KG",VLOOKUP(S37,$J$3:$Q$218,7,0)=0,VLOOKUP(S37,$J$3:$Q$218,8,0)=0),SUM($Q$3:$Q$218),SUMIF($J$3:$J$218,S37,$P$3:$P$218)),"") | W37: =IFERROR(IF(OR(M37="HOJA",M37="HOJA "),((MAX(ROUNDDOWN((0.915/G37),0)*ROUNDDOWN((2.44/H37),0),ROUNDDOWN((0.915/H37),0)*ROUNDDOWN((2.44/G37),0)))*G37*H37)/(0.915*2.44),""),"") | X37: =IFERROR(MAX(ROUNDDOWN((0.915/G37),0)*ROUNDDOWN((2.44/H37),0),ROUNDDOWN((0.915/H37),0)*ROUNDDOWN((2.44/G37),0)),"") | Y37: =IFERROR(IF(OR(M37="HOJA",M37="HOJA "),((MAX(ROUNDDOWN((0.915/G37),0)*ROUNDDOWN((3.05/H37),0),ROUNDDOWN((0.915/H37),0)*ROUNDDOWN((3.05/G37),0)))*G37*H37)/(0.915*3.05),""),"") | Z37: =IFERROR(MAX(ROUNDDOWN((0.915/G37),0)*ROUNDDOWN((3.05/H37),0),ROUNDDOWN((0.915/H37),0)*ROUNDDOWN((3.05/G37),0)),"") | AA37: =IFERROR(IF(OR(M37="HOJA",M37="HOJA "),((MAX(ROUNDDOWN((1.22/G37),0)*ROUNDDOWN((2.44/H37),0),ROUNDDOWN((1.22/H37),0)*ROUNDDOWN((2.44/G37),0)))*G37*H37)/(1.22*2.44),""),"") | AB37: =IFERROR(MAX(ROUNDDOWN((1.22/G37),0)*ROUNDDOWN((2.44/H37),0),ROUNDDOWN((1.22/H37),0)*ROUNDDOWN((2.44/G37),0)),"") | AC37: =IFERROR(IF(OR(M37="HOJA",M37="HOJA "),((MAX(ROUNDDOWN((1.22/G37),0)*ROUNDDOWN((3.05/H37),0),ROUNDDOWN((1.22/H37),0)*ROUNDDOWN((3.05/G37),0)))*G37*H37)/(1.22*3.05),""),"") | AD37: =IFERROR(MAX(ROUNDDOWN((1.22/G37),0)*ROUNDDOWN((3.05/H37),0),ROUNDDOWN((1.22/H37),0)*ROUNDDOWN((3.05/G37),0)),"")
L38: =IFERROR(VLOOKUP(J38,articulo:clave_comercial,2,0)," ") | M38: =UPPER(IFERROR(VLOOKUP(J38,articulo:clave_comercial,5,0)," ")) | N38: =IFERROR(IF(VLOOKUP(J38,articulo:clave_comercial,8,0)=0," ",VLOOKUP(J38,articulo:clave_comercial,8,0))," ") | O38: =IFERROR(IF(VLOOKUP(J38,articulo:clave_comercial,9,0)=0," ",VLOOKUP(J38,articulo:clave_comercial,9,0))," ") | P38: =IFERROR(IF(M38="HOJA",(D38*F38)/MAX(ROUNDDOWN((N38/G38),0)*ROUNDDOWN((O38/H38),0),ROUNDDOWN((N38/H38),0)*ROUNDDOWN((O38/G38),0)),IF(M38="HOJA ",(D38*F38)/MAX(ROUNDDOWN((N38/G38),0)*ROUNDDOWN((O38/H38),0),ROUNDDOWN((N38/H38),0)*ROUNDDOWN((O38/G38),0)),IF(M38="M",G38,IF(AND(M38="PIEZA",G38<>0),(D38*F38)/ROUNDDOWN((N38/G38),0),IF(M38="PIEZA",(D38*F38),IF(M38="CAJA",(D38*F38),IF(M38="DM2",(D38*F38),IF(M38="FT",(D38*F38),IF(M38="JGO",(D38*F38),IF(M38="KG",(D38*F38),IF(M38="LB",(D38*F38),IF(M38="LT",(D38*F38),IF(M38="M2",(D38*F38),IF(M38="M3",(D38*F38),IF(M38="ROLLO",(D38*F38),IF(M38="SQYDS",(D38*F38),IF(M38="UD./SERV.",(D38*F38),IF(M38="YD",(D38*F38)," ")))))))))))))))))),"") | Q38: =IFERROR(IF(M38="HOJA",D38*F38*G38*H38*2*0.125,IF(AND(M38="PIEZA",H38=0),D38*F38*G38*VLOOKUP(J38,articulo:clave_comercial,10,0)*0.125,0))," ") -> 0 | S38: {=IFERROR(INDEX($J$3:$J$52,MATCH(0,INDEX(COUNTIF(S$2:$S37,$J$3:$J$52),0,0),0))," ")} | T38: {=IFERROR(INDEX($L$3:$L$52,MATCH(0,INDEX(COUNTIF($T$2:T37,$L$3:$L$52),0,0),0))," ")} | U38: =IFERROR(IF(AND(VLOOKUP(S38,$J$3:$Q$218,4,0)="KG",VLOOKUP(S38,$J$3:$Q$218,7,0)=0,VLOOKUP(S38,$J$3:$Q$218,8,0)=0),SUM($Q$3:$Q$218),SUMIF($J$3:$J$218,S38,$P$3:$P$218)),"") | W38: =IFERROR(IF(OR(M38="HOJA",M38="HOJA "),((MAX(ROUNDDOWN((0.915/G38),0)*ROUNDDOWN((2.44/H38),0),ROUNDDOWN((0.915/H38),0)*ROUNDDOWN((2.44/G38),0)))*G38*H38)/(0.915*2.44),""),"") | X38: =IFERROR(MAX(ROUNDDOWN((0.915/G38),0)*ROUNDDOWN((2.44/H38),0),ROUNDDOWN((0.915/H38),0)*ROUNDDOWN((2.44/G38),0)),"") | Y38: =IFERROR(IF(OR(M38="HOJA",M38="HOJA "),((MAX(ROUNDDOWN((0.915/G38),0)*ROUNDDOWN((3.05/H38),0),ROUNDDOWN((0.915/H38),0)*ROUNDDOWN((3.05/G38),0)))*G38*H38)/(0.915*3.05),""),"") | Z38: =IFERROR(MAX(ROUNDDOWN((0.915/G38),0)*ROUNDDOWN((3.05/H38),0),ROUNDDOWN((0.915/H38),0)*ROUNDDOWN((3.05/G38),0)),"") | AA38: =IFERROR(IF(OR(M38="HOJA",M38="HOJA "),((MAX(ROUNDDOWN((1.22/G38),0)*ROUNDDOWN((2.44/H38),0),ROUNDDOWN((1.22/H38),0)*ROUNDDOWN((2.44/G38),0)))*G38*H38)/(1.22*2.44),""),"") | AB38: =IFERROR(MAX(ROUNDDOWN((1.22/G38),0)*ROUNDDOWN((2.44/H38),0),ROUNDDOWN((1.22/H38),0)*ROUNDDOWN((2.44/G38),0)),"") | AC38: =IFERROR(IF(OR(M38="HOJA",M38="HOJA "),((MAX(ROUNDDOWN((1.22/G38),0)*ROUNDDOWN((3.05/H38),0),ROUNDDOWN((1.22/H38),0)*ROUNDDOWN((3.05/G38),0)))*G38*H38)/(1.22*3.05),""),"") | AD38: =IFERROR(MAX(ROUNDDOWN((1.22/G38),0)*ROUNDDOWN((3.05/H38),0),ROUNDDOWN((1.22/H38),0)*ROUNDDOWN((3.05/G38),0)),"")
L39: =IFERROR(VLOOKUP(J39,articulo:clave_comercial,2,0)," ") | M39: =UPPER(IFERROR(VLOOKUP(J39,articulo:clave_comercial,5,0)," ")) | N39: =IFERROR(IF(VLOOKUP(J39,articulo:clave_comercial,8,0)=0," ",VLOOKUP(J39,articulo:clave_comercial,8,0))," ") | O39: =IFERROR(IF(VLOOKUP(J39,articulo:clave_comercial,9,0)=0," ",VLOOKUP(J39,articulo:clave_comercial,9,0))," ") | P39: =IFERROR(IF(M39="HOJA",(D39*F39)/MAX(ROUNDDOWN((N39/G39),0)*ROUNDDOWN((O39/H39),0),ROUNDDOWN((N39/H39),0)*ROUNDDOWN((O39/G39),0)),IF(M39="HOJA ",(D39*F39)/MAX(ROUNDDOWN((N39/G39),0)*ROUNDDOWN((O39/H39),0),ROUNDDOWN((N39/H39),0)*ROUNDDOWN((O39/G39),0)),IF(M39="M",G39,IF(AND(M39="PIEZA",G39<>0),(D39*F39)/ROUNDDOWN((N39/G39),0),IF(M39="PIEZA",(D39*F39),IF(M39="CAJA",(D39*F39),IF(M39="DM2",(D39*F39),IF(M39="FT",(D39*F39),IF(M39="JGO",(D39*F39),IF(M39="KG",(D39*F39),IF(M39="LB",(D39*F39),IF(M39="LT",(D39*F39),IF(M39="M2",(D39*F39),IF(M39="M3",(D39*F39),IF(M39="ROLLO",(D39*F39),IF(M39="SQYDS",(D39*F39),IF(M39="UD./SERV.",(D39*F39),IF(M39="YD",(D39*F39)," ")))))))))))))))))),"") | Q39: =IFERROR(IF(M39="HOJA",D39*F39*G39*H39*2*0.125,IF(AND(M39="PIEZA",H39=0),D39*F39*G39*VLOOKUP(J39,articulo:clave_comercial,10,0)*0.125,0))," ") -> 0 | S39: {=IFERROR(INDEX($J$3:$J$52,MATCH(0,INDEX(COUNTIF(S$2:$S38,$J$3:$J$52),0,0),0))," ")} | T39: {=IFERROR(INDEX($L$3:$L$52,MATCH(0,INDEX(COUNTIF($T$2:T38,$L$3:$L$52),0,0),0))," ")} | U39: =IFERROR(IF(AND(VLOOKUP(S39,$J$3:$Q$218,4,0)="KG",VLOOKUP(S39,$J$3:$Q$218,7,0)=0,VLOOKUP(S39,$J$3:$Q$218,8,0)=0),SUM($Q$3:$Q$218),SUMIF($J$3:$J$218,S39,$P$3:$P$218)),"") | W39: =IFERROR(IF(OR(M39="HOJA",M39="HOJA "),((MAX(ROUNDDOWN((0.915/G39),0)*ROUNDDOWN((2.44/H39),0),ROUNDDOWN((0.915/H39),0)*ROUNDDOWN((2.44/G39),0)))*G39*H39)/(0.915*2.44),""),"") | X39: =IFERROR(MAX(ROUNDDOWN((0.915/G39),0)*ROUNDDOWN((2.44/H39),0),ROUNDDOWN((0.915/H39),0)*ROUNDDOWN((2.44/G39),0)),"") | Y39: =IFERROR(IF(OR(M39="HOJA",M39="HOJA "),((MAX(ROUNDDOWN((0.915/G39),0)*ROUNDDOWN((3.05/H39),0),ROUNDDOWN((0.915/H39),0)*ROUNDDOWN((3.05/G39),0)))*G39*H39)/(0.915*3.05),""),"") | Z39: =IFERROR(MAX(ROUNDDOWN((0.915/G39),0)*ROUNDDOWN((3.05/H39),0),ROUNDDOWN((0.915/H39),0)*ROUNDDOWN((3.05/G39),0)),"") | AA39: =IFERROR(IF(OR(M39="HOJA",M39="HOJA "),((MAX(ROUNDDOWN((1.22/G39),0)*ROUNDDOWN((2.44/H39),0),ROUNDDOWN((1.22/H39),0)*ROUNDDOWN((2.44/G39),0)))*G39*H39)/(1.22*2.44),""),"") | AB39: =IFERROR(MAX(ROUNDDOWN((1.22/G39),0)*ROUNDDOWN((2.44/H39),0),ROUNDDOWN((1.22/H39),0)*ROUNDDOWN((2.44/G39),0)),"") | AC39: =IFERROR(IF(OR(M39="HOJA",M39="HOJA "),((MAX(ROUNDDOWN((1.22/G39),0)*ROUNDDOWN((3.05/H39),0),ROUNDDOWN((1.22/H39),0)*ROUNDDOWN((3.05/G39),0)))*G39*H39)/(1.22*3.05),""),"") | AD39: =IFERROR(MAX(ROUNDDOWN((1.22/G39),0)*ROUNDDOWN((3.05/H39),0),ROUNDDOWN((1.22/H39),0)*ROUNDDOWN((3.05/G39),0)),"")
L40: =IFERROR(VLOOKUP(J40,articulo:clave_comercial,2,0)," ") | M40: =UPPER(IFERROR(VLOOKUP(J40,articulo:clave_comercial,5,0)," ")) | N40: =IFERROR(IF(VLOOKUP(J40,articulo:clave_comercial,8,0)=0," ",VLOOKUP(J40,articulo:clave_comercial,8,0))," ") | O40: =IFERROR(IF(VLOOKUP(J40,articulo:clave_comercial,9,0)=0," ",VLOOKUP(J40,articulo:clave_comercial,9,0))," ") | P40: =IFERROR(IF(M40="HOJA",(D40*F40)/MAX(ROUNDDOWN((N40/G40),0)*ROUNDDOWN((O40/H40),0),ROUNDDOWN((N40/H40),0)*ROUNDDOWN((O40/G40),0)),IF(M40="HOJA ",(D40*F40)/MAX(ROUNDDOWN((N40/G40),0)*ROUNDDOWN((O40/H40),0),ROUNDDOWN((N40/H40),0)*ROUNDDOWN((O40/G40),0)),IF(M40="M",G40,IF(AND(M40="PIEZA",G40<>0),(D40*F40)/ROUNDDOWN((N40/G40),0),IF(M40="PIEZA",(D40*F40),IF(M40="CAJA",(D40*F40),IF(M40="DM2",(D40*F40),IF(M40="FT",(D40*F40),IF(M40="JGO",(D40*F40),IF(M40="KG",(D40*F40),IF(M40="LB",(D40*F40),IF(M40="LT",(D40*F40),IF(M40="M2",(D40*F40),IF(M40="M3",(D40*F40),IF(M40="ROLLO",(D40*F40),IF(M40="SQYDS",(D40*F40),IF(M40="UD./SERV.",(D40*F40),IF(M40="YD",(D40*F40)," ")))))))))))))))))),"") | Q40: =IFERROR(IF(M40="HOJA",D40*F40*G40*H40*2*0.125,IF(AND(M40="PIEZA",H40=0),D40*F40*G40*VLOOKUP(J40,articulo:clave_comercial,10,0)*0.125,0))," ") -> 0 | S40: {=IFERROR(INDEX($J$3:$J$52,MATCH(0,INDEX(COUNTIF(S$2:$S39,$J$3:$J$52),0,0),0))," ")} | T40: {=IFERROR(INDEX($L$3:$L$52,MATCH(0,INDEX(COUNTIF($T$2:T39,$L$3:$L$52),0,0),0))," ")} | U40: =IFERROR(IF(AND(VLOOKUP(S40,$J$3:$Q$218,4,0)="KG",VLOOKUP(S40,$J$3:$Q$218,7,0)=0,VLOOKUP(S40,$J$3:$Q$218,8,0)=0),SUM($Q$3:$Q$218),SUMIF($J$3:$J$218,S40,$P$3:$P$218)),"") | W40: =IFERROR(IF(OR(M40="HOJA",M40="HOJA "),((MAX(ROUNDDOWN((0.915/G40),0)*ROUNDDOWN((2.44/H40),0),ROUNDDOWN((0.915/H40),0)*ROUNDDOWN((2.44/G40),0)))*G40*H40)/(0.915*2.44),""),"") | X40: =IFERROR(MAX(ROUNDDOWN((0.915/G40),0)*ROUNDDOWN((2.44/H40),0),ROUNDDOWN((0.915/H40),0)*ROUNDDOWN((2.44/G40),0)),"") | Y40: =IFERROR(IF(OR(M40="HOJA",M40="HOJA "),((MAX(ROUNDDOWN((0.915/G40),0)*ROUNDDOWN((3.05/H40),0),ROUNDDOWN((0.915/H40),0)*ROUNDDOWN((3.05/G40),0)))*G40*H40)/(0.915*3.05),""),"") | Z40: =IFERROR(MAX(ROUNDDOWN((0.915/G40),0)*ROUNDDOWN((3.05/H40),0),ROUNDDOWN((0.915/H40),0)*ROUNDDOWN((3.05/G40),0)),"") | AA40: =IFERROR(IF(OR(M40="HOJA",M40="HOJA "),((MAX(ROUNDDOWN((1.22/G40),0)*ROUNDDOWN((2.44/H40),0),ROUNDDOWN((1.22/H40),0)*ROUNDDOWN((2.44/G40),0)))*G40*H40)/(1.22*2.44),""),"") | AB40: =IFERROR(MAX(ROUNDDOWN((1.22/G40),0)*ROUNDDOWN((2.44/H40),0),ROUNDDOWN((1.22/H40),0)*ROUNDDOWN((2.44/G40),0)),"") | AC40: =IFERROR(IF(OR(M40="HOJA",M40="HOJA "),((MAX(ROUNDDOWN((1.22/G40),0)*ROUNDDOWN((3.05/H40),0),ROUNDDOWN((1.22/H40),0)*ROUNDDOWN((3.05/G40),0)))*G40*H40)/(1.22*3.05),""),"") | AD40: =IFERROR(MAX(ROUNDDOWN((1.22/G40),0)*ROUNDDOWN((3.05/H40),0),ROUNDDOWN((1.22/H40),0)*ROUNDDOWN((3.05/G40),0)),"")
L41: =IFERROR(VLOOKUP(J41,articulo:clave_comercial,2,0)," ") | M41: =UPPER(IFERROR(VLOOKUP(J41,articulo:clave_comercial,5,0)," ")) | N41: =IFERROR(IF(VLOOKUP(J41,articulo:clave_comercial,8,0)=0," ",VLOOKUP(J41,articulo:clave_comercial,8,0))," ") | O41: =IFERROR(IF(VLOOKUP(J41,articulo:clave_comercial,9,0)=0," ",VLOOKUP(J41,articulo:clave_comercial,9,0))," ") | P41: =IFERROR(IF(M41="HOJA",(D41*F41)/MAX(ROUNDDOWN((N41/G41),0)*ROUNDDOWN((O41/H41),0),ROUNDDOWN((N41/H41),0)*ROUNDDOWN((O41/G41),0)),IF(M41="HOJA ",(D41*F41)/MAX(ROUNDDOWN((N41/G41),0)*ROUNDDOWN((O41/H41),0),ROUNDDOWN((N41/H41),0)*ROUNDDOWN((O41/G41),0)),IF(M41="M",G41,IF(AND(M41="PIEZA",G41<>0),(D41*F41)/ROUNDDOWN((N41/G41),0),IF(M41="PIEZA",(D41*F41),IF(M41="CAJA",(D41*F41),IF(M41="DM2",(D41*F41),IF(M41="FT",(D41*F41),IF(M41="JGO",(D41*F41),IF(M41="KG",(D41*F41),IF(M41="LB",(D41*F41),IF(M41="LT",(D41*F41),IF(M41="M2",(D41*F41),IF(M41="M3",(D41*F41),IF(M41="ROLLO",(D41*F41),IF(M41="SQYDS",(D41*F41),IF(M41="UD./SERV.",(D41*F41),IF(M41="YD",(D41*F41)," ")))))))))))))))))),"") | Q41: =IFERROR(IF(M41="HOJA",D41*F41*G41*H41*2*0.125,IF(AND(M41="PIEZA",H41=0),D41*F41*G41*VLOOKUP(J41,articulo:clave_comercial,10,0)*0.125,0))," ") -> 0 | S41: {=IFERROR(INDEX($J$3:$J$52,MATCH(0,INDEX(COUNTIF(S$2:$S40,$J$3:$J$52),0,0),0))," ")} | T41: {=IFERROR(INDEX($L$3:$L$52,MATCH(0,INDEX(COUNTIF($T$2:T40,$L$3:$L$52),0,0),0))," ")} | U41: =IFERROR(IF(AND(VLOOKUP(S41,$J$3:$Q$218,4,0)="KG",VLOOKUP(S41,$J$3:$Q$218,7,0)=0,VLOOKUP(S41,$J$3:$Q$218,8,0)=0),SUM($Q$3:$Q$218),SUMIF($J$3:$J$218,S41,$P$3:$P$218)),"") | W41: =IFERROR(IF(OR(M41="HOJA",M41="HOJA "),((MAX(ROUNDDOWN((0.915/G41),0)*ROUNDDOWN((2.44/H41),0),ROUNDDOWN((0.915/H41),0)*ROUNDDOWN((2.44/G41),0)))*G41*H41)/(0.915*2.44),""),"") | X41: =IFERROR(MAX(ROUNDDOWN((0.915/G41),0)*ROUNDDOWN((2.44/H41),0),ROUNDDOWN((0.915/H41),0)*ROUNDDOWN((2.44/G41),0)),"") | Y41: =IFERROR(IF(OR(M41="HOJA",M41="HOJA "),((MAX(ROUNDDOWN((0.915/G41),0)*ROUNDDOWN((3.05/H41),0),ROUNDDOWN((0.915/H41),0)*ROUNDDOWN((3.05/G41),0)))*G41*H41)/(0.915*3.05),""),"") | Z41: =IFERROR(MAX(ROUNDDOWN((0.915/G41),0)*ROUNDDOWN((3.05/H41),0),ROUNDDOWN((0.915/H41),0)*ROUNDDOWN((3.05/G41),0)),"") | AA41: =IFERROR(IF(OR(M41="HOJA",M41="HOJA "),((MAX(ROUNDDOWN((1.22/G41),0)*ROUNDDOWN((2.44/H41),0),ROUNDDOWN((1.22/H41),0)*ROUNDDOWN((2.44/G41),0)))*G41*H41)/(1.22*2.44),""),"") | AB41: =IFERROR(MAX(ROUNDDOWN((1.22/G41),0)*ROUNDDOWN((2.44/H41),0),ROUNDDOWN((1.22/H41),0)*ROUNDDOWN((2.44/G41),0)),"") | AC41: =IFERROR(IF(OR(M41="HOJA",M41="HOJA "),((MAX(ROUNDDOWN((1.22/G41),0)*ROUNDDOWN((3.05/H41),0),ROUNDDOWN((1.22/H41),0)*ROUNDDOWN((3.05/G41),0)))*G41*H41)/(1.22*3.05),""),"") | AD41: =IFERROR(MAX(ROUNDDOWN((1.22/G41),0)*ROUNDDOWN((3.05/H41),0),ROUNDDOWN((1.22/H41),0)*ROUNDDOWN((3.05/G41),0)),"")
A42: 7 | L42: =IFERROR(VLOOKUP(J42,articulo:clave_comercial,2,0)," ") | M42: =UPPER(IFERROR(VLOOKUP(J42,articulo:clave_comercial,5,0)," ")) | N42: =IFERROR(IF(VLOOKUP(J42,articulo:clave_comercial,8,0)=0," ",VLOOKUP(J42,articulo:clave_comercial,8,0))," ") | O42: =IFERROR(IF(VLOOKUP(J42,articulo:clave_comercial,9,0)=0," ",VLOOKUP(J42,articulo:clave_comercial,9,0))," ") | P42: =IFERROR(IF(M42="HOJA",(D42*F42)/MAX(ROUNDDOWN((N42/G42),0)*ROUNDDOWN((O42/H42),0),ROUNDDOWN((N42/H42),0)*ROUNDDOWN((O42/G42),0)),IF(M42="HOJA ",(D42*F42)/MAX(ROUNDDOWN((N42/G42),0)*ROUNDDOWN((O42/H42),0),ROUNDDOWN((N42/H42),0)*ROUNDDOWN((O42/G42),0)),IF(M42="M",G42,IF(AND(M42="PIEZA",G42<>0),(D42*F42)/ROUNDDOWN((N42/G42),0),IF(M42="PIEZA",(D42*F42),IF(M42="CAJA",(D42*F42),IF(M42="DM2",(D42*F42),IF(M42="FT",(D42*F42),IF(M42="JGO",(D42*F42),IF(M42="KG",(D42*F42),IF(M42="LB",(D42*F42),IF(M42="LT",(D42*F42),IF(M42="M2",(D42*F42),IF(M42="M3",(D42*F42),IF(M42="ROLLO",(D42*F42),IF(M42="SQYDS",(D42*F42),IF(M42="UD./SERV.",(D42*F42),IF(M42="YD",(D42*F42)," ")))))))))))))))))),"") | Q42: =IFERROR(IF(M42="HOJA",D42*F42*G42*H42*2*0.125,IF(AND(M42="PIEZA",H42=0),D42*F42*G42*VLOOKUP(J42,articulo:clave_comercial,10,0)*0.125,0))," ") -> 0 | S42: {=IFERROR(INDEX($J$3:$J$52,MATCH(0,INDEX(COUNTIF(S$2:$S41,$J$3:$J$52),0,0),0))," ")} | T42: {=IFERROR(INDEX($L$3:$L$52,MATCH(0,INDEX(COUNTIF($T$2:T41,$L$3:$L$52),0,0),0))," ")} | U42: =IFERROR(IF(AND(VLOOKUP(S42,$J$3:$Q$218,4,0)="KG",VLOOKUP(S42,$J$3:$Q$218,7,0)=0,VLOOKUP(S42,$J$3:$Q$218,8,0)=0),SUM($Q$3:$Q$218),SUMIF($J$3:$J$218,S42,$P$3:$P$218)),"") | W42: =IFERROR(IF(OR(M42="HOJA",M42="HOJA "),((MAX(ROUNDDOWN((0.915/G42),0)*ROUNDDOWN((2.44/H42),0),ROUNDDOWN((0.915/H42),0)*ROUNDDOWN((2.44/G42),0)))*G42*H42)/(0.915*2.44),""),"") | X42: =IFERROR(MAX(ROUNDDOWN((0.915/G42),0)*ROUNDDOWN((2.44/H42),0),ROUNDDOWN((0.915/H42),0)*ROUNDDOWN((2.44/G42),0)),"") | Y42: =IFERROR(IF(OR(M42="HOJA",M42="HOJA "),((MAX(ROUNDDOWN((0.915/G42),0)*ROUNDDOWN((3.05/H42),0),ROUNDDOWN((0.915/H42),0)*ROUNDDOWN((3.05/G42),0)))*G42*H42)/(0.915*3.05),""),"") | Z42: =IFERROR(MAX(ROUNDDOWN((0.915/G42),0)*ROUNDDOWN((3.05/H42),0),ROUNDDOWN((0.915/H42),0)*ROUNDDOWN((3.05/G42),0)),"") | AA42: =IFERROR(IF(OR(M42="HOJA",M42="HOJA "),((MAX(ROUNDDOWN((1.22/G42),0)*ROUNDDOWN((2.44/H42),0),ROUNDDOWN((1.22/H42),0)*ROUNDDOWN((2.44/G42),0)))*G42*H42)/(1.22*2.44),""),"") | AB42: =IFERROR(MAX(ROUNDDOWN((1.22/G42),0)*ROUNDDOWN((2.44/H42),0),ROUNDDOWN((1.22/H42),0)*ROUNDDOWN((2.44/G42),0)),"") | AC42: =IFERROR(IF(OR(M42="HOJA",M42="HOJA "),((MAX(ROUNDDOWN((1.22/G42),0)*ROUNDDOWN((3.05/H42),0),ROUNDDOWN((1.22/H42),0)*ROUNDDOWN((3.05/G42),0)))*G42*H42)/(1.22*3.05),""),"") | AD42: =IFERROR(MAX(ROUNDDOWN((1.22/G42),0)*ROUNDDOWN((3.05/H42),0),ROUNDDOWN((1.22/H42),0)*ROUNDDOWN((3.05/G42),0)),"")
L43: =IFERROR(VLOOKUP(J43,articulo:clave_comercial,2,0)," ") | M43: =UPPER(IFERROR(VLOOKUP(J43,articulo:clave_comercial,5,0)," ")) | N43: =IFERROR(IF(VLOOKUP(J43,articulo:clave_comercial,8,0)=0," ",VLOOKUP(J43,articulo:clave_comercial,8,0))," ") | O43: =IFERROR(IF(VLOOKUP(J43,articulo:clave_comercial,9,0)=0," ",VLOOKUP(J43,articulo:clave_comercial,9,0))," ") | P43: =IFERROR(IF(M43="HOJA",(D43*F43)/MAX(ROUNDDOWN((N43/G43),0)*ROUNDDOWN((O43/H43),0),ROUNDDOWN((N43/H43),0)*ROUNDDOWN((O43/G43),0)),IF(M43="HOJA ",(D43*F43)/MAX(ROUNDDOWN((N43/G43),0)*ROUNDDOWN((O43/H43),0),ROUNDDOWN((N43/H43),0)*ROUNDDOWN((O43/G43),0)),IF(M43="M",G43,IF(AND(M43="PIEZA",G43<>0),(D43*F43)/ROUNDDOWN((N43/G43),0),IF(M43="PIEZA",(D43*F43),IF(M43="CAJA",(D43*F43),IF(M43="DM2",(D43*F43),IF(M43="FT",(D43*F43),IF(M43="JGO",(D43*F43),IF(M43="KG",(D43*F43),IF(M43="LB",(D43*F43),IF(M43="LT",(D43*F43),IF(M43="M2",(D43*F43),IF(M43="M3",(D43*F43),IF(M43="ROLLO",(D43*F43),IF(M43="SQYDS",(D43*F43),IF(M43="UD./SERV.",(D43*F43),IF(M43="YD",(D43*F43)," ")))))))))))))))))),"") | Q43: =IFERROR(IF(M43="HOJA",D43*F43*G43*H43*2*0.125,IF(AND(M43="PIEZA",H43=0),D43*F43*G43*VLOOKUP(J43,articulo:clave_comercial,10,0)*0.125,0))," ") -> 0 | S43: {=IFERROR(INDEX($J$3:$J$52,MATCH(0,INDEX(COUNTIF(S$2:$S42,$J$3:$J$52),0,0),0))," ")} | T43: {=IFERROR(INDEX($L$3:$L$52,MATCH(0,INDEX(COUNTIF($T$2:T42,$L$3:$L$52),0,0),0))," ")} | U43: =IFERROR(IF(AND(VLOOKUP(S43,$J$3:$Q$218,4,0)="KG",VLOOKUP(S43,$J$3:$Q$218,7,0)=0,VLOOKUP(S43,$J$3:$Q$218,8,0)=0),SUM($Q$3:$Q$218),SUMIF($J$3:$J$218,S43,$P$3:$P$218)),"") | W43: =IFERROR(IF(OR(M43="HOJA",M43="HOJA "),((MAX(ROUNDDOWN((0.915/G43),0)*ROUNDDOWN((2.44/H43),0),ROUNDDOWN((0.915/H43),0)*ROUNDDOWN((2.44/G43),0)))*G43*H43)/(0.915*2.44),""),"") | X43: =IFERROR(MAX(ROUNDDOWN((0.915/G43),0)*ROUNDDOWN((2.44/H43),0),ROUNDDOWN((0.915/H43),0)*ROUNDDOWN((2.44/G43),0)),"") | Y43: =IFERROR(IF(OR(M43="HOJA",M43="HOJA "),((MAX(ROUNDDOWN((0.915/G43),0)*ROUNDDOWN((3.05/H43),0),ROUNDDOWN((0.915/H43),0)*ROUNDDOWN((3.05/G43),0)))*G43*H43)/(0.915*3.05),""),"") | Z43: =IFERROR(MAX(ROUNDDOWN((0.915/G43),0)*ROUNDDOWN((3.05/H43),0),ROUNDDOWN((0.915/H43),0)*ROUNDDOWN((3.05/G43),0)),"") | AA43: =IFERROR(IF(OR(M43="HOJA",M43="HOJA "),((MAX(ROUNDDOWN((1.22/G43),0)*ROUNDDOWN((2.44/H43),0),ROUNDDOWN((1.22/H43),0)*ROUNDDOWN((2.44/G43),0)))*G43*H43)/(1.22*2.44),""),"") | AB43: =IFERROR(MAX(ROUNDDOWN((1.22/G43),0)*ROUNDDOWN((2.44/H43),0),ROUNDDOWN((1.22/H43),0)*ROUNDDOWN((2.44/G43),0)),"") | AC43: =IFERROR(IF(OR(M43="HOJA",M43="HOJA "),((MAX(ROUNDDOWN((1.22/G43),0)*ROUNDDOWN((3.05/H43),0),ROUNDDOWN((1.22/H43),0)*ROUNDDOWN((3.05/G43),0)))*G43*H43)/(1.22*3.05),""),"") | AD43: =IFERROR(MAX(ROUNDDOWN((1.22/G43),0)*ROUNDDOWN((3.05/H43),0),ROUNDDOWN((1.22/H43),0)*ROUNDDOWN((3.05/G43),0)),"")
L44: =IFERROR(VLOOKUP(J44,articulo:clave_comercial,2,0)," ") | M44: =UPPER(IFERROR(VLOOKUP(J44,articulo:clave_comercial,5,0)," ")) | N44: =IFERROR(IF(VLOOKUP(J44,articulo:clave_comercial,8,0)=0," ",VLOOKUP(J44,articulo:clave_comercial,8,0))," ") | O44: =IFERROR(IF(VLOOKUP(J44,articulo:clave_comercial,9,0)=0," ",VLOOKUP(J44,articulo:clave_comercial,9,0))," ") | P44: =IFERROR(IF(M44="HOJA",(D44*F44)/MAX(ROUNDDOWN((N44/G44),0)*ROUNDDOWN((O44/H44),0),ROUNDDOWN((N44/H44),0)*ROUNDDOWN((O44/G44),0)),IF(M44="HOJA ",(D44*F44)/MAX(ROUNDDOWN((N44/G44),0)*ROUNDDOWN((O44/H44),0),ROUNDDOWN((N44/H44),0)*ROUNDDOWN((O44/G44),0)),IF(M44="M",G44,IF(AND(M44="PIEZA",G44<>0),(D44*F44)/ROUNDDOWN((N44/G44),0),IF(M44="PIEZA",(D44*F44),IF(M44="CAJA",(D44*F44),IF(M44="DM2",(D44*F44),IF(M44="FT",(D44*F44),IF(M44="JGO",(D44*F44),IF(M44="KG",(D44*F44),IF(M44="LB",(D44*F44),IF(M44="LT",(D44*F44),IF(M44="M2",(D44*F44),IF(M44="M3",(D44*F44),IF(M44="ROLLO",(D44*F44),IF(M44="SQYDS",(D44*F44),IF(M44="UD./SERV.",(D44*F44),IF(M44="YD",(D44*F44)," ")))))))))))))))))),"") | Q44: =IFERROR(IF(M44="HOJA",D44*F44*G44*H44*2*0.125,IF(AND(M44="PIEZA",H44=0),D44*F44*G44*VLOOKUP(J44,articulo:clave_comercial,10,0)*0.125,0))," ") -> 0 | S44: {=IFERROR(INDEX($J$3:$J$52,MATCH(0,INDEX(COUNTIF(S$2:$S43,$J$3:$J$52),0,0),0))," ")} | T44: {=IFERROR(INDEX($L$3:$L$52,MATCH(0,INDEX(COUNTIF($T$2:T43,$L$3:$L$52),0,0),0))," ")} | U44: =IFERROR(IF(AND(VLOOKUP(S44,$J$3:$Q$218,4,0)="KG",VLOOKUP(S44,$J$3:$Q$218,7,0)=0,VLOOKUP(S44,$J$3:$Q$218,8,0)=0),SUM($Q$3:$Q$218),SUMIF($J$3:$J$218,S44,$P$3:$P$218)),"") | W44: =IFERROR(IF(OR(M44="HOJA",M44="HOJA "),((MAX(ROUNDDOWN((0.915/G44),0)*ROUNDDOWN((2.44/H44),0),ROUNDDOWN((0.915/H44),0)*ROUNDDOWN((2.44/G44),0)))*G44*H44)/(0.915*2.44),""),"") | X44: =IFERROR(MAX(ROUNDDOWN((0.915/G44),0)*ROUNDDOWN((2.44/H44),0),ROUNDDOWN((0.915/H44),0)*ROUNDDOWN((2.44/G44),0)),"") | Y44: =IFERROR(IF(OR(M44="HOJA",M44="HOJA "),((MAX(ROUNDDOWN((0.915/G44),0)*ROUNDDOWN((3.05/H44),0),ROUNDDOWN((0.915/H44),0)*ROUNDDOWN((3.05/G44),0)))*G44*H44)/(0.915*3.05),""),"") | Z44: =IFERROR(MAX(ROUNDDOWN((0.915/G44),0)*ROUNDDOWN((3.05/H44),0),ROUNDDOWN((0.915/H44),0)*ROUNDDOWN((3.05/G44),0)),"") | AA44: =IFERROR(IF(OR(M44="HOJA",M44="HOJA "),((MAX(ROUNDDOWN((1.22/G44),0)*ROUNDDOWN((2.44/H44),0),ROUNDDOWN((1.22/H44),0)*ROUNDDOWN((2.44/G44),0)))*G44*H44)/(1.22*2.44),""),"") | AB44: =IFERROR(MAX(ROUNDDOWN((1.22/G44),0)*ROUNDDOWN((2.44/H44),0),ROUNDDOWN((1.22/H44),0)*ROUNDDOWN((2.44/G44),0)),"") | AC44: =IFERROR(IF(OR(M44="HOJA",M44="HOJA "),((MAX(ROUNDDOWN((1.22/G44),0)*ROUNDDOWN((3.05/H44),0),ROUNDDOWN((1.22/H44),0)*ROUNDDOWN((3.05/G44),0)))*G44*H44)/(1.22*3.05),""),"") | AD44: =IFERROR(MAX(ROUNDDOWN((1.22/G44),0)*ROUNDDOWN((3.05/H44),0),ROUNDDOWN((1.22/H44),0)*ROUNDDOWN((3.05/G44),0)),"")
L45: =IFERROR(VLOOKUP(J45,articulo:clave_comercial,2,0)," ") | M45: =UPPER(IFERROR(VLOOKUP(J45,articulo:clave_comercial,5,0)," ")) | N45: =IFERROR(IF(VLOOKUP(J45,articulo:clave_comercial,8,0)=0," ",VLOOKUP(J45,articulo:clave_comercial,8,0))," ") | O45: =IFERROR(IF(VLOOKUP(J45,articulo:clave_comercial,9,0)=0," ",VLOOKUP(J45,articulo:clave_comercial,9,0))," ") | P45: =IFERROR(IF(M45="HOJA",(D45*F45)/MAX(ROUNDDOWN((N45/G45),0)*ROUNDDOWN((O45/H45),0),ROUNDDOWN((N45/H45),0)*ROUNDDOWN((O45/G45),0)),IF(M45="HOJA ",(D45*F45)/MAX(ROUNDDOWN((N45/G45),0)*ROUNDDOWN((O45/H45),0),ROUNDDOWN((N45/H45),0)*ROUNDDOWN((O45/G45),0)),IF(M45="M",G45,IF(AND(M45="PIEZA",G45<>0),(D45*F45)/ROUNDDOWN((N45/G45),0),IF(M45="PIEZA",(D45*F45),IF(M45="CAJA",(D45*F45),IF(M45="DM2",(D45*F45),IF(M45="FT",(D45*F45),IF(M45="JGO",(D45*F45),IF(M45="KG",(D45*F45),IF(M45="LB",(D45*F45),IF(M45="LT",(D45*F45),IF(M45="M2",(D45*F45),IF(M45="M3",(D45*F45),IF(M45="ROLLO",(D45*F45),IF(M45="SQYDS",(D45*F45),IF(M45="UD./SERV.",(D45*F45),IF(M45="YD",(D45*F45)," ")))))))))))))))))),"") | Q45: =IFERROR(IF(M45="HOJA",D45*F45*G45*H45*2*0.125,IF(AND(M45="PIEZA",H45=0),D45*F45*G45*VLOOKUP(J45,articulo:clave_comercial,10,0)*0.125,0))," ") -> 0 | S45: {=IFERROR(INDEX($J$3:$J$52,MATCH(0,INDEX(COUNTIF(S$2:$S44,$J$3:$J$52),0,0),0))," ")} | T45: {=IFERROR(INDEX($L$3:$L$52,MATCH(0,INDEX(COUNTIF($T$2:T44,$L$3:$L$52),0,0),0))," ")} | U45: =IFERROR(IF(AND(VLOOKUP(S45,$J$3:$Q$218,4,0)="KG",VLOOKUP(S45,$J$3:$Q$218,7,0)=0,VLOOKUP(S45,$J$3:$Q$218,8,0)=0),SUM($Q$3:$Q$218),SUMIF($J$3:$J$218,S45,$P$3:$P$218)),"") | W45: =IFERROR(IF(OR(M45="HOJA",M45="HOJA "),((MAX(ROUNDDOWN((0.915/G45),0)*ROUNDDOWN((2.44/H45),0),ROUNDDOWN((0.915/H45),0)*ROUNDDOWN((2.44/G45),0)))*G45*H45)/(0.915*2.44),""),"") | X45: =IFERROR(MAX(ROUNDDOWN((0.915/G45),0)*ROUNDDOWN((2.44/H45),0),ROUNDDOWN((0.915/H45),0)*ROUNDDOWN((2.44/G45),0)),"") | Y45: =IFERROR(IF(OR(M45="HOJA",M45="HOJA "),((MAX(ROUNDDOWN((0.915/G45),0)*ROUNDDOWN((3.05/H45),0),ROUNDDOWN((0.915/H45),0)*ROUNDDOWN((3.05/G45),0)))*G45*H45)/(0.915*3.05),""),"") | Z45: =IFERROR(MAX(ROUNDDOWN((0.915/G45),0)*ROUNDDOWN((3.05/H45),0),ROUNDDOWN((0.915/H45),0)*ROUNDDOWN((3.05/G45),0)),"") | AA45: =IFERROR(IF(OR(M45="HOJA",M45="HOJA "),((MAX(ROUNDDOWN((1.22/G45),0)*ROUNDDOWN((2.44/H45),0),ROUNDDOWN((1.22/H45),0)*ROUNDDOWN((2.44/G45),0)))*G45*H45)/(1.22*2.44),""),"") | AB45: =IFERROR(MAX(ROUNDDOWN((1.22/G45),0)*ROUNDDOWN((2.44/H45),0),ROUNDDOWN((1.22/H45),0)*ROUNDDOWN((2.44/G45),0)),"") | AC45: =IFERROR(IF(OR(M45="HOJA",M45="HOJA "),((MAX(ROUNDDOWN((1.22/G45),0)*ROUNDDOWN((3.05/H45),0),ROUNDDOWN((1.22/H45),0)*ROUNDDOWN((3.05/G45),0)))*G45*H45)/(1.22*3.05),""),"") | AD45: =IFERROR(MAX(ROUNDDOWN((1.22/G45),0)*ROUNDDOWN((3.05/H45),0),ROUNDDOWN((1.22/H45),0)*ROUNDDOWN((3.05/G45),0)),"")
L46: =IFERROR(VLOOKUP(J46,articulo:clave_comercial,2,0)," ") | M46: =UPPER(IFERROR(VLOOKUP(J46,articulo:clave_comercial,5,0)," ")) | N46: =IFERROR(IF(VLOOKUP(J46,articulo:clave_comercial,8,0)=0," ",VLOOKUP(J46,articulo:clave_comercial,8,0))," ") | O46: =IFERROR(IF(VLOOKUP(J46,articulo:clave_comercial,9,0)=0," ",VLOOKUP(J46,articulo:clave_comercial,9,0))," ") | P46: =IFERROR(IF(M46="HOJA",(D46*F46)/MAX(ROUNDDOWN((N46/G46),0)*ROUNDDOWN((O46/H46),0),ROUNDDOWN((N46/H46),0)*ROUNDDOWN((O46/G46),0)),IF(M46="HOJA ",(D46*F46)/MAX(ROUNDDOWN((N46/G46),0)*ROUNDDOWN((O46/H46),0),ROUNDDOWN((N46/H46),0)*ROUNDDOWN((O46/G46),0)),IF(M46="M",G46,IF(AND(M46="PIEZA",G46<>0),(D46*F46)/ROUNDDOWN((N46/G46),0),IF(M46="PIEZA",(D46*F46),IF(M46="CAJA",(D46*F46),IF(M46="DM2",(D46*F46),IF(M46="FT",(D46*F46),IF(M46="JGO",(D46*F46),IF(M46="KG",(D46*F46),IF(M46="LB",(D46*F46),IF(M46="LT",(D46*F46),IF(M46="M2",(D46*F46),IF(M46="M3",(D46*F46),IF(M46="ROLLO",(D46*F46),IF(M46="SQYDS",(D46*F46),IF(M46="UD./SERV.",(D46*F46),IF(M46="YD",(D46*F46)," ")))))))))))))))))),"") | Q46: =IFERROR(IF(M46="HOJA",D46*F46*G46*H46*2*0.125,IF(AND(M46="PIEZA",H46=0),D46*F46*G46*VLOOKUP(J46,articulo:clave_comercial,10,0)*0.125,0))," ") -> 0 | S46: {=IFERROR(INDEX($J$3:$J$52,MATCH(0,INDEX(COUNTIF(S$2:$S45,$J$3:$J$52),0,0),0))," ")} | T46: {=IFERROR(INDEX($L$3:$L$52,MATCH(0,INDEX(COUNTIF($T$2:T45,$L$3:$L$52),0,0),0))," ")} | U46: =IFERROR(IF(AND(VLOOKUP(S46,$J$3:$Q$218,4,0)="KG",VLOOKUP(S46,$J$3:$Q$218,7,0)=0,VLOOKUP(S46,$J$3:$Q$218,8,0)=0),SUM($Q$3:$Q$218),SUMIF($J$3:$J$218,S46,$P$3:$P$218)),"") | W46: =IFERROR(IF(OR(M46="HOJA",M46="HOJA "),((MAX(ROUNDDOWN((0.915/G46),0)*ROUNDDOWN((2.44/H46),0),ROUNDDOWN((0.915/H46),0)*ROUNDDOWN((2.44/G46),0)))*G46*H46)/(0.915*2.44),""),"") | X46: =IFERROR(MAX(ROUNDDOWN((0.915/G46),0)*ROUNDDOWN((2.44/H46),0),ROUNDDOWN((0.915/H46),0)*ROUNDDOWN((2.44/G46),0)),"") | Y46: =IFERROR(IF(OR(M46="HOJA",M46="HOJA "),((MAX(ROUNDDOWN((0.915/G46),0)*ROUNDDOWN((3.05/H46),0),ROUNDDOWN((0.915/H46),0)*ROUNDDOWN((3.05/G46),0)))*G46*H46)/(0.915*3.05),""),"") | Z46: =IFERROR(MAX(ROUNDDOWN((0.915/G46),0)*ROUNDDOWN((3.05/H46),0),ROUNDDOWN((0.915/H46),0)*ROUNDDOWN((3.05/G46),0)),"") | AA46: =IFERROR(IF(OR(M46="HOJA",M46="HOJA "),((MAX(ROUNDDOWN((1.22/G46),0)*ROUNDDOWN((2.44/H46),0),ROUNDDOWN((1.22/H46),0)*ROUNDDOWN((2.44/G46),0)))*G46*H46)/(1.22*2.44),""),"") | AB46: =IFERROR(MAX(ROUNDDOWN((1.22/G46),0)*ROUNDDOWN((2.44/H46),0),ROUNDDOWN((1.22/H46),0)*ROUNDDOWN((2.44/G46),0)),"") | AC46: =IFERROR(IF(OR(M46="HOJA",M46="HOJA "),((MAX(ROUNDDOWN((1.22/G46),0)*ROUNDDOWN((3.05/H46),0),ROUNDDOWN((1.22/H46),0)*ROUNDDOWN((3.05/G46),0)))*G46*H46)/(1.22*3.05),""),"") | AD46: =IFERROR(MAX(ROUNDDOWN((1.22/G46),0)*ROUNDDOWN((3.05/H46),0),ROUNDDOWN((1.22/H46),0)*ROUNDDOWN((3.05/G46),0)),"")
L47: =IFERROR(VLOOKUP(J47,articulo:clave_comercial,2,0)," ") | M47: =UPPER(IFERROR(VLOOKUP(J47,articulo:clave_comercial,5,0)," ")) | N47: =IFERROR(IF(VLOOKUP(J47,articulo:clave_comercial,8,0)=0," ",VLOOKUP(J47,articulo:clave_comercial,8,0))," ") | O47: =IFERROR(IF(VLOOKUP(J47,articulo:clave_comercial,9,0)=0," ",VLOOKUP(J47,articulo:clave_comercial,9,0))," ") | P47: =IFERROR(IF(M47="HOJA",(D47*F47)/MAX(ROUNDDOWN((N47/G47),0)*ROUNDDOWN((O47/H47),0),ROUNDDOWN((N47/H47),0)*ROUNDDOWN((O47/G47),0)),IF(M47="HOJA ",(D47*F47)/MAX(ROUNDDOWN((N47/G47),0)*ROUNDDOWN((O47/H47),0),ROUNDDOWN((N47/H47),0)*ROUNDDOWN((O47/G47),0)),IF(M47="M",G47,IF(AND(M47="PIEZA",G47<>0),(D47*F47)/ROUNDDOWN((N47/G47),0),IF(M47="PIEZA",(D47*F47),IF(M47="CAJA",(D47*F47),IF(M47="DM2",(D47*F47),IF(M47="FT",(D47*F47),IF(M47="JGO",(D47*F47),IF(M47="KG",(D47*F47),IF(M47="LB",(D47*F47),IF(M47="LT",(D47*F47),IF(M47="M2",(D47*F47),IF(M47="M3",(D47*F47),IF(M47="ROLLO",(D47*F47),IF(M47="SQYDS",(D47*F47),IF(M47="UD./SERV.",(D47*F47),IF(M47="YD",(D47*F47)," ")))))))))))))))))),"") | Q47: =IFERROR(IF(M47="HOJA",D47*F47*G47*H47*2*0.125,IF(AND(M47="PIEZA",H47=0),D47*F47*G47*VLOOKUP(J47,articulo:clave_comercial,10,0)*0.125,0))," ") -> 0 | S47: {=IFERROR(INDEX($J$3:$J$52,MATCH(0,INDEX(COUNTIF(S$2:$S46,$J$3:$J$52),0,0),0))," ")} | T47: {=IFERROR(INDEX($L$3:$L$52,MATCH(0,INDEX(COUNTIF($T$2:T46,$L$3:$L$52),0,0),0))," ")} | U47: =IFERROR(IF(AND(VLOOKUP(S47,$J$3:$Q$218,4,0)="KG",VLOOKUP(S47,$J$3:$Q$218,7,0)=0,VLOOKUP(S47,$J$3:$Q$218,8,0)=0),SUM($Q$3:$Q$218),SUMIF($J$3:$J$218,S47,$P$3:$P$218)),"") | W47: =IFERROR(IF(OR(M47="HOJA",M47="HOJA "),((MAX(ROUNDDOWN((0.915/G47),0)*ROUNDDOWN((2.44/H47),0),ROUNDDOWN((0.915/H47),0)*ROUNDDOWN((2.44/G47),0)))*G47*H47)/(0.915*2.44),""),"") | X47: =IFERROR(MAX(ROUNDDOWN((0.915/G47),0)*ROUNDDOWN((2.44/H47),0),ROUNDDOWN((0.915/H47),0)*ROUNDDOWN((2.44/G47),0)),"") | Y47: =IFERROR(IF(OR(M47="HOJA",M47="HOJA "),((MAX(ROUNDDOWN((0.915/G47),0)*ROUNDDOWN((3.05/H47),0),ROUNDDOWN((0.915/H47),0)*ROUNDDOWN((3.05/G47),0)))*G47*H47)/(0.915*3.05),""),"") | Z47: =IFERROR(MAX(ROUNDDOWN((0.915/G47),0)*ROUNDDOWN((3.05/H47),0),ROUNDDOWN((0.915/H47),0)*ROUNDDOWN((3.05/G47),0)),"") | AA47: =IFERROR(IF(OR(M47="HOJA",M47="HOJA "),((MAX(ROUNDDOWN((1.22/G47),0)*ROUNDDOWN((2.44/H47),0),ROUNDDOWN((1.22/H47),0)*ROUNDDOWN((2.44/G47),0)))*G47*H47)/(1.22*2.44),""),"") | AB47: =IFERROR(MAX(ROUNDDOWN((1.22/G47),0)*ROUNDDOWN((2.44/H47),0),ROUNDDOWN((1.22/H47),0)*ROUNDDOWN((2.44/G47),0)),"") | AC47: =IFERROR(IF(OR(M47="HOJA",M47="HOJA "),((MAX(ROUNDDOWN((1.22/G47),0)*ROUNDDOWN((3.05/H47),0),ROUNDDOWN((1.22/H47),0)*ROUNDDOWN((3.05/G47),0)))*G47*H47)/(1.22*3.05),""),"") | AD47: =IFERROR(MAX(ROUNDDOWN((1.22/G47),0)*ROUNDDOWN((3.05/H47),0),ROUNDDOWN((1.22/H47),0)*ROUNDDOWN((3.05/G47),0)),"")
